Workbook

Sheet Lisez-moi
A1: MON HEROS — Systeme de jeu (maths) v1.0
A2: Classeur de game design pour l'app get-fit. Toute la balance du RPG dans un seul fichier.
A5: PRINCIPE DIRECTEUR
A6: 1. L'entrainement est le moteur. | B6: On peut atteindre le niveau max sans jamais logger un repas.
A7: 2. La nutrition est un accelerateur. | B7: Elle multiplie l'XP gagne et augmente la Chance. Elle ne debloque rien d'exclusif.
A8: 3. La penalite est douce et reversible. | B8: Le Moral baisse, jamais le niveau. Aucune perte d'objet ni de progres acquis.
A9: 4. Le donjon porte la boucle courte. | B9: Il tourne tout seul, donne du loot chaque jour, et se durcit a chaque cycle.
A10: 5. Le rythme est cale sur la vraie vie. | B10: Tout est dimensionne pour 4 seances/semaine. Pas de farm possible sans entrainement reel.
A12: COMMENT LIRE CE CLASSEUR
A13: Cellules JAUNES avec texte BLEU | B13: -> leviers a ajuster. Ce sont les seules cellules a modifier.
A14: Texte NOIR | B14: -> formule calculee. Ne pas ecraser.
A15: Texte VERT | B15: -> lien vers un autre onglet.
A17: ONGLETS
A18: Parametres | B18: Tous les leviers du jeu au meme endroit. Point de depart de chaque ajustement.
A19: Progression | B19: Courbe XP niveau 1 a 50, stats du personnage, gemmes, temps reel estime.
A20: XP Seance | B20: Comment une vraie seance se convertit en XP. Exemples chiffres.
A21: Nutrition-Moral | B21: Score nutritionnel quotidien, multiplicateur XP, systeme de Moral et penalites.
A22: Donjon | B22: PV/ATQ des ennemis par palier et par cycle, boss, or et essence largues.
A23: Sim Combat | B23: Resout un combat joueur vs palier. Sert a verifier qu'un niveau donne passe ou casse.
A24: Equipement | B24: 6 emplacements, 5 raretes, puissance des objets, couts de forge.
A25: Loot-Pity | B25: Taux de drop, effet de la Chance, systeme anti-malchance (pity doux + dur).
A26: Economie | B26: Revenus et depenses des 3 monnaies : Or, Essence, Gemmes.
A27: Sim 52 semaines | B27: Projection an 1 : niveau, cycle de donjon, monnaies, semaine par semaine.
A29: SOURCES CONSULTEES POUR LA BALANCE
A30: Courbe XP polynomiale, exposant 1,5-2,2 | B30: jaconir.online — RPG XP Curves Explained (exposant >2,5 = mur infranchissable)
A31: Soft cap apres un niveau palier | B31: meme source — evite le mur de fin de partie
A32: Ennemi ~2x le joueur, boss ~5x PV | B32: forums.rpgmakerweb.com — Balancing enemy stats, gold, exp
A33: Plafonner le pire cas de malchance (pity) | B33: gamedeveloper.com — Emotions and Randomness: Loot Drops
A34: Pity dur type Granblue/Genshin | B34: arxiv.org 2208.03602 — Gacha Game: Prospect Theory Meets Optimal Pricing
A35: Reussite le jour 1 = +64% de retention | B35: guul.games / donnees plateforme Trophy — gamification fitness
A36: Streaks = mecanique de retention #1 | B36: trophy.so — etude de cas Streaks
A37: Rendements decroissants sur stats tardives | B37: gamescrye.com — 5 Tips for Balancing an RPG Game
A39: AVERTISSEMENT
A40: Je suis un assistant IA, pas un professionnel de la sante. | B40: Consulte ton medecin de famille avant d'entreprendre un nouveau regime.
A42: RESULTAT DE LA BALANCE (rythme 4 seances/semaine)
A43: Niveau 5 | B43: 1 semaine — l'accroche : une victoire des la premiere semaine.
A44: Niveau 10 | B44: 1,7 mois — le donjon tourne, l'equipement commence a compter.
A45: Niveau 20 | B45: 10 mois — cycle 8 du donjon, epique bien forge.
A46: Niveau 25 | B46: 1 an et demi — soft cap, la courbe s'aplatit.
A47: Niveau 50 | B47: horizon pluriannuel, volontairement. C'est une app de vie, pas une saison.
A48: Boss du donjon | B48: ~10 a 15 tours a niveau approprie ; il porte a lui seul la moitie des degats subis.
A49: Run reussie type | B49: se termine avec 5 a 25% des PV. Serree par design.
A50: Legendaire garanti | B50: au 60e objet largue, soit ~3 semaines dans le pire des cas.
A51: Forge complete d'un objet | B51: ~140 gemmes = environ un an d'entrainement reel. Un seul objet par an.
A52: Gain max de la nutrition | B52: +25% d'XP et +30 de Chance. Reel, jamais obligatoire.
A53: Penalite max du moral | B53: -15% d'XP. Efface en deux bonnes journees.
A55: CE QUI EST IMPOSSIBLE PAR DESIGN
A56: Farmer sa sortie d'un mur | B56: Le niveau plafonne tout. Le niveau n'existe que par l'entrainement reel.
A57: Acheter de la puissance | B57: Les gemmes ne viennent que des montees de niveau.
A58: Perdre du progres acquis | B58: Le moral baisse ; le niveau, les objets et les monnaies ne baissent jamais.
A59: Etre puni de ne pas logger sa nutrition | B59: Ne rien logger est strictement neutre.

Sheet Parametres
A1: PARAMETRES — tous les leviers du jeu
A2: Modifie uniquement les cellules jaunes. Tout le reste du classeur s'ajuste automatiquement.
A4: XP & COURBE DE NIVEAU
A5: XP de base par seance | B5: 50 | C5: XP | D5: Recompense de presence : tu t'es rendu au gym.
A6: Diviseur de volume | B6: 200 | C6: lb/XP | D6: Volume total (poids x reps x series) divise par ce chiffre.
A7: Bonus par record personnel (PR) | B7: 25 | C7: XP | D7: Recompense le progres reel, pas juste la repetition.
A8: Coefficient courbe XP | B8: 50 | D8: XP requis = coeff x niveau^exposant
A9: Exposant courbe XP | B9: 1.5 | D9: 1,5 = standard RPG. >2,5 cree un mur (source: jaconir).
A10: Niveau du soft cap | B10: 25 | C10: niv | D10: Au-dela, la courbe devient lineaire au lieu d'exploser.
A11: Increment lineaire apres soft cap | B11: 200 | C11: XP | D11: Cout ajoute par niveau apres le soft cap. Bas volontairement : le niv. 50 doit rester atteignable.
A12: Niveau maximum | B12: 50 | C12: niv | D12: Horizon long terme volontairement pluriannuel.
A14: STATS DU PERSONNAGE
A15: PV de base | B15: 100 | C15: PV | D15: Niveau 1.
A16: PV par niveau | B16: 35 | C16: PV | D16: Croissance lineaire = previsible. Calibre pour survivre a une run complete.
A17: ATQ de base | B17: 10 | C17: ATQ
A18: ATQ par niveau | B18: 6 | C18: ATQ | D18: Calibre pour tuer le boss en ~12 tours a niveau approprie.
A19: DEF de base | B19: 5 | C19: DEF
A20: DEF par niveau | B20: 2.5 | C20: DEF
A21: Critique de base | B21: 0.05 | C21: % | D21: 5% au niveau 1.
A22: Gain de critique maximal | B22: 0.15 | C22: % | D22: Plafond du gain lie au niveau : +15 points max.
A23: Constante K du critique | B23: 20 | D23: crit = base + max x niv/(niv+K). Rendements decroissants.
A24: Multiplicateur de coup critique | B24: 1.75 | C24: x
A25: Constante d'armure | B25: 80 | D25: reduction = DEF/(DEF+K). Jamais de degats negatifs, rendements decroissants.
A26: Regeneration entre paliers | B26: 0.25 | C26: % PV max | D26: % des PV max recuperes apres chaque palier. Calibre pour que le BOSS soit le vrai combat.
A27: NUTRITION
A28: Bonus XP — calories dans la cible | B28: 0.05 | C28: % | D28: Cible +/- 10%. Independant des 2 autres.
A29: Bonus XP — proteines atteintes | B29: 0.08 | C29: % | D29: Au moins 90% de la cible. Le plus eleve : coherent avec un style riche en proteines.
A30: Bonus XP — eau atteinte | B30: 0.04 | C30: % | D30: Au moins 90% de la cible.
A31: Bonus XP par jour de serie (2+ cibles) | B31: 0.01 | C31: % | D31: Un jour compte pour la serie des que 2 des 3 cibles sont atteintes.
A32: Bonus XP de serie — maximum | B32: 0.15 | C32: % | D32: Plafond a 15 jours de serie consecutifs (2+ cibles/jour).
A33: Chance par jour de serie nutri | B33: 2 | C33: pts | D33: Meme compteur de serie que le bonus XP.
A34: Chance maximale (nutrition) | B34: 30 | C34: pts | D34: Plafond a 15 jours (meme fenetre que le bonus XP).
A35: Bonus XP par jour de serie | B35: 0.01 | C35: % | D35: S'accumule tant que les jours 'reussis' s'enchainent.
A36: MORAL & PENALITES | B36: 0.15 | C36: % | D36: Plafond a 15 jours de serie.
A37: Moral maximum | B37: 100 | C37: pts | D37: Depart a 100.
A38: Moral — seance loggee | B38: 8 | C38: pts
A39: Moral — seance prevue manquee | B39: -10 | C39: pts | D39: Seule source de penalite du jeu. La nutrition n'affecte jamais le moral.
A40: Multiplicateur XP a moral 0 | B40: 0.85 | C40: x | D40: Plancher : -15% max. Jamais de spirale.
A41: Seuil de moral plein | B41: 80 | C41: pts | D41: Au-dessus, aucun malus. Deux bonnes seances suffisent a y remonter.
A42: Moral — seance loggee | B42: 8 | C42: pts
A43: Moral — seance prevue manquee | B43: -10 | C43: pts | D43: Seule source de penalite. La nutrition n'affecte plus le moral.
A44: Multiplicateur XP a moral 0 | B44: 0.85 | C44: x | D44: Plancher : -15% max. Jamais de spirale.
A45: REGULARITE (STREAK D'ENTRAINEMENT) | B45: 80 | C45: pts | D45: Au-dessus, aucun malus.
A46: Objectif de seances par semaine | B46: 4 | C46: seances | D46: Base de tous les calculs de rythme.
A47: Bonus XP par semaine de streak | B47: 0.02 | C47: % | D47: Cumulatif.
A48: Bonus de streak maximal | B48: 0.2 | C48: % | D48: Plafond a 10 semaines consecutives.
A50: DONJON
A51: Paliers par cycle | B51: 10 | C51: paliers | D51: Le 10e est le boss.
A52: PV ennemi — base | B52: 50 | C52: PV | D52: Calibre : donjon ouvert des le niveau 6, boss abattu en ~10 tours a niveau approprie.
A53: PV ennemi — exposant palier | B53: 0.9 | D53: Exposant bas : les 10 paliers sont UNE run, pas 10 zones. C'est le CYCLE qui durcit.
A54: ATQ ennemi — base | B54: 10 | C54: ATQ
A55: ATQ ennemi — exposant palier | B55: 0.8
A56: DEF ennemi — base | B56: 4 | C56: DEF
A57: DEF ennemi — exposant palier | B57: 0.85
A58: Croissance par cycle | B58: 0.2 | C58: % | D58: 20% par cycle. C'est CE levier qui cree le mur et pousse a s'entrainer.
A59: Multiplicateur PV du boss | B59: 2.2 | C59: x | D59: Le boss porte a lui seul ~50% des degats subis d'une run.
A60: Multiplicateur ATQ du boss | B60: 1.5 | C60: x
A62: ECONOMIE — 3 MONNAIES
A63: Or par palier nettoye | B63: 10 | C63: or | D63: x palier. Monnaie commune, achete des coffres.
A64: Bonus d'or par cycle | B64: 0.1 | C64: %
A65: Essence par palier nettoye | B65: 1 | C65: ess | D65: Farmable. Achete de petites ameliorations de stats.
A66: Essence bonus du boss | B66: 5 | C66: ess
A67: Cout d'un coffre (or) | B67: 3000 | C67: or | D67: ~1 coffre/semaine. Il complete les drops, il ne les remplace pas.
A68: Cout amelioration stat (essence) | B68: 40 | C68: ess | D68: Cout de base d'une amelioration de stat en essence.
A69: Facteur de cout essence | B69: 1.35 | C69: x | D69: Cout x1,35 cumulatif : la 5e amelioration est rapide, la 20e est un objectif d'annee.
A70: Gemmes de base par niveau | B70: 3 | C70: gem | D70: SEULE source de gemmes = monter de niveau = vrai entrainement.
A71: Gemmes bonus par 5 niveaux | B71: 1 | C71: gem
A73: LOOT
A74: Chance de drop par palier | B74: 0.1 | C74: % | D74: Un objet tous les 10 paliers environ. Rare par design : l'inventaire doit avoir du poids.
A75: Poids — Commun | B75: 70 | D75: La matiere premiere de la fusion.
A76: Poids — Rare | B76: 22
A77: Poids — Ultra-rare | B77: 6.5
A78: Poids — Mythique | B78: 1.4 | D78: Un drop direct est un evenement.
A79: Poids — Legendaire | B79: 0.1 | D79: Drop direct quasi impossible : la fusion est le vrai chemin.
A80: Effet de la Chance | B80: 0.01 | D80: Chaque point de Chance ajoute 1% relatif aux raretes hautes.
A81: Debut du pity doux | B81: 40 | C81: drops | D81: Sans legendaire, les odds montent a partir d'ici.
A82: Increment du pity doux | B82: 0.03 | C82: % | D82: Par drop supplementaire.
A83: Pity dur (garantie legendaire) | B83: 60 | C83: drops | D83: Pire cas plafonne. Source: gamedeveloper.com.
A85: EQUIPEMENT
A86: Puissance de base d'un objet | B86: 6
A87: Puissance par palier de donjon | B87: 4 | D87: Le palier ou l'objet tombe determine sa puissance brute.
A88: Mult. rarete — Commun | B88: 1 | C88: x
A89: Mult. rarete — Rare | B89: 1.6 | C89: x
A90: Mult. rarete — Ultra-rare | B90: 2.6 | C90: x
A91: Mult. rarete — Mythique | B91: 4.2 | C91: x | D91: Progression ~x1,6 par palier de rarete.
A92: Mult. rarete — Legendaire | B92: 6.8 | C92: x
A93: Gain par niveau de forge | B93: 0.08 | C93: %
A94: Niveau de forge maximal | B94: 10 | C94: niv
A95: Cout de forge de base | B95: 5 | C95: gem
A96: Facteur de cout de forge | B96: 1.22 | C96: x | D96: Forge complete d'UN objet ~= 140 gemmes ~= un an d'entrainement. C'est le sommet de prestige.
A98: SEANCE DE REFERENCE (sert aux estimations de temps reel)
A99: Volume de reference par seance | B99: 20000 | C99: lb | D99: Ex.: 8 exercices x 4 series x 8 reps x ~78 lb moyen.
A100: PR moyens par seance | B100: 0.5 | C100: PR | D100: Un record personnel une seance sur deux au debut.
A101: Mult. nutrition moyen suppose | B101: 1.1 | C101: x | D101: Hypothese realiste : nutrition suivie ~2 jours sur 5.
A102: Mult. moral moyen suppose | B102: 0.98 | C102: x | D102: Quelques seances manquees par mois.
A103: Mult. streak moyen suppose | B103: 1.1 | C103: x | D103: Regularite correcte mais pas parfaite.
A104: XP moyen par seance (calcule) | B104: =ROUND((B5+B99/B6+B100*B7)*B101*B102*B103,0) -> 193 | C104: XP | D104: Base de toutes les estimations de duree du classeur.
A106: FUSION & VENTE D'EQUIPEMENT
A107: Objets requis par fusion | B107: 3 | C107: objets | D107: 3 objets identiques en rarete ET en emplacement = 1 objet de la rarete au-dessus.
A108: Emplacements du personnage | B108: 6 | C108: slots | D108: La fusion exige le meme emplacement : impossible de tout canaliser vers une seule piece.
...

Sheet Progression
A1: PROGRESSION — courbe XP, stats et temps reel estime
A2: XP requis = coefficient x niveau^exposant, puis lineaire apres le soft cap (evite le mur de fin de partie). Stats PV/ATQ/DEF lineaires = previsibles ; critique a rendements decroissants.
A4: Niveau | B4: XP requis (du niv. precedent) | C4: XP cumulatif | D4: PV | E4: ATQ | F4: DEF | G4: Critique | H4: Gemmes gagnees | I4: Gemmes cumulees | J4: Seances cumulees | K4: Semaines estimees | L4: Mois estimes | M4: Jalon
A5: 1 | B5: =IF(A5=1,0,IF(A5-1<=Parametres!$B$10,ROUND(Parametres!$B$8*(A5-1)^Parametres!$B$9,0),ROUND(Parametres!$B$8*Parametres!$B$10^Parametres!$B$9+Parametres!$B$11*(A5-1-Parametres!$B$10),0))) -> 0 | C5: =B5 -> 0 | D5: =Parametres!$B$15+Parametres!$B$16*(A5-1) -> 100 | E5: =Parametres!$B$17+Parametres!$B$18*(A5-1) -> 10 | F5: =Parametres!$B$19+Parametres!$B$20*(A5-1) -> 5 | G5: =Parametres!$B$21+Parametres!$B$22*(A5/(A5+Parametres!$B$23)) -> 0.057142857 | H5: =IF(A5=1,0,Parametres!$B$70+Parametres!$B$71*INT(A5/5)) -> 0 | I5: =H5 -> 0 | J5: =ROUND(C5/Parametres!$B$104,0) -> 0 | K5: =ROUND(J5/Parametres!$B$46,1) -> 0 | L5: =ROUND(K5/4.345,1) -> 0 | M5: Depart
A6: 2 | B6: =IF(A6=1,0,IF(A6-1<=Parametres!$B$10,ROUND(Parametres!$B$8*(A6-1)^Parametres!$B$9,0),ROUND(Parametres!$B$8*Parametres!$B$10^Parametres!$B$9+Parametres!$B$11*(A6-1-Parametres!$B$10),0))) -> 50 | C6: =C5+B6 -> 50 | D6: =Parametres!$B$15+Parametres!$B$16*(A6-1) -> 135 | E6: =Parametres!$B$17+Parametres!$B$18*(A6-1) -> 16 | F6: =Parametres!$B$19+Parametres!$B$20*(A6-1) -> 7.5 | G6: =Parametres!$B$21+Parametres!$B$22*(A6/(A6+Parametres!$B$23)) -> 0.063636364 | H6: =IF(A6=1,0,Parametres!$B$70+Parametres!$B$71*INT(A6/5)) -> 3 | I6: =I5+H6 -> 3 | J6: =ROUND(C6/Parametres!$B$104,0) -> 0 | K6: =ROUND(J6/Parametres!$B$46,1) -> 0 | L6: =ROUND(K6/4.345,1) -> 0
A7: 3 | B7: =IF(A7=1,0,IF(A7-1<=Parametres!$B$10,ROUND(Parametres!$B$8*(A7-1)^Parametres!$B$9,0),ROUND(Parametres!$B$8*Parametres!$B$10^Parametres!$B$9+Parametres!$B$11*(A7-1-Parametres!$B$10),0))) -> 141 | C7: =C6+B7 -> 191 | D7: =Parametres!$B$15+Parametres!$B$16*(A7-1) -> 170 | E7: =Parametres!$B$17+Parametres!$B$18*(A7-1) -> 22 | F7: =Parametres!$B$19+Parametres!$B$20*(A7-1) -> 10 | G7: =Parametres!$B$21+Parametres!$B$22*(A7/(A7+Parametres!$B$23)) -> 0.069565217 | H7: =IF(A7=1,0,Parametres!$B$70+Parametres!$B$71*INT(A7/5)) -> 3 | I7: =I6+H7 -> 6 | J7: =ROUND(C7/Parametres!$B$104,0) -> 1 | K7: =ROUND(J7/Parametres!$B$46,1) -> 0.3 | L7: =ROUND(K7/4.345,1) -> 0.1 | M7: Premier equipement
A8: 4 | B8: =IF(A8=1,0,IF(A8-1<=Parametres!$B$10,ROUND(Parametres!$B$8*(A8-1)^Parametres!$B$9,0),ROUND(Parametres!$B$8*Parametres!$B$10^Parametres!$B$9+Parametres!$B$11*(A8-1-Parametres!$B$10),0))) -> 260 | C8: =C7+B8 -> 451 | D8: =Parametres!$B$15+Parametres!$B$16*(A8-1) -> 205 | E8: =Parametres!$B$17+Parametres!$B$18*(A8-1) -> 28 | F8: =Parametres!$B$19+Parametres!$B$20*(A8-1) -> 12.5 | G8: =Parametres!$B$21+Parametres!$B$22*(A8/(A8+Parametres!$B$23)) -> 0.075 | H8: =IF(A8=1,0,Parametres!$B$70+Parametres!$B$71*INT(A8/5)) -> 3 | I8: =I7+H8 -> 9 | J8: =ROUND(C8/Parametres!$B$104,0) -> 2 | K8: =ROUND(J8/Parametres!$B$46,1) -> 0.5 | L8: =ROUND(K8/4.345,1) -> 0.1
A9: 5 | B9: =IF(A9=1,0,IF(A9-1<=Parametres!$B$10,ROUND(Parametres!$B$8*(A9-1)^Parametres!$B$9,0),ROUND(Parametres!$B$8*Parametres!$B$10^Parametres!$B$9+Parametres!$B$11*(A9-1-Parametres!$B$10),0))) -> 400 | C9: =C8+B9 -> 851 | D9: =Parametres!$B$15+Parametres!$B$16*(A9-1) -> 240 | E9: =Parametres!$B$17+Parametres!$B$18*(A9-1) -> 34 | F9: =Parametres!$B$19+Parametres!$B$20*(A9-1) -> 15 | G9: =Parametres!$B$21+Parametres!$B$22*(A9/(A9+Parametres!$B$23)) -> 0.08 | H9: =IF(A9=1,0,Parametres!$B$70+Parametres!$B$71*INT(A9/5)) -> 4 | I9: =I8+H9 -> 13 | J9: =ROUND(C9/Parametres!$B$104,0) -> 4 | K9: =ROUND(J9/Parametres!$B$46,1) -> 1 | L9: =ROUND(K9/4.345,1) -> 0.2 | M9: Donjon debloque
A10: 6 | B10: =IF(A10=1,0,IF(A10-1<=Parametres!$B$10,ROUND(Parametres!$B$8*(A10-1)^Parametres!$B$9,0),ROUND(Parametres!$B$8*Parametres!$B$10^Parametres!$B$9+Parametres!$B$11*(A10-1-Parametres!$B$10),0))) -> 559 | C10: =C9+B10 -> 1410 | D10: =Parametres!$B$15+Parametres!$B$16*(A10-1) -> 275 | E10: =Parametres!$B$17+Parametres!$B$18*(A10-1) -> 40 | F10: =Parametres!$B$19+Parametres!$B$20*(A10-1) -> 17.5 | G10: =Parametres!$B$21+Parametres!$B$22*(A10/(A10+Parametres!$B$23)) -> 0.084615385 | H10: =IF(A10=1,0,Parametres!$B$70+Parametres!$B$71*INT(A10/5)) -> 4 | I10: =I9+H10 -> 17 | J10: =ROUND(C10/Parametres!$B$104,0) -> 7 | K10: =ROUND(J10/Parametres!$B$46,1) -> 1.8 | L10: =ROUND(K10/4.345,1) -> 0.4
A11: 7 | B11: =IF(A11=1,0,IF(A11-1<=Parametres!$B$10,ROUND(Parametres!$B$8*(A11-1)^Parametres!$B$9,0),ROUND(Parametres!$B$8*Parametres!$B$10^Parametres!$B$9+Parametres!$B$11*(A11-1-Parametres!$B$10),0))) -> 735 | C11: =C10+B11 -> 2145 | D11: =Parametres!$B$15+Parametres!$B$16*(A11-1) -> 310 | E11: =Parametres!$B$17+Parametres!$B$18*(A11-1) -> 46 | F11: =Parametres!$B$19+Parametres!$B$20*(A11-1) -> 20 | G11: =Parametres!$B$21+Parametres!$B$22*(A11/(A11+Parametres!$B$23)) -> 0.088888889 | H11: =IF(A11=1,0,Parametres!$B$70+Parametres!$B$71*INT(A11/5)) -> 4 | I11: =I10+H11 -> 21 | J11: =ROUND(C11/Parametres!$B$104,0) -> 11 | K11: =ROUND(J11/Parametres!$B$46,1) -> 2.8 | L11: =ROUND(K11/4.345,1) -> 0.6
A12: 8 | B12: =IF(A12=1,0,IF(A12-1<=Parametres!$B$10,ROUND(Parametres!$B$8*(A12-1)^Parametres!$B$9,0),ROUND(Parametres!$B$8*Parametres!$B$10^Parametres!$B$9+Parametres!$B$11*(A12-1-Parametres!$B$10),0))) -> 926 | C12: =C11+B12 -> 3071 | D12: =Parametres!$B$15+Parametres!$B$16*(A12-1) -> 345 | E12: =Parametres!$B$17+Parametres!$B$18*(A12-1) -> 52 | F12: =Parametres!$B$19+Parametres!$B$20*(A12-1) -> 22.5 | G12: =Parametres!$B$21+Parametres!$B$22*(A12/(A12+Parametres!$B$23)) -> 0.092857143 | H12: =IF(A12=1,0,Parametres!$B$70+Parametres!$B$71*INT(A12/5)) -> 4 | I12: =I11+H12 -> 25 | J12: =ROUND(C12/Parametres!$B$104,0) -> 16 | K12: =ROUND(J12/Parametres!$B$46,1) -> 4 | L12: =ROUND(K12/4.345,1) -> 0.9
A13: 9 | B13: =IF(A13=1,0,IF(A13-1<=Parametres!$B$10,ROUND(Parametres!$B$8*(A13-1)^Parametres!$B$9,0),ROUND(Parametres!$B$8*Parametres!$B$10^Parametres!$B$9+Parametres!$B$11*(A13-1-Parametres!$B$10),0))) -> 1131 | C13: =C12+B13 -> 4202 | D13: =Parametres!$B$15+Parametres!$B$16*(A13-1) -> 380 | E13: =Parametres!$B$17+Parametres!$B$18*(A13-1) -> 58 | F13: =Parametres!$B$19+Parametres!$B$20*(A13-1) -> 25 | G13: =Parametres!$B$21+Parametres!$B$22*(A13/(A13+Parametres!$B$23)) -> 0.096551724 | H13: =IF(A13=1,0,Parametres!$B$70+Parametres!$B$71*INT(A13/5)) -> 4 | I13: =I12+H13 -> 29 | J13: =ROUND(C13/Parametres!$B$104,0) -> 22 | K13: =ROUND(J13/Parametres!$B$46,1) -> 5.5 | L13: =ROUND(K13/4.345,1) -> 1.3
A14: 10 | B14: =IF(A14=1,0,IF(A14-1<=Parametres!$B$10,ROUND(Parametres!$B$8*(A14-1)^Parametres!$B$9,0),ROUND(Parametres!$B$8*Parametres!$B$10^Parametres!$B$9+Parametres!$B$11*(A14-1-Parametres!$B$10),0))) -> 1350 | C14: =C13+B14 -> 5552 | D14: =Parametres!$B$15+Parametres!$B$16*(A14-1) -> 415 | E14: =Parametres!$B$17+Parametres!$B$18*(A14-1) -> 64 | F14: =Parametres!$B$19+Parametres!$B$20*(A14-1) -> 27.5 | G14: =Parametres!$B$21+Parametres!$B$22*(A14/(A14+Parametres!$B$23)) -> 0.1 | H14: =IF(A14=1,0,Parametres!$B$70+Parametres!$B$71*INT(A14/5)) -> 5 | I14: =I13+H14 -> 34 | J14: =ROUND(C14/Parametres!$B$104,0) -> 29 | K14: =ROUND(J14/Parametres!$B$46,1) -> 7.3 | L14: =ROUND(K14/4.345,1) -> 1.7 | M14: Cycle 2 accessible
A15: 11 | B15: =IF(A15=1,0,IF(A15-1<=Parametres!$B$10,ROUND(Parametres!$B$8*(A15-1)^Parametres!$B$9,0),ROUND(Parametres!$B$8*Parametres!$B$10^Parametres!$B$9+Parametres!$B$11*(A15-1-Parametres!$B$10),0))) -> 1581 | C15: =C14+B15 -> 7133 | D15: =Parametres!$B$15+Parametres!$B$16*(A15-1) -> 450 | E15: =Parametres!$B$17+Parametres!$B$18*(A15-1) -> 70 | F15: =Parametres!$B$19+Parametres!$B$20*(A15-1) -> 30 | G15: =Parametres!$B$21+Parametres!$B$22*(A15/(A15+Parametres!$B$23)) -> 0.10322581 | H15: =IF(A15=1,0,Parametres!$B$70+Parametres!$B$71*INT(A15/5)) -> 5 | I15: =I14+H15 -> 39 | J15: =ROUND(C15/Parametres!$B$104,0) -> 37 | K15: =ROUND(J15/Parametres!$B$46,1) -> 9.3 | L15: =ROUND(K15/4.345,1) -> 2.1
A16: 12 | B16: =IF(A16=1,0,IF(A16-1<=Parametres!$B$10,ROUND(Parametres!$B$8*(A16-1)^Parametres!$B$9,0),ROUND(Parametres!$B$8*Parametres!$B$10^Parametres!$B$9+Parametres!$B$11*(A16-1-Parametres!$B$10),0))) -> 1824 | C16: =C15+B16 -> 8957 | D16: =Parametres!$B$15+Parametres!$B$16*(A16-1) -> 485 | E16: =Parametres!$B$17+Parametres!$B$18*(A16-1) -> 76 | F16: =Parametres!$B$19+Parametres!$B$20*(A16-1) -> 32.5 | G16: =Parametres!$B$21+Parametres!$B$22*(A16/(A16+Parametres!$B$23)) -> 0.10625 | H16: =IF(A16=1,0,Parametres!$B$70+Parametres!$B$71*INT(A16/5)) -> 5 | I16: =I15+H16 -> 44 | J16: =ROUND(C16/Parametres!$B$104,0) -> 46 | K16: =ROUND(J16/Parametres!$B$46,1) -> 11.5 | L16: =ROUND(K16/4.345,1) -> 2.6
A17: 13 | B17: =IF(A17=1,0,IF(A17-1<=Parametres!$B$10,ROUND(Parametres!$B$8*(A17-1)^Parametres!$B$9,0),ROUND(Parametres!$B$8*Parametres!$B$10^Parametres!$B$9+Parametres!$B$11*(A17-1-Parametres!$B$10),0))) -> 2078 | C17: =C16+B17 -> 11035 | D17: =Parametres!$B$15+Parametres!$B$16*(A17-1) -> 520 | E17: =Parametres!$B$17+Parametres!$B$18*(A17-1) -> 82 | F17: =Parametres!$B$19+Parametres!$B$20*(A17-1) -> 35 | G17: =Parametres!$B$21+Parametres!$B$22*(A17/(A17+Parametres!$B$23)) -> 0.10909091 | H17: =IF(A17=1,0,Parametres!$B$70+Parametres!$B$71*INT(A17/5)) -> 5 | I17: =I16+H17 -> 49 | J17: =ROUND(C17/Parametres!$B$104,0) -> 57 | K17: =ROUND(J17/Parametres!$B$46,1) -> 14.3 | L17: =ROUND(K17/4.345,1) -> 3.3
A18: 14 | B18: =IF(A18=1,0,IF(A18-1<=Parametres!$B$10,ROUND(Parametres!$B$8*(A18-1)^Parametres!$B$9,0),ROUND(Parametres!$B$8*Parametres!$B$10^Parametres!$B$9+Parametres!$B$11*(A18-1-Parametres!$B$10),0))) -> 2344 | C18: =C17+B18 -> 13379 | D18: =Parametres!$B$15+Parametres!$B$16*(A18-1) -> 555 | E18: =Parametres!$B$17+Parametres!$B$18*(A18-1) -> 88 | F18: =Parametres!$B$19+Parametres!$B$20*(A18-1) -> 37.5 | G18: =Parametres!$B$21+Parametres!$B$22*(A18/(A18+Parametres!$B$23)) -> 0.11176471 | H18: =IF(A18=1,0,Parametres!$B$70+Parametres!$B$71*INT(A18/5)) -> 5 | I18: =I17+H18 -> 54 | J18: =ROUND(C18/Parametres!$B$104,0) -> 69 | K18: =ROUND(J18/Parametres!$B$46,1) -> 17.3 | L18: =ROUND(K18/4.345,1) -> 4
A19: 15 | B19: =IF(A19=1,0,IF(A19-1<=Parametres!$B$10,ROUND(Parametres!$B$8*(A19-1)^Parametres!$B$9,0),ROUND(Parametres!$B$8*Parametres!$B$10^Parametres!$B$9+Parametres!$B$11*(A19-1-Parametres!$B$10),0))) -> 2619 | C19: =C18+B19 -> 15998 | D19: =Parametres!$B$15+Parametres!$B$16*(A19-1) -> 590 | E19: =Parametres!$B$17+Parametres!$B$18*(A19-1) -> 94 | F19: =Parametres!$B$19+Parametres!$B$20*(A19-1) -> 40 | G19: =Parametres!$B$21+Parametres!$B$22*(A19/(A19+Parametres!$B$23)) -> 0.11428571 | H19: =IF(A19=1,0,Parametres!$B$70+Parametres!$B$71*INT(A19/5)) -> 6 | I19: =I18+H19 -> 60 | J19: =ROUND(C19/Parametres!$B$104,0) -> 83 | K19: =ROUND(J19/Parametres!$B$46,1) -> 20.8 | L19: =ROUND(K19/4.345,1) -> 4.8 | M19: Coffres legendaires viables
A20: 16 | B20: =IF(A20=1,0,IF(A20-1<=Parametres!$B$10,ROUND(Parametres!$B$8*(A20-1)^Parametres!$B$9,0),ROUND(Parametres!$B$8*Parametres!$B$10^Parametres!$B$9+Parametres!$B$11*(A20-1-Parametres!$B$10),0))) -> 2905 | C20: =C19+B20 -> 18903 | D20: =Parametres!$B$15+Parametres!$B$16*(A20-1) -> 625 | E20: =Parametres!$B$17+Parametres!$B$18*(A20-1) -> 100 | F20: =Parametres!$B$19+Parametres!$B$20*(A20-1) -> 42.5 | G20: =Parametres!$B$21+Parametres!$B$22*(A20/(A20+Parametres!$B$23)) -> 0.11666667 | H20: =IF(A20=1,0,Parametres!$B$70+Parametres!$B$71*INT(A20/5)) -> 6 | I20: =I19+H20 -> 66 | J20: =ROUND(C20/Parametres!$B$104,0) -> 98 | K20: =ROUND(J20/Parametres!$B$46,1) -> 24.5 | L20: =ROUND(K20/4.345,1) -> 5.6
A21: 17 | B21: =IF(A21=1,0,IF(A21-1<=Parametres!$B$10,ROUND(Parametres!$B$8*(A21-1)^Parametres!$B$9,0),ROUND(Parametres!$B$8*Parametres!$B$10^Parametres!$B$9+Parametres!$B$11*(A21-1-Parametres!$B$10),0))) -> 3200 | C21: =C20+B21 -> 22103 | D21: =Parametres!$B$15+Parametres!$B$16*(A21-1) -> 660 | E21: =Parametres!$B$17+Parametres!$B$18*(A21-1) -> 106 | F21: =Parametres!$B$19+Parametres!$B$20*(A21-1) -> 45 | G21: =Parametres!$B$21+Parametres!$B$22*(A21/(A21+Parametres!$B$23)) -> 0.11891892 | H21: =IF(A21=1,0,Parametres!$B$70+Parametres!$B$71*INT(A21/5)) -> 6 | I21: =I20+H21 -> 72 | J21: =ROUND(C21/Parametres!$B$104,0) -> 115 | K21: =ROUND(J21/Parametres!$B$46,1) -> 28.8 | L21: =ROUND(K21/4.345,1) -> 6.6
A22: 18 | B22: =IF(A22=1,0,IF(A22-1<=Parametres!$B$10,ROUND(Parametres!$B$8*(A22-1)^Parametres!$B$9,0),ROUND(Parametres!$B$8*Parametres!$B$10^Parametres!$B$9+Parametres!$B$11*(A22-1-Parametres!$B$10),0))) -> 3505 | C22: =C21+B22 -> 25608 | D22: =Parametres!$B$15+Parametres!$B$16*(A22-1) -> 695 | E22: =Parametres!$B$17+Parametres!$B$18*(A22-1) -> 112 | F22: =Parametres!$B$19+Parametres!$B$20*(A22-1) -> 47.5 | G22: =Parametres!$B$21+Parametres!$B$22*(A22/(A22+Parametres!$B$23)) -> 0.12105263 | H22: =IF(A22=1,0,Parametres!$B$70+Parametres!$B$71*INT(A22/5)) -> 6 | I22: =I21+H22 -> 78 | J22: =ROUND(C22/Parametres!$B$104,0) -> 133 | K22: =ROUND(J22/Parametres!$B$46,1) -> 33.3 | L22: =ROUND(K22/4.345,1) -> 7.7
A23: 19 | B23: =IF(A23=1,0,IF(A23-1<=Parametres!$B$10,ROUND(Parametres!$B$8*(A23-1)^Parametres!$B$9,0),ROUND(Parametres!$B$8*Parametres!$B$10^Parametres!$B$9+Parametres!$B$11*(A23-1-Parametres!$B$10),0))) -> 3818 | C23: =C22+B23 -> 29426 | D23: =Parametres!$B$15+Parametres!$B$16*(A23-1) -> 730 | E23: =Parametres!$B$17+Parametres!$B$18*(A23-1) -> 118 | F23: =Parametres!$B$19+Parametres!$B$20*(A23-1) -> 50 | G23: =Parametres!$B$21+Parametres!$B$22*(A23/(A23+Parametres!$B$23)) -> 0.12307692 | H23: =IF(A23=1,0,Parametres!$B$70+Parametres!$B$71*INT(A23/5)) -> 6 | I23: =I22+H23 -> 84 | J23: =ROUND(C23/Parametres!$B$104,0) -> 152 | K23: =ROUND(J23/Parametres!$B$46,1) -> 38 | L23: =ROUND(K23/4.345,1) -> 8.7
A24: 20 | B24: =IF(A24=1,0,IF(A24-1<=Parametres!$B$10,ROUND(Parametres!$B$8*(A24-1)^Parametres!$B$9,0),ROUND(Parametres!$B$8*Parametres!$B$10^Parametres!$B$9+Parametres!$B$11*(A24-1-Parametres!$B$10),0))) -> 4141 | C24: =C23+B24 -> 33567 | D24: =Parametres!$B$15+Parametres!$B$16*(A24-1) -> 765 | E24: =Parametres!$B$17+Parametres!$B$18*(A24-1) -> 124 | F24: =Parametres!$B$19+Parametres!$B$20*(A24-1) -> 52.5 | G24: =Parametres!$B$21+Parametres!$B$22*(A24/(A24+Parametres!$B$23)) -> 0.125 | H24: =IF(A24=1,0,Parametres!$B$70+Parametres!$B$71*INT(A24/5)) -> 7 | I24: =I23+H24 -> 91 | J24: =ROUND(C24/Parametres!$B$104,0) -> 174 | K24: =ROUND(J24/Parametres!$B$46,1) -> 43.5 | L24: =ROUND(K24/4.345,1) -> 10
A25: 21 | B25: =IF(A25=1,0,IF(A25-1<=Parametres!$B$10,ROUND(Parametres!$B$8*(A25-1)^Parametres!$B$9,0),ROUND(Parametres!$B$8*Parametres!$B$10^Parametres!$B$9+Parametres!$B$11*(A25-1-Parametres!$B$10),0))) -> 4472 | C25: =C24+B25 -> 38039 | D25: =Parametres!$B$15+Parametres!$B$16*(A25-1) -> 800 | E25: =Parametres!$B$17+Parametres!$B$18*(A25-1) -> 130 | F25: =Parametres!$B$19+Parametres!$B$20*(A25-1) -> 55 | G25: =Parametres!$B$21+Parametres!$B$22*(A25/(A25+Parametres!$B$23)) -> 0.12682927 | H25: =IF(A25=1,0,Parametres!$B$70+Parametres!$B$71*INT(A25/5)) -> 7 | I25: =I24+H25 -> 98 | J25: =ROUND(C25/Parametres!$B$104,0) -> 197 | K25: =ROUND(J25/Parametres!$B$46,1) -> 49.3 | L25: =ROUND(K25/4.345,1) -> 11.3
A26: 22 | B26: =IF(A26=1,0,IF(A26-1<=Parametres!$B$10,ROUND(Parametres!$B$8*(A26-1)^Parametres!$B$9,0),ROUND(Parametres!$B$8*Parametres!$B$10^Parametres!$B$9+Parametres!$B$11*(A26-1-Parametres!$B$10),0))) -> 4812 | C26: =C25+B26 -> 42851 | D26: =Parametres!$B$15+Parametres!$B$16*(A26-1) -> 835 | E26: =Parametres!$B$17+Parametres!$B$18*(A26-1) -> 136 | F26: =Parametres!$B$19+Parametres!$B$20*(A26-1) -> 57.5 | G26: =Parametres!$B$21+Parametres!$B$22*(A26/(A26+Parametres!$B$23)) -> 0.12857143 | H26: =IF(A26=1,0,Parametres!$B$70+Parametres!$B$71*INT(A26/5)) -> 7 | I26: =I25+H26 -> 105 | J26: =ROUND(C26/Parametres!$B$104,0) -> 222 | K26: =ROUND(J26/Parametres!$B$46,1) -> 55.5 | L26: =ROUND(K26/4.345,1) -> 12.8
A27: 23 | B27: =IF(A27=1,0,IF(A27-1<=Parametres!$B$10,ROUND(Parametres!$B$8*(A27-1)^Parametres!$B$9,0),ROUND(Parametres!$B$8*Parametres!$B$10^Parametres!$B$9+Parametres!$B$11*(A27-1-Parametres!$B$10),0))) -> 5159 | C27: =C26+B27 -> 48010 | D27: =Parametres!$B$15+Parametres!$B$16*(A27-1) -> 870 | E27: =Parametres!$B$17+Parametres!$B$18*(A27-1) -> 142 | F27: =Parametres!$B$19+Parametres!$B$20*(A27-1) -> 60 | G27: =Parametres!$B$21+Parametres!$B$22*(A27/(A27+Parametres!$B$23)) -> 0.13023256 | H27: =IF(A27=1,0,Parametres!$B$70+Parametres!$B$71*INT(A27/5)) -> 7 | I27: =I26+H27 -> 112 | J27: =ROUND(C27/Parametres!$B$104,0) -> 249 | K27: =ROUND(J27/Parametres!$B$46,1) -> 62.3 | L27: =ROUND(K27/4.345,1) -> 14.3
A28: 24 | B28: =IF(A28=1,0,IF(A28-1<=Parametres!$B$10,ROUND(Parametres!$B$8*(A28-1)^Parametres!$B$9,0),ROUND(Parametres!$B$8*Parametres!$B$10^Parametres!$B$9+Parametres!$B$11*(A28-1-Parametres!$B$10),0))) -> 5515 | C28: =C27+B28 -> 53525 | D28: =Parametres!$B$15+Parametres!$B$16*(A28-1) -> 905 | E28: =Parametres!$B$17+Parametres!$B$18*(A28-1) -> 148 | F28: =Parametres!$B$19+Parametres!$B$20*(A28-1) -> 62.5 | G28: =Parametres!$B$21+Parametres!$B$22*(A28/(A28+Parametres!$B$23)) -> 0.13181818 | H28: =IF(A28=1,0,Parametres!$B$70+Parametres!$B$71*INT(A28/5)) -> 7 | I28: =I27+H28 -> 119 | J28: =ROUND(C28/Parametres!$B$104,0) -> 277 | K28: =ROUND(J28/Parametres!$B$46,1) -> 69.3 | L28: =ROUND(K28/4.345,1) -> 15.9
A29: 25 | B29: =IF(A29=1,0,IF(A29-1<=Parametres!$B$10,ROUND(Parametres!$B$8*(A29-1)^Parametres!$B$9,0),ROUND(Parametres!$B$8*Parametres!$B$10^Parametres!$B$9+Parametres!$B$11*(A29-1-Parametres!$B$10),0))) -> 5879 | C29: =C28+B29 -> 59404 | D29: =Parametres!$B$15+Parametres!$B$16*(A29-1) -> 940 | E29: =Parametres!$B$17+Parametres!$B$18*(A29-1) -> 154 | F29: =Parametres!$B$19+Parametres!$B$20*(A29-1) -> 65 | G29: =Parametres!$B$21+Parametres!$B$22*(A29/(A29+Parametres!$B$23)) -> 0.13333333 | H29: =IF(A29=1,0,Parametres!$B$70+Parametres!$B$71*INT(A29/5)) -> 8 | I29: =I28+H29 -> 127 | J29: =ROUND(C29/Parametres!$B$104,0) -> 308 | K29: =ROUND(J29/Parametres!$B$46,1) -> 77 | L29: =ROUND(K29/4.345,1) -> 17.7 | M29: Soft cap — la courbe s'aplatit
A30: 26 | B30: =IF(A30=1,0,IF(A30-1<=Parametres!$B$10,ROUND(Parametres!$B$8*(A30-1)^Parametres!$B$9,0),ROUND(Parametres!$B$8*Parametres!$B$10^Parametres!$B$9+Parametres!$B$11*(A30-1-Parametres!$B$10),0))) -> 6250 | C30: =C29+B30 -> 65654 | D30: =Parametres!$B$15+Parametres!$B$16*(A30-1) -> 975 | E30: =Parametres!$B$17+Parametres!$B$18*(A30-1) -> 160 | F30: =Parametres!$B$19+Parametres!$B$20*(A30-1) -> 67.5 | G30: =Parametres!$B$21+Parametres!$B$22*(A30/(A30+Parametres!$B$23)) -> 0.13478261 | H30: =IF(A30=1,0,Parametres!$B$70+Parametres!$B$71*INT(A30/5)) -> 8 | I30: =I29+H30 -> 135 | J30: =ROUND(C30/Parametres!$B$104,0) -> 340 | K30: =ROUND(J30/Parametres!$B$46,1) -> 85 | L30: =ROUND(K30/4.345,1) -> 19.6
A31: 27 | B31: =IF(A31=1,0,IF(A31-1<=Parametres!$B$10,ROUND(Parametres!$B$8*(A31-1)^Parametres!$B$9,0),ROUND(Parametres!$B$8*Parametres!$B$10^Parametres!$B$9+Parametres!$B$11*(A31-1-Parametres!$B$10),0))) -> 6450 | C31: =C30+B31 -> 72104 | D31: =Parametres!$B$15+Parametres!$B$16*(A31-1) -> 1010 | E31: =Parametres!$B$17+Parametres!$B$18*(A31-1) -> 166 | F31: =Parametres!$B$19+Parametres!$B$20*(A31-1) -> 70 | G31: =Parametres!$B$21+Parametres!$B$22*(A31/(A31+Parametres!$B$23)) -> 0.13617021 | H31: =IF(A31=1,0,Parametres!$B$70+Parametres!$B$71*INT(A31/5)) -> 8 | I31: =I30+H31 -> 143 | J31: =ROUND(C31/Parametres!$B$104,0) -> 374 | K31: =ROUND(J31/Parametres!$B$46,1) -> 93.5 | L31: =ROUND(K31/4.345,1) -> 21.5
A32: 28 | B32: =IF(A32=1,0,IF(A32-1<=Parametres!$B$10,ROUND(Parametres!$B$8*(A32-1)^Parametres!$B$9,0),ROUND(Parametres!$B$8*Parametres!$B$10^Parametres!$B$9+Parametres!$B$11*(A32-1-Parametres!$B$10),0))) -> 6650 | C32: =C31+B32 -> 78754 | D32: =Parametres!$B$15+Parametres!$B$16*(A32-1) -> 1045 | E32: =Parametres!$B$17+Parametres!$B$18*(A32-1) -> 172 | F32: =Parametres!$B$19+Parametres!$B$20*(A32-1) -> 72.5 | G32: =Parametres!$B$21+Parametres!$B$22*(A32/(A32+Parametres!$B$23)) -> 0.1375 | H32: =IF(A32=1,0,Parametres!$B$70+Parametres!$B$71*INT(A32/5)) -> 8 | I32: =I31+H32 -> 151 | J32: =ROUND(C32/Parametres!$B$104,0) -> 408 | K32: =ROUND(J32/Parametres!$B$46,1) -> 102 | L32: =ROUND(K32/4.345,1) -> 23.5
A33: 29 | B33: =IF(A33=1,0,IF(A33-1<=Parametres!$B$10,ROUND(Parametres!$B$8*(A33-1)^Parametres!$B$9,0),ROUND(Parametres!$B$8*Parametres!$B$10^Parametres!$B$9+Parametres!$B$11*(A33-1-Parametres!$B$10),0))) -> 6850 | C33: =C32+B33 -> 85604 | D33: =Parametres!$B$15+Parametres!$B$16*(A33-1) -> 1080 | E33: =Parametres!$B$17+Parametres!$B$18*(A33-1) -> 178 | F33: =Parametres!$B$19+Parametres!$B$20*(A33-1) -> 75 | G33: =Parametres!$B$21+Parametres!$B$22*(A33/(A33+Parametres!$B$23)) -> 0.13877551 | H33: =IF(A33=1,0,Parametres!$B$70+Parametres!$B$71*INT(A33/5)) -> 8 | I33: =I32+H33 -> 159 | J33: =ROUND(C33/Parametres!$B$104,0) -> 444 | K33: =ROUND(J33/Parametres!$B$46,1) -> 111 | L33: =ROUND(K33/4.345,1) -> 25.5
A34: 30 | B34: =IF(A34=1,0,IF(A34-1<=Parametres!$B$10,ROUND(Parametres!$B$8*(A34-1)^Parametres!$B$9,0),ROUND(Parametres!$B$8*Parametres!$B$10^Parametres!$B$9+Parametres!$B$11*(A34-1-Parametres!$B$10),0))) -> 7050 | C34: =C33+B34 -> 92654 | D34: =Parametres!$B$15+Parametres!$B$16*(A34-1) -> 1115 | E34: =Parametres!$B$17+Parametres!$B$18*(A34-1) -> 184 | F34: =Parametres!$B$19+Parametres!$B$20*(A34-1) -> 77.5 | G34: =Parametres!$B$21+Parametres!$B$22*(A34/(A34+Parametres!$B$23)) -> 0.14 | H34: =IF(A34=1,0,Parametres!$B$70+Parametres!$B$71*INT(A34/5)) -> 9 | I34: =I33+H34 -> 168 | J34: =ROUND(C34/Parametres!$B$104,0) -> 480 | K34: =ROUND(J34/Parametres!$B$46,1) -> 120 | L34: =ROUND(K34/4.345,1) -> 27.6
A35: 31 | B35: =IF(A35=1,0,IF(A35-1<=Parametres!$B$10,ROUND(Parametres!$B$8*(A35-1)^Parametres!$B$9,0),ROUND(Parametres!$B$8*Parametres!$B$10^Parametres!$B$9+Parametres!$B$11*(A35-1-Parametres!$B$10),0))) -> 7250 | C35: =C34+B35 -> 99904 | D35: =Parametres!$B$15+Parametres!$B$16*(A35-1) -> 1150 | E35: =Parametres!$B$17+Parametres!$B$18*(A35-1) -> 190 | F35: =Parametres!$B$19+Parametres!$B$20*(A35-1) -> 80 | G35: =Parametres!$B$21+Parametres!$B$22*(A35/(A35+Parametres!$B$23)) -> 0.14117647 | H35: =IF(A35=1,0,Parametres!$B$70+Parametres!$B$71*INT(A35/5)) -> 9 | I35: =I34+H35 -> 177 | J35: =ROUND(C35/Parametres!$B$104,0) -> 518 | K35: =ROUND(J35/Parametres!$B$46,1) -> 129.5 | L35: =ROUND(K35/4.345,1) -> 29.8
A36: 32 | B36: =IF(A36=1,0,IF(A36-1<=Parametres!$B$10,ROUND(Parametres!$B$8*(A36-1)^Parametres!$B$9,0),ROUND(Parametres!$B$8*Parametres!$B$10^Parametres!$B$9+Parametres!$B$11*(A36-1-Parametres!$B$10),0))) -> 7450 | C36: =C35+B36 -> 107354 | D36: =Parametres!$B$15+Parametres!$B$16*(A36-1) -> 1185 | E36: =Parametres!$B$17+Parametres!$B$18*(A36-1) -> 196 | F36: =Parametres!$B$19+Parametres!$B$20*(A36-1) -> 82.5 | G36: =Parametres!$B$21+Parametres!$B$22*(A36/(A36+Parametres!$B$23)) -> 0.14230769 | H36: =IF(A36=1,0,Parametres!$B$70+Parametres!$B$71*INT(A36/5)) -> 9 | I36: =I35+H36 -> 186 | J36: =ROUND(C36/Parametres!$B$104,0) -> 556 | K36: =ROUND(J36/Parametres!$B$46,1) -> 139 | L36: =ROUND(K36/4.345,1) -> 32
A37: 33 | B37: =IF(A37=1,0,IF(A37-1<=Parametres!$B$10,ROUND(Parametres!$B$8*(A37-1)^Parametres!$B$9,0),ROUND(Parametres!$B$8*Parametres!$B$10^Parametres!$B$9+Parametres!$B$11*(A37-1-Parametres!$B$10),0))) -> 7650 | C37: =C36+B37 -> 115004 | D37: =Parametres!$B$15+Parametres!$B$16*(A37-1) -> 1220 | E37: =Parametres!$B$17+Parametres!$B$18*(A37-1) -> 202 | F37: =Parametres!$B$19+Parametres!$B$20*(A37-1) -> 85 | G37: =Parametres!$B$21+Parametres!$B$22*(A37/(A37+Parametres!$B$23)) -> 0.14339623 | H37: =IF(A37=1,0,Parametres!$B$70+Parametres!$B$71*INT(A37/5)) -> 9 | I37: =I36+H37 -> 195 | J37: =ROUND(C37/Parametres!$B$104,0) -> 596 | K37: =ROUND(J37/Parametres!$B$46,1) -> 149 | L37: =ROUND(K37/4.345,1) -> 34.3
A38: 34 | B38: =IF(A38=1,0,IF(A38-1<=Parametres!$B$10,ROUND(Parametres!$B$8*(A38-1)^Parametres!$B$9,0),ROUND(Parametres!$B$8*Parametres!$B$10^Parametres!$B$9+Parametres!$B$11*(A38-1-Parametres!$B$10),0))) -> 7850 | C38: =C37+B38 -> 122854 | D38: =Parametres!$B$15+Parametres!$B$16*(A38-1) -> 1255 | E38: =Parametres!$B$17+Parametres!$B$18*(A38-1) -> 208 | F38: =Parametres!$B$19+Parametres!$B$20*(A38-1) -> 87.5 | G38: =Parametres!$B$21+Parametres!$B$22*(A38/(A38+Parametres!$B$23)) -> 0.14444444 | H38: =IF(A38=1,0,Parametres!$B$70+Parametres!$B$71*INT(A38/5)) -> 9 | I38: =I37+H38 -> 204 | J38: =ROUND(C38/Parametres!$B$104,0) -> 637 | K38: =ROUND(J38/Parametres!$B$46,1) -> 159.3 | L38: =ROUND(K38/4.345,1) -> 36.7
A39: 35 | B39: =IF(A39=1,0,IF(A39-1<=Parametres!$B$10,ROUND(Parametres!$B$8*(A39-1)^Parametres!$B$9,0),ROUND(Parametres!$B$8*Parametres!$B$10^Parametres!$B$9+Parametres!$B$11*(A39-1-Parametres!$B$10),0))) -> 8050 | C39: =C38+B39 -> 130904 | D39: =Parametres!$B$15+Parametres!$B$16*(A39-1) -> 1290 | E39: =Parametres!$B$17+Parametres!$B$18*(A39-1) -> 214 | F39: =Parametres!$B$19+Parametres!$B$20*(A39-1) -> 90 | G39: =Parametres!$B$21+Parametres!$B$22*(A39/(A39+Parametres!$B$23)) -> 0.14545455 | H39: =IF(A39=1,0,Parametres!$B$70+Parametres!$B$71*INT(A39/5)) -> 10 | I39: =I38+H39 -> 214 | J39: =ROUND(C39/Parametres!$B$104,0) -> 678 | K39: =ROUND(J39/Parametres!$B$46,1) -> 169.5 | L39: =ROUND(K39/4.345,1) -> 39
A40: 36 | B40: =IF(A40=1,0,IF(A40-1<=Parametres!$B$10,ROUND(Parametres!$B$8*(A40-1)^Parametres!$B$9,0),ROUND(Parametres!$B$8*Parametres!$B$10^Parametres!$B$9+Parametres!$B$11*(A40-1-Parametres!$B$10),0))) -> 8250 | C40: =C39+B40 -> 139154 | D40: =Parametres!$B$15+Parametres!$B$16*(A40-1) -> 1325 | E40: =Parametres!$B$17+Parametres!$B$18*(A40-1) -> 220 | F40: =Parametres!$B$19+Parametres!$B$20*(A40-1) -> 92.5 | G40: =Parametres!$B$21+Parametres!$B$22*(A40/(A40+Parametres!$B$23)) -> 0.14642857 | H40: =IF(A40=1,0,Parametres!$B$70+Parametres!$B$71*INT(A40/5)) -> 10 | I40: =I39+H40 -> 224 | J40: =ROUND(C40/Parametres!$B$104,0) -> 721 | K40: =ROUND(J40/Parametres!$B$46,1) -> 180.3 | L40: =ROUND(K40/4.345,1) -> 41.5
A41: 37 | B41: =IF(A41=1,0,IF(A41-1<=Parametres!$B$10,ROUND(Parametres!$B$8*(A41-1)^Parametres!$B$9,0),ROUND(Parametres!$B$8*Parametres!$B$10^Parametres!$B$9+Parametres!$B$11*(A41-1-Parametres!$B$10),0))) -> 8450 | C41: =C40+B41 -> 147604 | D41: =Parametres!$B$15+Parametres!$B$16*(A41-1) -> 1360 | E41: =Parametres!$B$17+Parametres!$B$18*(A41-1) -> 226 | F41: =Parametres!$B$19+Parametres!$B$20*(A41-1) -> 95 | G41: =Parametres!$B$21+Parametres!$B$22*(A41/(A41+Parametres!$B$23)) -> 0.14736842 | H41: =IF(A41=1,0,Parametres!$B$70+Parametres!$B$71*INT(A41/5)) -> 10 | I41: =I40+H41 -> 234 | J41: =ROUND(C41/Parametres!$B$104,0) -> 765 | K41: =ROUND(J41/Parametres!$B$46,1) -> 191.3 | L41: =ROUND(K41/4.345,1) -> 44
... A43: 39 | B43: =IF(A43=1,0,IF(A43-1<=Parametres!$B$10,ROUND(Parametres!$B$8*(A43-1)^Parametres!$B$9,0),ROUND(Parametres!$B$8*Parametres!$B$10^Parametres!$B$9+Parametres!$B$11*(A43-1-Parametres!$B$10),0))) -> 8850 | C43: =C42+B43 -> 165104 | D43: =Parametres!$B$15+Parametres!$B$16*(A43-1) -> 1430 | E43: =Parametres!$B$17+Parametres!$B$18*(A43-1) -> 238 | F43: =Parametres!$B$19+Parametres!$B$20*(A43-1) -> 100 | G43: =Parametres!$B$21+Parametres!$B$22*(A43/(A43+Parametres!$B$23)) -> 0.14915254 | H43: =IF(A43=1,0,Parametres!$B$70+Parametres!$B$71*INT(A43/5)) -> 10 | I43: =I42+H43 -> 254 | J43: =ROUND(C43/Parametres!$B$104,0) -> 855 | K43: =ROUND(J43/Parametres!$B$46,1) -> 213.8 | L43: =ROUND(K43/4.345,1) -> 49.2
A44: 40 | B44: =IF(A44=1,0,IF(A44-1<=Parametres!$B$10,ROUND(Parametres!$B$8*(A44-1)^Parametres!$B$9,0),ROUND(Parametres!$B$8*Parametres!$B$10^Parametres!$B$9+Parametres!$B$11*(A44-1-Parametres!$B$10),0))) -> 9050 | C44: =C43+B44 -> 174154 | D44: =Parametres!$B$15+Parametres!$B$16*(A44-1) -> 1465 | E44: =Parametres!$B$17+Parametres!$B$18*(A44-1) -> 244 | F44: =Parametres!$B$19+Parametres!$B$20*(A44-1) -> 102.5 | G44: =Parametres!$B$21+Parametres!$B$22*(A44/(A44+Parametres!$B$23)) -> 0.15 | H44: =IF(A44=1,0,Parametres!$B$70+Parametres!$B$71*INT(A44/5)) -> 11 | I44: =I43+H44 -> 265 | J44: =ROUND(C44/Parametres!$B$104,0) -> 902 | K44: =ROUND(J44/Parametres!$B$46,1) -> 225.5 | L44: =ROUND(K44/4.345,1) -> 51.9 | M44: Vetéran
A45: 41 | B45: =IF(A45=1,0,IF(A45-1<=Parametres!$B$10,ROUND(Parametres!$B$8*(A45-1)^Parametres!$B$9,0),ROUND(Parametres!$B$8*Parametres!$B$10^Parametres!$B$9+Parametres!$B$11*(A45-1-Parametres!$B$10),0))) -> 9250 | C45: =C44+B45 -> 183404 | D45: =Parametres!$B$15+Parametres!$B$16*(A45-1) -> 1500 | E45: =Parametres!$B$17+Parametres!$B$18*(A45-1) -> 250 | F45: =Parametres!$B$19+Parametres!$B$20*(A45-1) -> 105 | G45: =Parametres!$B$21+Parametres!$B$22*(A45/(A45+Parametres!$B$23)) -> 0.15081967 | H45: =IF(A45=1,0,Parametres!$B$70+Parametres!$B$71*INT(A45/5)) -> 11 | I45: =I44+H45 -> 276 | J45: =ROUND(C45/Parametres!$B$104,0) -> 950 | K45: =ROUND(J45/Parametres!$B$46,1) -> 237.5 | L45: =ROUND(K45/4.345,1) -> 54.7
A46: 42 | B46: =IF(A46=1,0,IF(A46-1<=Parametres!$B$10,ROUND(Parametres!$B$8*(A46-1)^Parametres!$B$9,0),ROUND(Parametres!$B$8*Parametres!$B$10^Parametres!$B$9+Parametres!$B$11*(A46-1-Parametres!$B$10),0))) -> 9450 | C46: =C45+B46 -> 192854 | D46: =Parametres!$B$15+Parametres!$B$16*(A46-1) -> 1535 | E46: =Parametres!$B$17+Parametres!$B$18*(A46-1) -> 256 | F46: =Parametres!$B$19+Parametres!$B$20*(A46-1) -> 107.5 | G46: =Parametres!$B$21+Parametres!$B$22*(A46/(A46+Parametres!$B$23)) -> 0.1516129 | H46: =IF(A46=1,0,Parametres!$B$70+Parametres!$B$71*INT(A46/5)) -> 11 | I46: =I45+H46 -> 287 | J46: =ROUND(C46/Parametres!$B$104,0) -> 999 | K46: =ROUND(J46/Parametres!$B$46,1) -> 249.8 | L46: =ROUND(K46/4.345,1) -> 57.5
A47: 43 | B47: =IF(A47=1,0,IF(A47-1<=Parametres!$B$10,ROUND(Parametres!$B$8*(A47-1)^Parametres!$B$9,0),ROUND(Parametres!$B$8*Parametres!$B$10^Parametres!$B$9+Parametres!$B$11*(A47-1-Parametres!$B$10),0))) -> 9650 | C47: =C46+B47 -> 202504 | D47: =Parametres!$B$15+Parametres!$B$16*(A47-1) -> 1570 | E47: =Parametres!$B$17+Parametres!$B$18*(A47-1) -> 262 | F47: =Parametres!$B$19+Parametres!$B$20*(A47-1) -> 110 | G47: =Parametres!$B$21+Parametres!$B$22*(A47/(A47+Parametres!$B$23)) -> 0.15238095 | H47: =IF(A47=1,0,Parametres!$B$70+Parametres!$B$71*INT(A47/5)) -> 11 | I47: =I46+H47 -> 298 | J47: =ROUND(C47/Parametres!$B$104,0) -> 1049 | K47: =ROUND(J47/Parametres!$B$46,1) -> 262.3 | L47: =ROUND(K47/4.345,1) -> 60.4
A48: 44 | B48: =IF(A48=1,0,IF(A48-1<=Parametres!$B$10,ROUND(Parametres!$B$8*(A48-1)^Parametres!$B$9,0),ROUND(Parametres!$B$8*Parametres!$B$10^Parametres!$B$9+Parametres!$B$11*(A48-1-Parametres!$B$10),0))) -> 9850 | C48: =C47+B48 -> 212354 | D48: =Parametres!$B$15+Parametres!$B$16*(A48-1) -> 1605 | E48: =Parametres!$B$17+Parametres!$B$18*(A48-1) -> 268 | F48: =Parametres!$B$19+Parametres!$B$20*(A48-1) -> 112.5 | G48: =Parametres!$B$21+Parametres!$B$22*(A48/(A48+Parametres!$B$23)) -> 0.153125 | H48: =IF(A48=1,0,Parametres!$B$70+Parametres!$B$71*INT(A48/5)) -> 11 | I48: =I47+H48 -> 309 | J48: =ROUND(C48/Parametres!$B$104,0) -> 1100 | K48: =ROUND(J48/Parametres!$B$46,1) -> 275 | L48: =ROUND(K48/4.345,1) -> 63.3
A49: 45 | B49: =IF(A49=1,0,IF(A49-1<=Parametres!$B$10,ROUND(Parametres!$B$8*(A49-1)^Parametres!$B$9,0),ROUND(Parametres!$B$8*Parametres!$B$10^Parametres!$B$9+Parametres!$B$11*(A49-1-Parametres!$B$10),0))) -> 10050 | C49: =C48+B49 -> 222404 | D49: =Parametres!$B$15+Parametres!$B$16*(A49-1) -> 1640 | E49: =Parametres!$B$17+Parametres!$B$18*(A49-1) -> 274 | F49: =Parametres!$B$19+Parametres!$B$20*(A49-1) -> 115 | G49: =Parametres!$B$21+Parametres!$B$22*(A49/(A49+Parametres!$B$23)) -> 0.15384615 | H49: =IF(A49=1,0,Parametres!$B$70+Parametres!$B$71*INT(A49/5)) -> 12 | I49: =I48+H49 -> 321 | J49: =ROUND(C49/Parametres!$B$104,0) -> 1152 | K49: =ROUND(J49/Parametres!$B$46,1) -> 288 | L49: =ROUND(K49/4.345,1) -> 66.3
A50: 46 | B50: =IF(A50=1,0,IF(A50-1<=Parametres!$B$10,ROUND(Parametres!$B$8*(A50-1)^Parametres!$B$9,0),ROUND(Parametres!$B$8*Parametres!$B$10^Parametres!$B$9+Parametres!$B$11*(A50-1-Parametres!$B$10),0))) -> 10250 | C50: =C49+B50 -> 232654 | D50: =Parametres!$B$15+Parametres!$B$16*(A50-1) -> 1675 | E50: =Parametres!$B$17+Parametres!$B$18*(A50-1) -> 280 | F50: =Parametres!$B$19+Parametres!$B$20*(A50-1) -> 117.5 | G50: =Parametres!$B$21+Parametres!$B$22*(A50/(A50+Parametres!$B$23)) -> 0.15454545 | H50: =IF(A50=1,0,Parametres!$B$70+Parametres!$B$71*INT(A50/5)) -> 12 | I50: =I49+H50 -> 333 | J50: =ROUND(C50/Parametres!$B$104,0) -> 1205 | K50: =ROUND(J50/Parametres!$B$46,1) -> 301.3 | L50: =ROUND(K50/4.345,1) -> 69.3
A51: 47 | B51: =IF(A51=1,0,IF(A51-1<=Parametres!$B$10,ROUND(Parametres!$B$8*(A51-1)^Parametres!$B$9,0),ROUND(Parametres!$B$8*Parametres!$B$10^Parametres!$B$9+Parametres!$B$11*(A51-1-Parametres!$B$10),0))) -> 10450 | C51: =C50+B51 -> 243104 | D51: =Parametres!$B$15+Parametres!$B$16*(A51-1) -> 1710 | E51: =Parametres!$B$17+Parametres!$B$18*(A51-1) -> 286 | F51: =Parametres!$B$19+Parametres!$B$20*(A51-1) -> 120 | G51: =Parametres!$B$21+Parametres!$B$22*(A51/(A51+Parametres!$B$23)) -> 0.15522388 | H51: =IF(A51=1,0,Parametres!$B$70+Parametres!$B$71*INT(A51/5)) -> 12 | I51: =I50+H51 -> 345 | J51: =ROUND(C51/Parametres!$B$104,0) -> 1260 | K51: =ROUND(J51/Parametres!$B$46,1) -> 315 | L51: =ROUND(K51/4.345,1) -> 72.5
A52: 48 | B52: =IF(A52=1,0,IF(A52-1<=Parametres!$B$10,ROUND(Parametres!$B$8*(A52-1)^Parametres!$B$9,0),ROUND(Parametres!$B$8*Parametres!$B$10^Parametres!$B$9+Parametres!$B$11*(A52-1-Parametres!$B$10),0))) -> 10650 | C52: =C51+B52 -> 253754 | D52: =Parametres!$B$15+Parametres!$B$16*(A52-1) -> 1745 | E52: =Parametres!$B$17+Parametres!$B$18*(A52-1) -> 292 | F52: =Parametres!$B$19+Parametres!$B$20*(A52-1) -> 122.5 | G52: =Parametres!$B$21+Parametres!$B$22*(A52/(A52+Parametres!$B$23)) -> 0.15588235 | H52: =IF(A52=1,0,Parametres!$B$70+Parametres!$B$71*INT(A52/5)) -> 12 | I52: =I51+H52 -> 357 | J52: =ROUND(C52/Parametres!$B$104,0) -> 1315 | K52: =ROUND(J52/Parametres!$B$46,1) -> 328.8 | L52: =ROUND(K52/4.345,1) -> 75.7
A53: 49 | B53: =IF(A53=1,0,IF(A53-1<=Parametres!$B$10,ROUND(Parametres!$B$8*(A53-1)^Parametres!$B$9,0),ROUND(Parametres!$B$8*Parametres!$B$10^Parametres!$B$9+Parametres!$B$11*(A53-1-Parametres!$B$10),0))) -> 10850 | C53: =C52+B53 -> 264604 | D53: =Parametres!$B$15+Parametres!$B$16*(A53-1) -> 1780 | E53: =Parametres!$B$17+Parametres!$B$18*(A53-1) -> 298 | F53: =Parametres!$B$19+Parametres!$B$20*(A53-1) -> 125 | G53: =Parametres!$B$21+Parametres!$B$22*(A53/(A53+Parametres!$B$23)) -> 0.15652174 | H53: =IF(A53=1,0,Parametres!$B$70+Parametres!$B$71*INT(A53/5)) -> 12 | I53: =I52+H53 -> 369 | J53: =ROUND(C53/Parametres!$B$104,0) -> 1371 | K53: =ROUND(J53/Parametres!$B$46,1) -> 342.8 | L53: =ROUND(K53/4.345,1) -> 78.9
A54: 50 | B54: =IF(A54=1,0,IF(A54-1<=Parametres!$B$10,ROUND(Parametres!$B$8*(A54-1)^Parametres!$B$9,0),ROUND(Parametres!$B$8*Parametres!$B$10^Parametres!$B$9+Parametres!$B$11*(A54-1-Parametres!$B$10),0))) -> 11050 | C54: =C53+B54 -> 275654 | D54: =Parametres!$B$15+Parametres!$B$16*(A54-1) -> 1815 | E54: =Parametres!$B$17+Parametres!$B$18*(A54-1) -> 304 | F54: =Parametres!$B$19+Parametres!$B$20*(A54-1) -> 127.5 | G54: =Parametres!$B$21+Parametres!$B$22*(A54/(A54+Parametres!$B$23)) -> 0.15714286 | H54: =IF(A54=1,0,Parametres!$B$70+Parametres!$B$71*INT(A54/5)) -> 13 | I54: =I53+H54 -> 382 | J54: =ROUND(C54/Parametres!$B$104,0) -> 1428 | K54: =ROUND(J54/Parametres!$B$46,1) -> 357 | L54: =ROUND(K54/4.345,1) -> 82.2 | M54: Niveau maximum

Sheet XP Seance
A1: XP SEANCE — comment une vraie seance devient de l'XP
A2: XP brut = XP de base + (volume total / diviseur) + (nb de PR x bonus PR). Puis : XP final = XP brut x mult. nutrition x mult. moral x mult. streak.
A4: POURQUOI CE DECOUPAGE
A5: XP de base | B5: Recompense le fait de se presenter. Empeche qu'une petite seance ne donne rien.
A6: Composante volume | B6: Recompense le travail reel effectue. Impossible a farmer sans lever des charges.
A7: Bonus PR | B7: Recompense le progres, pas la repetition. C'est le lien direct avec la vraie vie.
A8: Multiplicateurs | B8: Nutrition, moral et regularite ne creent jamais d'XP a eux seuls — ils amplifient une seance reelle.
A10: EXEMPLES CHIFFRES — modifie les cellules jaunes pour tester
A11: Type de seance | B11: Volume total (lb) | C11: Nb de PR | D11: XP brut | E11: Mult. nutrition | F11: Mult. moral | G11: Mult. streak | H11: XP final | I11: % du niveau 5
A12: Seance legere / retour de pause | B12: 9000 | C12: 0 | D12: =ROUND(Parametres!$B$5+B12/Parametres!$B$6+C12*Parametres!$B$7,0) -> 95 | E12: 1 | F12: 0.9 | G12: 1 | H12: =ROUND(D12*E12*F12*G12,0) -> 86 | I12: =H12/Progression!$C$9 -> 0.10105758
A13: Seance normale — aucune nutrition loggee | B13: 20000 | C13: 0 | D13: =ROUND(Parametres!$B$5+B13/Parametres!$B$6+C13*Parametres!$B$7,0) -> 150 | E13: 1 | F13: 1 | G13: 1 | H13: =ROUND(D13*E13*F13*G13,0) -> 150 | I13: =H13/Progression!$C$9 -> 0.17626322
A14: Seance normale — nutrition parfaite | B14: 20000 | C14: 0 | D14: =ROUND(Parametres!$B$5+B14/Parametres!$B$6+C14*Parametres!$B$7,0) -> 150 | E14: =1+'Nutrition-Moral'!$C$9 -> 1.17 | F14: 1 | G14: 1 | H14: =ROUND(D14*E14*F14*G14,0) -> 176 | I14: =H14/Progression!$C$9 -> 0.20681551
A15: Seance normale + 1 PR + nutrition parfaite | B15: 20000 | C15: 1 | D15: =ROUND(Parametres!$B$5+B15/Parametres!$B$6+C15*Parametres!$B$7,0) -> 175 | E15: =1+'Nutrition-Moral'!$C$9 -> 1.17 | F15: 1 | G15: 1 | H15: =ROUND(D15*E15*F15*G15,0) -> 205 | I15: =H15/Progression!$C$9 -> 0.24089307
A16: Grosse seance, tout aligne (streak entrainement 10 sem. + serie nutri 15 j) | B16: 30000 | C16: 2 | D16: =ROUND(Parametres!$B$5+B16/Parametres!$B$6+C16*Parametres!$B$7,0) -> 250 | E16: ='Nutrition-Moral'!$D$32 -> 1.32 | F16: 1 | G16: 1.2 | H16: =ROUND(D16*E16*F16*G16,0) -> 396 | I16: =H16/Progression!$C$9 -> 0.4653349
A17: Grosse seance mais moral au plancher | B17: 30000 | C17: 2 | D17: =ROUND(Parametres!$B$5+B17/Parametres!$B$6+C17*Parametres!$B$7,0) -> 250 | E17: 1 | F17: 0.85 | G17: 1 | H17: =ROUND(D17*E17*F17*G17,0) -> 213 | I17: =H17/Progression!$C$9 -> 0.25029377
A19: Lecture : sans nutrition loggee tu restes a 1,00 (aucun malus). Trois cibles + 15 jours de serie = jusqu'a +32% d'XP par seance. Le moral (separe) ne descend jamais sous -15%.
A21: REPERES DE VOLUME REEL (pour calibrer)
A22: Profil de seance | B22: Exercices | C22: Series x reps | D22: Charge moyenne (lb) | E22: Volume total (lb)
A23: Court / accessoire | B23: 5 | C23: 3 x 10 | D23: 60 | E23: =B23*30*D23 -> 9000
A24: Standard haut du corps | B24: 7 | C24: 4 x 8 | D24: 85 | E24: =B24*32*D24 -> 19040
A25: Standard bas du corps | B25: 6 | C25: 4 x 8 | D25: 145 | E25: =B25*32*D25 -> 27840
A26: Longue seance full body | B26: 9 | C26: 4 x 8 | D26: 100 | E26: =B26*32*D26 -> 28800

Sheet Nutrition-Moral
A1: NUTRITION & MORAL — bonus pur, jamais de penalite
A2: La nutrition n'accorde que des bonus. Rien loggee ou cibles ratees = multiplicateur neutre (1,00), jamais de malus. Le moral, lui, ne reagit qu'a l'entrainement reel.
A4: LES 3 CIBLES DU JOUR — chacune independante
A5: Cible | B5: Condition de reussite | C5: Bonus XP si atteinte | D5: Si non atteinte
A6: Calories | B6: Dans +/- 10% de la cible quotidienne (2760 cal) | C6: =Parametres!$B$28 -> 0.05 | D6: Aucun bonus. Jamais de malus.
A7: Proteines | B7: Au moins 90% de la cible (150 g) | C7: =Parametres!$B$29 -> 0.08 | D7: Aucun bonus. Jamais de malus.
A8: Eau | B8: Au moins 90% de la cible (3,1 L) | C8: =Parametres!$B$30 -> 0.04 | D8: Aucun bonus. Jamais de malus.
A9: Maximum cumule (3 cibles le meme jour) | C9: =SUM(C6:C8) -> 0.17
A11: LES 8 COMBINAISONS POSSIBLES D'UNE JOURNEE
A12: Calories | B12: Proteines | C12: Eau | D12: Bonus XP du jour | E12: Nb de cibles atteintes | F12: Compte pour la serie ? (2+)
A13: Oui | B13: Oui | C13: Oui | D13: =Parametres!$B$28+Parametres!$B$29+Parametres!$B$30 -> 0.17 | E13: 3 | F13: OUI
A14: Oui | B14: Oui | C14: Non | D14: =Parametres!$B$28+Parametres!$B$29+0 -> 0.13 | E14: 2 | F14: OUI
A15: Oui | B15: Non | C15: Oui | D15: =Parametres!$B$28+0+Parametres!$B$30 -> 0.09 | E15: 2 | F15: OUI
A16: Oui | B16: Non | C16: Non | D16: =Parametres!$B$28+0+0 -> 0.05 | E16: 1 | F16: non
A17: Non | B17: Oui | C17: Oui | D17: =0+Parametres!$B$29+Parametres!$B$30 -> 0.12 | E17: 2 | F17: OUI
A18: Non | B18: Oui | C18: Non | D18: =0+Parametres!$B$29+0 -> 0.08 | E18: 1 | F18: non
A19: Non | B19: Non | C19: Oui | D19: =0+0+Parametres!$B$30 -> 0.04 | E19: 1 | F19: non
A20: Non | B20: Non | C20: Non | D20: =0+0+0 -> 0 | E20: 0 | F20: non
A21: Ligne du bas (aucune cible) : bonus = 0%, multiplicateur = 1,00. Des 2 cibles sur 3, le jour alimente deja la serie.
A23: LA SERIE (STREAK) — jours parfaits consecutifs
A24: Un jour compte pour la serie des que 2 des 3 cibles sont atteintes (pas besoin des 3). Un jour sous ce seuil — ou non loggue — fait retomber la serie a 0, sans jamais faire descendre le multiplicateur sous 1,00.
A25: Jours parfaits consecutifs | B25: Bonus XP de serie | C25: Chance gagnee | D25: Multiplicateur total (jour parfait + serie)
A26: 0 | B26: =MIN(A26*Parametres!$B$31,Parametres!$B$32) -> 0 | C26: =MIN(A26*Parametres!$B$33,Parametres!$B$34) -> 0 | D26: =1+Parametres!$B$28+Parametres!$B$29+Parametres!$B$30+B26 -> 1.17
A27: 1 | B27: =MIN(A27*Parametres!$B$31,Parametres!$B$32) -> 0.01 | C27: =MIN(A27*Parametres!$B$33,Parametres!$B$34) -> 2 | D27: =1+Parametres!$B$28+Parametres!$B$29+Parametres!$B$30+B27 -> 1.18
A28: 3 | B28: =MIN(A28*Parametres!$B$31,Parametres!$B$32) -> 0.03 | C28: =MIN(A28*Parametres!$B$33,Parametres!$B$34) -> 6 | D28: =1+Parametres!$B$28+Parametres!$B$29+Parametres!$B$30+B28 -> 1.2
A29: 5 | B29: =MIN(A29*Parametres!$B$31,Parametres!$B$32) -> 0.05 | C29: =MIN(A29*Parametres!$B$33,Parametres!$B$34) -> 10 | D29: =1+Parametres!$B$28+Parametres!$B$29+Parametres!$B$30+B29 -> 1.22
A30: 7 | B30: =MIN(A30*Parametres!$B$31,Parametres!$B$32) -> 0.07 | C30: =MIN(A30*Parametres!$B$33,Parametres!$B$34) -> 14 | D30: =1+Parametres!$B$28+Parametres!$B$29+Parametres!$B$30+B30 -> 1.24
A31: 10 | B31: =MIN(A31*Parametres!$B$31,Parametres!$B$32) -> 0.1 | C31: =MIN(A31*Parametres!$B$33,Parametres!$B$34) -> 20 | D31: =1+Parametres!$B$28+Parametres!$B$29+Parametres!$B$30+B31 -> 1.27
A32: 15 | B32: =MIN(A32*Parametres!$B$31,Parametres!$B$32) -> 0.15 | C32: =MIN(A32*Parametres!$B$33,Parametres!$B$34) -> 30 | D32: =1+Parametres!$B$28+Parametres!$B$29+Parametres!$B$30+B32 -> 1.32
A33: 20 | B33: =MIN(A33*Parametres!$B$31,Parametres!$B$32) -> 0.15 | C33: =MIN(A33*Parametres!$B$33,Parametres!$B$34) -> 30 | D33: =1+Parametres!$B$28+Parametres!$B$29+Parametres!$B$30+B33 -> 1.32
A35: A 15 jours de serie et une journee parfaite : multiplicateur de 1,32, soit +32% d'XP sur la seance.
A37: EXEMPLE — UNE SEMAINE TYPE
A38: Jour | B38: 2+ cibles atteintes ? | C38: Serie en cours | D38: Bonus serie | E38: Bonus du jour | F38: Multiplicateur total
A39: Jour 1 | B39: Oui | C39: =IF(B39="Oui",IF(ROW()=39,1,C38+1),0) -> 1 | D39: =MIN(C39*Parametres!$B$31,Parametres!$B$32) -> 0.01 | E39: =IF(B39="Oui",Parametres!$B$28+Parametres!$B$29+Parametres!$B$30,0) -> 0.17 | F39: =1+E39+D39 -> 1.18
A40: Jour 2 | B40: Oui | C40: =IF(B40="Oui",IF(ROW()=39,1,C39+1),0) -> 2 | D40: =MIN(C40*Parametres!$B$31,Parametres!$B$32) -> 0.02 | E40: =IF(B40="Oui",Parametres!$B$28+Parametres!$B$29+Parametres!$B$30,0) -> 0.17 | F40: =1+E40+D40 -> 1.19
A41: Jour 3 | B41: Non | C41: =IF(B41="Oui",IF(ROW()=39,1,C40+1),0) -> 0 | D41: =MIN(C41*Parametres!$B$31,Parametres!$B$32) -> 0 | E41: =IF(B41="Oui",Parametres!$B$28+Parametres!$B$29+Parametres!$B$30,0) -> 0 | F41: =1+E41+D41 -> 1
A42: Jour 4 | B42: Oui | C42: =IF(B42="Oui",IF(ROW()=39,1,C41+1),0) -> 1 | D42: =MIN(C42*Parametres!$B$31,Parametres!$B$32) -> 0.01 | E42: =IF(B42="Oui",Parametres!$B$28+Parametres!$B$29+Parametres!$B$30,0) -> 0.17 | F42: =1+E42+D42 -> 1.18
A43: Jour 5 | B43: Oui | C43: =IF(B43="Oui",IF(ROW()=39,1,C42+1),0) -> 2 | D43: =MIN(C43*Parametres!$B$31,Parametres!$B$32) -> 0.02 | E43: =IF(B43="Oui",Parametres!$B$28+Parametres!$B$29+Parametres!$B$30,0) -> 0.17 | F43: =1+E43+D43 -> 1.19
A44: Jour 6 | B44: Oui | C44: =IF(B44="Oui",IF(ROW()=39,1,C43+1),0) -> 3 | D44: =MIN(C44*Parametres!$B$31,Parametres!$B$32) -> 0.03 | E44: =IF(B44="Oui",Parametres!$B$28+Parametres!$B$29+Parametres!$B$30,0) -> 0.17 | F44: =1+E44+D44 -> 1.2
A45: Jour 7 | B45: Non | C45: =IF(B45="Oui",IF(ROW()=39,1,C44+1),0) -> 0 | D45: =MIN(C45*Parametres!$B$31,Parametres!$B$32) -> 0 | E45: =IF(B45="Oui",Parametres!$B$28+Parametres!$B$29+Parametres!$B$30,0) -> 0 | F45: =1+E45+D45 -> 1
A47: Jour 3 rate -> la serie retombe a 0, mais le multiplicateur ne descend jamais sous 1,00 (jamais de malus).
A49: MORAL — reagit uniquement a l'entrainement
A50: Systeme totalement separe de la nutrition. Seule source de penalite du jeu, et elle est plafonnee.
A51: Evenement | B51: Effet sur le Moral
A52: Seance loggee | B52: =Parametres!$B$38 -> 8
A53: Seance prevue manquee (objectif hebdo) | B53: =Parametres!$B$39 -> -10
A56: IMPACT DU MORAL SUR L'XP
A57: Moral | B57: Mult. XP (moral seul) | C57: Etat
A58: 0 | B58: =Parametres!$B$40+(1-Parametres!$B$40)*MIN(A58,Parametres!$B$41)/Parametres!$B$41 -> 0.85 | C58: =IF(A58>=Parametres!$B$41,"Plein — aucun malus","Entame") -> Entame
A59: 20 | B59: =Parametres!$B$40+(1-Parametres!$B$40)*MIN(A59,Parametres!$B$41)/Parametres!$B$41 -> 0.8875 | C59: =IF(A59>=Parametres!$B$41,"Plein — aucun malus","Entame") -> Entame
A60: 40 | B60: =Parametres!$B$40+(1-Parametres!$B$40)*MIN(A60,Parametres!$B$41)/Parametres!$B$41 -> 0.925 | C60: =IF(A60>=Parametres!$B$41,"Plein — aucun malus","Entame") -> Entame
A61: 60 | B61: =Parametres!$B$40+(1-Parametres!$B$40)*MIN(A61,Parametres!$B$41)/Parametres!$B$41 -> 0.9625 | C61: =IF(A61>=Parametres!$B$41,"Plein — aucun malus","Entame") -> Entame
A62: 80 | B62: =Parametres!$B$40+(1-Parametres!$B$40)*MIN(A62,Parametres!$B$41)/Parametres!$B$41 -> 1 | C62: =IF(A62>=Parametres!$B$41,"Plein — aucun malus","Entame") -> Plein — aucun malus
A63: 100 | B63: =Parametres!$B$40+(1-Parametres!$B$40)*MIN(A63,Parametres!$B$41)/Parametres!$B$41 -> 1 | C63: =IF(A63>=Parametres!$B$41,"Plein — aucun malus","Entame") -> Plein — aucun malus
A65: Le multiplicateur final d'une seance = mult. nutrition (jour + serie) x mult. moral x mult. streak entrainement x mult. collier. Deux systemes independants qui se multiplient, jamais ne s'annulent.

Sheet Donjon
A1: DONJON — 10 paliers, le 10e est le boss
A2: Il se resout tout seul, meme hors-ligne (rattrapage au chargement). Echec = retour au palier 1. Chaque cycle complete durcit tout : c'est le mur qui pousse a s'entrainer davantage.
A4: Cycle a afficher | B4: 1 | C4: Cycle 1 = premiere descente. Modifie cette cellule pour voir l'escalade.
A6: Palier | B6: Type | C6: PV ennemi | D6: ATQ ennemi | E6: DEF ennemi | F6: Or largue | G6: Essence | H6: Or cumule (la run) | I6: Essence cumulee
A7: 1 | B7: =IF(A7=Parametres!$B$51,"BOSS","Monstre") -> Monstre | C7: =ROUND(Parametres!$B$52*A7^Parametres!$B$53*(1+Parametres!$B$58)^($B$4-1)*IF(A7=Parametres!$B$51,Parametres!$B$59,1),0) -> 50 | D7: =ROUND(Parametres!$B$54*A7^Parametres!$B$55*(1+Parametres!$B$58)^($B$4-1)*IF(A7=Parametres!$B$51,Parametres!$B$60,1),0) -> 10 | E7: =ROUND(Parametres!$B$56*A7^Parametres!$B$57*(1+Parametres!$B$58)^($B$4-1),0) -> 4 | F7: =ROUND(Parametres!$B$63*A7*(1+Parametres!$B$64*($B$4-1)),0) -> 10 | G7: =Parametres!$B$65+IF(A7=Parametres!$B$51,Parametres!$B$66,0) -> 1 | H7: =F7 -> 10 | I7: =G7 -> 1
A8: 2 | B8: =IF(A8=Parametres!$B$51,"BOSS","Monstre") -> Monstre | C8: =ROUND(Parametres!$B$52*A8^Parametres!$B$53*(1+Parametres!$B$58)^($B$4-1)*IF(A8=Parametres!$B$51,Parametres!$B$59,1),0) -> 93 | D8: =ROUND(Parametres!$B$54*A8^Parametres!$B$55*(1+Parametres!$B$58)^($B$4-1)*IF(A8=Parametres!$B$51,Parametres!$B$60,1),0) -> 17 | E8: =ROUND(Parametres!$B$56*A8^Parametres!$B$57*(1+Parametres!$B$58)^($B$4-1),0) -> 7 | F8: =ROUND(Parametres!$B$63*A8*(1+Parametres!$B$64*($B$4-1)),0) -> 20 | G8: =Parametres!$B$65+IF(A8=Parametres!$B$51,Parametres!$B$66,0) -> 1 | H8: =H7+F8 -> 30 | I8: =I7+G8 -> 2
A9: 3 | B9: =IF(A9=Parametres!$B$51,"BOSS","Monstre") -> Monstre | C9: =ROUND(Parametres!$B$52*A9^Parametres!$B$53*(1+Parametres!$B$58)^($B$4-1)*IF(A9=Parametres!$B$51,Parametres!$B$59,1),0) -> 134 | D9: =ROUND(Parametres!$B$54*A9^Parametres!$B$55*(1+Parametres!$B$58)^($B$4-1)*IF(A9=Parametres!$B$51,Parametres!$B$60,1),0) -> 24 | E9: =ROUND(Parametres!$B$56*A9^Parametres!$B$57*(1+Parametres!$B$58)^($B$4-1),0) -> 10 | F9: =ROUND(Parametres!$B$63*A9*(1+Parametres!$B$64*($B$4-1)),0) -> 30 | G9: =Parametres!$B$65+IF(A9=Parametres!$B$51,Parametres!$B$66,0) -> 1 | H9: =H8+F9 -> 60 | I9: =I8+G9 -> 3
A10: 4 | B10: =IF(A10=Parametres!$B$51,"BOSS","Monstre") -> Monstre | C10: =ROUND(Parametres!$B$52*A10^Parametres!$B$53*(1+Parametres!$B$58)^($B$4-1)*IF(A10=Parametres!$B$51,Parametres!$B$59,1),0) -> 174 | D10: =ROUND(Parametres!$B$54*A10^Parametres!$B$55*(1+Parametres!$B$58)^($B$4-1)*IF(A10=Parametres!$B$51,Parametres!$B$60,1),0) -> 30 | E10: =ROUND(Parametres!$B$56*A10^Parametres!$B$57*(1+Parametres!$B$58)^($B$4-1),0) -> 13 | F10: =ROUND(Parametres!$B$63*A10*(1+Parametres!$B$64*($B$4-1)),0) -> 40 | G10: =Parametres!$B$65+IF(A10=Parametres!$B$51,Parametres!$B$66,0) -> 1 | H10: =H9+F10 -> 100 | I10: =I9+G10 -> 4
A11: 5 | B11: =IF(A11=Parametres!$B$51,"BOSS","Monstre") -> Monstre | C11: =ROUND(Parametres!$B$52*A11^Parametres!$B$53*(1+Parametres!$B$58)^($B$4-1)*IF(A11=Parametres!$B$51,Parametres!$B$59,1),0) -> 213 | D11: =ROUND(Parametres!$B$54*A11^Parametres!$B$55*(1+Parametres!$B$58)^($B$4-1)*IF(A11=Parametres!$B$51,Parametres!$B$60,1),0) -> 36 | E11: =ROUND(Parametres!$B$56*A11^Parametres!$B$57*(1+Parametres!$B$58)^($B$4-1),0) -> 16 | F11: =ROUND(Parametres!$B$63*A11*(1+Parametres!$B$64*($B$4-1)),0) -> 50 | G11: =Parametres!$B$65+IF(A11=Parametres!$B$51,Parametres!$B$66,0) -> 1 | H11: =H10+F11 -> 150 | I11: =I10+G11 -> 5
A12: 6 | B12: =IF(A12=Parametres!$B$51,"BOSS","Monstre") -> Monstre | C12: =ROUND(Parametres!$B$52*A12^Parametres!$B$53*(1+Parametres!$B$58)^($B$4-1)*IF(A12=Parametres!$B$51,Parametres!$B$59,1),0) -> 251 | D12: =ROUND(Parametres!$B$54*A12^Parametres!$B$55*(1+Parametres!$B$58)^($B$4-1)*IF(A12=Parametres!$B$51,Parametres!$B$60,1),0) -> 42 | E12: =ROUND(Parametres!$B$56*A12^Parametres!$B$57*(1+Parametres!$B$58)^($B$4-1),0) -> 18 | F12: =ROUND(Parametres!$B$63*A12*(1+Parametres!$B$64*($B$4-1)),0) -> 60 | G12: =Parametres!$B$65+IF(A12=Parametres!$B$51,Parametres!$B$66,0) -> 1 | H12: =H11+F12 -> 210 | I12: =I11+G12 -> 6
A13: 7 | B13: =IF(A13=Parametres!$B$51,"BOSS","Monstre") -> Monstre | C13: =ROUND(Parametres!$B$52*A13^Parametres!$B$53*(1+Parametres!$B$58)^($B$4-1)*IF(A13=Parametres!$B$51,Parametres!$B$59,1),0) -> 288 | D13: =ROUND(Parametres!$B$54*A13^Parametres!$B$55*(1+Parametres!$B$58)^($B$4-1)*IF(A13=Parametres!$B$51,Parametres!$B$60,1),0) -> 47 | E13: =ROUND(Parametres!$B$56*A13^Parametres!$B$57*(1+Parametres!$B$58)^($B$4-1),0) -> 21 | F13: =ROUND(Parametres!$B$63*A13*(1+Parametres!$B$64*($B$4-1)),0) -> 70 | G13: =Parametres!$B$65+IF(A13=Parametres!$B$51,Parametres!$B$66,0) -> 1 | H13: =H12+F13 -> 280 | I13: =I12+G13 -> 7
A14: 8 | B14: =IF(A14=Parametres!$B$51,"BOSS","Monstre") -> Monstre | C14: =ROUND(Parametres!$B$52*A14^Parametres!$B$53*(1+Parametres!$B$58)^($B$4-1)*IF(A14=Parametres!$B$51,Parametres!$B$59,1),0) -> 325 | D14: =ROUND(Parametres!$B$54*A14^Parametres!$B$55*(1+Parametres!$B$58)^($B$4-1)*IF(A14=Parametres!$B$51,Parametres!$B$60,1),0) -> 53 | E14: =ROUND(Parametres!$B$56*A14^Parametres!$B$57*(1+Parametres!$B$58)^($B$4-1),0) -> 23 | F14: =ROUND(Parametres!$B$63*A14*(1+Parametres!$B$64*($B$4-1)),0) -> 80 | G14: =Parametres!$B$65+IF(A14=Parametres!$B$51,Parametres!$B$66,0) -> 1 | H14: =H13+F14 -> 360 | I14: =I13+G14 -> 8
A15: 9 | B15: =IF(A15=Parametres!$B$51,"BOSS","Monstre") -> Monstre | C15: =ROUND(Parametres!$B$52*A15^Parametres!$B$53*(1+Parametres!$B$58)^($B$4-1)*IF(A15=Parametres!$B$51,Parametres!$B$59,1),0) -> 361 | D15: =ROUND(Parametres!$B$54*A15^Parametres!$B$55*(1+Parametres!$B$58)^($B$4-1)*IF(A15=Parametres!$B$51,Parametres!$B$60,1),0) -> 58 | E15: =ROUND(Parametres!$B$56*A15^Parametres!$B$57*(1+Parametres!$B$58)^($B$4-1),0) -> 26 | F15: =ROUND(Parametres!$B$63*A15*(1+Parametres!$B$64*($B$4-1)),0) -> 90 | G15: =Parametres!$B$65+IF(A15=Parametres!$B$51,Parametres!$B$66,0) -> 1 | H15: =H14+F15 -> 450 | I15: =I14+G15 -> 9
A16: 10 | B16: =IF(A16=Parametres!$B$51,"BOSS","Monstre") -> BOSS | C16: =ROUND(Parametres!$B$52*A16^Parametres!$B$53*(1+Parametres!$B$58)^($B$4-1)*IF(A16=Parametres!$B$51,Parametres!$B$59,1),0) -> 874 | D16: =ROUND(Parametres!$B$54*A16^Parametres!$B$55*(1+Parametres!$B$58)^($B$4-1)*IF(A16=Parametres!$B$51,Parametres!$B$60,1),0) -> 95 | E16: =ROUND(Parametres!$B$56*A16^Parametres!$B$57*(1+Parametres!$B$58)^($B$4-1),0) -> 28 | F16: =ROUND(Parametres!$B$63*A16*(1+Parametres!$B$64*($B$4-1)),0) -> 100 | G16: =Parametres!$B$65+IF(A16=Parametres!$B$51,Parametres!$B$66,0) -> 6 | H16: =H15+F16 -> 550 | I16: =I15+G16 -> 15
A19: ESCALADE DES CYCLES — le boss cycle par cycle
A20: Cycle | B20: PV du boss | C20: ATQ du boss | D20: Or de la run complete | E20: Essence de la run | F20: Difficulte relative | G20: Commentaire
A21: 1 | B21: =ROUND(Parametres!$B$52*Parametres!$B$51^Parametres!$B$53*(1+Parametres!$B$58)^(A21-1)*Parametres!$B$59,0) -> 874 | C21: =ROUND(Parametres!$B$54*Parametres!$B$51^Parametres!$B$55*(1+Parametres!$B$58)^(A21-1)*Parametres!$B$60,0) -> 95 | D21: =ROUND(Parametres!$B$63*55*(1+Parametres!$B$64*(A21-1)),0) -> 550 | E21: =Parametres!$B$65*Parametres!$B$51+Parametres!$B$66 -> 15 | F21: =(1+Parametres!$B$58)^(A21-1) -> 1 | G21: Accessible des le niveau 5.
A22: 2 | B22: =ROUND(Parametres!$B$52*Parametres!$B$51^Parametres!$B$53*(1+Parametres!$B$58)^(A22-1)*Parametres!$B$59,0) -> 1049 | C22: =ROUND(Parametres!$B$54*Parametres!$B$51^Parametres!$B$55*(1+Parametres!$B$58)^(A22-1)*Parametres!$B$60,0) -> 114 | D22: =ROUND(Parametres!$B$63*55*(1+Parametres!$B$64*(A22-1)),0) -> 605 | E22: =Parametres!$B$65*Parametres!$B$51+Parametres!$B$66 -> 15 | F22: =(1+Parametres!$B$58)^(A22-1) -> 1.2
A23: 3 | B23: =ROUND(Parametres!$B$52*Parametres!$B$51^Parametres!$B$53*(1+Parametres!$B$58)^(A23-1)*Parametres!$B$59,0) -> 1258 | C23: =ROUND(Parametres!$B$54*Parametres!$B$51^Parametres!$B$55*(1+Parametres!$B$58)^(A23-1)*Parametres!$B$60,0) -> 136 | D23: =ROUND(Parametres!$B$63*55*(1+Parametres!$B$64*(A23-1)),0) -> 660 | E23: =Parametres!$B$65*Parametres!$B$51+Parametres!$B$66 -> 15 | F23: =(1+Parametres!$B$58)^(A23-1) -> 1.44 | G23: Il faut de l'equipement rare.
A24: 4 | B24: =ROUND(Parametres!$B$52*Parametres!$B$51^Parametres!$B$53*(1+Parametres!$B$58)^(A24-1)*Parametres!$B$59,0) -> 1510 | C24: =ROUND(Parametres!$B$54*Parametres!$B$51^Parametres!$B$55*(1+Parametres!$B$58)^(A24-1)*Parametres!$B$60,0) -> 164 | D24: =ROUND(Parametres!$B$63*55*(1+Parametres!$B$64*(A24-1)),0) -> 715 | E24: =Parametres!$B$65*Parametres!$B$51+Parametres!$B$66 -> 15 | F24: =(1+Parametres!$B$58)^(A24-1) -> 1.728
A25: 5 | B25: =ROUND(Parametres!$B$52*Parametres!$B$51^Parametres!$B$53*(1+Parametres!$B$58)^(A25-1)*Parametres!$B$59,0) -> 1812 | C25: =ROUND(Parametres!$B$54*Parametres!$B$51^Parametres!$B$55*(1+Parametres!$B$58)^(A25-1)*Parametres!$B$60,0) -> 196 | D25: =ROUND(Parametres!$B$63*55*(1+Parametres!$B$64*(A25-1)),0) -> 770 | E25: =Parametres!$B$65*Parametres!$B$51+Parametres!$B$66 -> 15 | F25: =(1+Parametres!$B$58)^(A25-1) -> 2.0736 | G25: Premier vrai palier de patience.
A26: 6 | B26: =ROUND(Parametres!$B$52*Parametres!$B$51^Parametres!$B$53*(1+Parametres!$B$58)^(A26-1)*Parametres!$B$59,0) -> 2174 | C26: =ROUND(Parametres!$B$54*Parametres!$B$51^Parametres!$B$55*(1+Parametres!$B$58)^(A26-1)*Parametres!$B$60,0) -> 236 | D26: =ROUND(Parametres!$B$63*55*(1+Parametres!$B$64*(A26-1)),0) -> 825 | E26: =Parametres!$B$65*Parametres!$B$51+Parametres!$B$66 -> 15 | F26: =(1+Parametres!$B$58)^(A26-1) -> 2.48832
A27: 7 | B27: =ROUND(Parametres!$B$52*Parametres!$B$51^Parametres!$B$53*(1+Parametres!$B$58)^(A27-1)*Parametres!$B$59,0) -> 2609 | C27: =ROUND(Parametres!$B$54*Parametres!$B$51^Parametres!$B$55*(1+Parametres!$B$58)^(A27-1)*Parametres!$B$60,0) -> 283 | D27: =ROUND(Parametres!$B$63*55*(1+Parametres!$B$64*(A27-1)),0) -> 880 | E27: =Parametres!$B$65*Parametres!$B$51+Parametres!$B$66 -> 15 | F27: =(1+Parametres!$B$58)^(A27-1) -> 2.985984
A28: 8 | B28: =ROUND(Parametres!$B$52*Parametres!$B$51^Parametres!$B$53*(1+Parametres!$B$58)^(A28-1)*Parametres!$B$59,0) -> 3131 | C28: =ROUND(Parametres!$B$54*Parametres!$B$51^Parametres!$B$55*(1+Parametres!$B$58)^(A28-1)*Parametres!$B$60,0) -> 339 | D28: =ROUND(Parametres!$B$63*55*(1+Parametres!$B$64*(A28-1)),0) -> 935 | E28: =Parametres!$B$65*Parametres!$B$51+Parametres!$B$66 -> 15 | F28: =(1+Parametres!$B$58)^(A28-1) -> 3.5831808 | G28: Exige de l'epique bien forge.
A29: 9 | B29: =ROUND(Parametres!$B$52*Parametres!$B$51^Parametres!$B$53*(1+Parametres!$B$58)^(A29-1)*Parametres!$B$59,0) -> 3757 | C29: =ROUND(Parametres!$B$54*Parametres!$B$51^Parametres!$B$55*(1+Parametres!$B$58)^(A29-1)*Parametres!$B$60,0) -> 407 | D29: =ROUND(Parametres!$B$63*55*(1+Parametres!$B$64*(A29-1)),0) -> 990 | E29: =Parametres!$B$65*Parametres!$B$51+Parametres!$B$66 -> 15 | F29: =(1+Parametres!$B$58)^(A29-1) -> 4.299817
A30: 10 | B30: =ROUND(Parametres!$B$52*Parametres!$B$51^Parametres!$B$53*(1+Parametres!$B$58)^(A30-1)*Parametres!$B$59,0) -> 4508 | C30: =ROUND(Parametres!$B$54*Parametres!$B$51^Parametres!$B$55*(1+Parametres!$B$58)^(A30-1)*Parametres!$B$60,0) -> 488 | D30: =ROUND(Parametres!$B$63*55*(1+Parametres!$B$64*(A30-1)),0) -> 1045 | E30: =Parametres!$B$65*Parametres!$B$51+Parametres!$B$66 -> 15 | F30: =(1+Parametres!$B$58)^(A30-1) -> 5.1597804
A31: 11 | B31: =ROUND(Parametres!$B$52*Parametres!$B$51^Parametres!$B$53*(1+Parametres!$B$58)^(A31-1)*Parametres!$B$59,0) -> 5410 | C31: =ROUND(Parametres!$B$54*Parametres!$B$51^Parametres!$B$55*(1+Parametres!$B$58)^(A31-1)*Parametres!$B$60,0) -> 586 | D31: =ROUND(Parametres!$B$63*55*(1+Parametres!$B$64*(A31-1)),0) -> 1100 | E31: =Parametres!$B$65*Parametres!$B$51+Parametres!$B$66 -> 15 | F31: =(1+Parametres!$B$58)^(A31-1) -> 6.1917364
A32: 12 | B32: =ROUND(Parametres!$B$52*Parametres!$B$51^Parametres!$B$53*(1+Parametres!$B$58)^(A32-1)*Parametres!$B$59,0) -> 6492 | C32: =ROUND(Parametres!$B$54*Parametres!$B$51^Parametres!$B$55*(1+Parametres!$B$58)^(A32-1)*Parametres!$B$60,0) -> 703 | D32: =ROUND(Parametres!$B$63*55*(1+Parametres!$B$64*(A32-1)),0) -> 1155 | E32: =Parametres!$B$65*Parametres!$B$51+Parametres!$B$66 -> 15 | F32: =(1+Parametres!$B$58)^(A32-1) -> 7.4300837 | G32: Zone de fin de partie.
A33: 13 | B33: =ROUND(Parametres!$B$52*Parametres!$B$51^Parametres!$B$53*(1+Parametres!$B$58)^(A33-1)*Parametres!$B$59,0) -> 7791 | C33: =ROUND(Parametres!$B$54*Parametres!$B$51^Parametres!$B$55*(1+Parametres!$B$58)^(A33-1)*Parametres!$B$60,0) -> 844 | D33: =ROUND(Parametres!$B$63*55*(1+Parametres!$B$64*(A33-1)),0) -> 1210 | E33: =Parametres!$B$65*Parametres!$B$51+Parametres!$B$66 -> 15 | F33: =(1+Parametres!$B$58)^(A33-1) -> 8.9161004
A34: 14 | B34: =ROUND(Parametres!$B$52*Parametres!$B$51^Parametres!$B$53*(1+Parametres!$B$58)^(A34-1)*Parametres!$B$59,0) -> 9349 | C34: =ROUND(Parametres!$B$54*Parametres!$B$51^Parametres!$B$55*(1+Parametres!$B$58)^(A34-1)*Parametres!$B$60,0) -> 1013 | D34: =ROUND(Parametres!$B$63*55*(1+Parametres!$B$64*(A34-1)),0) -> 1265 | E34: =Parametres!$B$65*Parametres!$B$51+Parametres!$B$66 -> 15 | F34: =(1+Parametres!$B$58)^(A34-1) -> 10.699321
A35: 15 | B35: =ROUND(Parametres!$B$52*Parametres!$B$51^Parametres!$B$53*(1+Parametres!$B$58)^(A35-1)*Parametres!$B$59,0) -> 11218 | C35: =ROUND(Parametres!$B$54*Parametres!$B$51^Parametres!$B$55*(1+Parametres!$B$58)^(A35-1)*Parametres!$B$60,0) -> 1215 | D35: =ROUND(Parametres!$B$63*55*(1+Parametres!$B$64*(A35-1)),0) -> 1320 | E35: =Parametres!$B$65*Parametres!$B$51+Parametres!$B$66 -> 15 | F35: =(1+Parametres!$B$58)^(A35-1) -> 12.839185 | G35: Necessite du legendaire + forge max.
A37: Note de design : les PV ne se regenerent PAS entre les paliers d'une meme run. Une descente est donc une gestion de ressource, pas 10 combats independants. C'est ce qui rend l'equipement defensif utile et le boss reellement menacant.
A39: FRONTIERE NIVEAU / CYCLE — quel niveau faut-il pour nettoyer quel cycle
A40: Obtenu par recherche exhaustive sur le modele de combat (equipement moyen du cycle precedent). C'est la table de reference pour verifier que le rythme du donjon suit celui de l'entrainement.
A41: Cycle | B41: Niveau minimum | C41: Semaines estimees (rythme 4 seances) | D41: Niveaux depuis le cycle precedent | E41: Ressenti
A42: 1 | B42: 6 | C42: =INDEX(Progression!$K$5:$K$54,B42) -> 1.8 | D42: =B42 -> 6 | E42: Donjon ouvert. Premieres victoires rapides.
A43: 2 | B43: 7 | C43: =INDEX(Progression!$K$5:$K$54,B43) -> 2.8 | D43: =B43-B42 -> 1 | E43: Un seul niveau d'ecart : ca enchaine.
A44: 3 | B44: 8 | C44: =INDEX(Progression!$K$5:$K$54,B44) -> 4 | D44: =B44-B43 -> 1 | E44: Toujours rapide — c'est la phase d'accroche.
A45: 4 | B45: 10 | C45: =INDEX(Progression!$K$5:$K$54,B45) -> 7.3 | D45: =B45-B44 -> 2 | E45: Premier vrai palier de patience.
A46: 5 | B46: 11 | C46: =INDEX(Progression!$K$5:$K$54,B46) -> 9.3 | D46: =B46-B45 -> 1
A47: 6 | B47: 13 | C47: =INDEX(Progression!$K$5:$K$54,B47) -> 14.3 | D47: =B47-B46 -> 2 | E47: L'equipement commence a compter autant que le niveau.
A48: 7 | B48: 16 | C48: =INDEX(Progression!$K$5:$K$54,B48) -> 24.5 | D48: =B48-B47 -> 3
A49: 8 | B49: 18 | C49: =INDEX(Progression!$K$5:$K$54,B49) -> 33.3 | D49: =B49-B48 -> 2 | E49: Il faut de l'epique bien forge.
A50: 9 | B50: 21 | C50: =INDEX(Progression!$K$5:$K$54,B50) -> 49.3 | D50: =B50-B49 -> 3
A51: 10 | B51: 26 | C51: =INDEX(Progression!$K$5:$K$54,B51) -> 85 | D51: =B51-B50 -> 5 | E51: Zone de fin de partie. Chaque cycle = plusieurs mois.
A52: 11 | B52: 30 | C52: =INDEX(Progression!$K$5:$K$54,B52) -> 120 | D52: =B52-B51 -> 4
A53: 12 | B53: 35 | C53: =INDEX(Progression!$K$5:$K$54,B53) -> 169.5 | D53: =B53-B52 -> 5 | E53: Necessite du legendaire + forge poussee.
A55: Lecture : les 3 premiers cycles s'enchainent en quelques semaines (l'accroche), puis l'ecart se creuse. Passe le cycle 10, un cycle represente plusieurs mois d'entrainement reel. Le donjon ne peut jamais depasser le niveau — impossible de farmer sa sortie d'un mur.

Sheet Sim Combat
A1: SIMULATEUR DE COMBAT — est-ce que ce niveau passe le donjon ?
A2: Degats = ATQ x (1 - DEF/(DEF+K)). Les PV ne remontent que partiellement entre les paliers (levier de regeneration) : une run est une gestion de ressource, pas 10 combats independants.
A4: ENTREES — modifie les cellules jaunes
A5: Niveau du joueur | B5: 11 | D5: Palier moyen de drop | E5: 8
A6: Cycle du donjon | B6: 5 | D6: Rarete moyenne (1=commun, 2,6=epique) | E6: 1.8
A7: Bonus ATQ de l'equipement | B7: =ROUND((Parametres!$B$86+Parametres!$B$87*$E$5)*$E$6*(1+Parametres!$B$58)^($B$6-1),0) -> 142 | D7: PV par point de puissance | E7: 4.8
A8: Bonus PV de l'equipement | B8: =ROUND((Parametres!$B$86+Parametres!$B$87*$E$5)*$E$6*(1+Parametres!$B$58)^($B$6-1)*$E$7,0) -> 681 | D8: DEF par point de puissance | E8: 0.5
A9: Bonus DEF de l'equipement | B9: =ROUND((Parametres!$B$86+Parametres!$B$87*$E$5)*$E$6*(1+Parametres!$B$58)^($B$6-1)*$E$8,0) -> 71 | D9: L'equipement s'ajuste au cycle choisi. Ecris tes vrais chiffres en B7:B9 pour tester un set precis.
A10: Bonus critique de l'equipement | B10: 0.05 | D10: Bonus critique de l'equipement (bague).
A12: STATS EFFECTIVES DU PERSONNAGE
A13: PV total | B13: =INDEX(Progression!$D$5:$D$54,MATCH($B$5,Progression!$A$5:$A$54,0))+$B$8 -> 1131
A14: ATQ total | B14: =INDEX(Progression!$E$5:$E$54,MATCH($B$5,Progression!$A$5:$A$54,0))+$B$7 -> 212
A15: DEF totale | B15: =INDEX(Progression!$F$5:$F$54,MATCH($B$5,Progression!$A$5:$A$54,0))+$B$9 -> 101
A16: Critique total | B16: =INDEX(Progression!$G$5:$G$54,MATCH($B$5,Progression!$A$5:$A$54,0))+$B$10 -> 0.15322581
A17: Reduction de degats subie | B17: =$B$15/($B$15+Parametres!$B$25) -> 0.55801105
A19: RESOLUTION PALIER PAR PALIER
A20: Palier | B20: PV ennemi | C20: ATQ ennemi | D20: DEF ennemi | E20: Degats par coup | F20: Degats moyens (avec crit) | G20: Tours pour tuer | H20: Degats subis par tour | I20: PV perdus au palier | J20: PV restants | K20: Resultat
A21: 1 | B21: =ROUND(Parametres!$B$52*A21^Parametres!$B$53*(1+Parametres!$B$58)^($B$6-1)*IF(A21=Parametres!$B$51,Parametres!$B$59,1),0) -> 104 | C21: =ROUND(Parametres!$B$54*A21^Parametres!$B$55*(1+Parametres!$B$58)^($B$6-1)*IF(A21=Parametres!$B$51,Parametres!$B$60,1),0) -> 21 | D21: =ROUND(Parametres!$B$56*A21^Parametres!$B$57*(1+Parametres!$B$58)^($B$6-1),0) -> 8 | E21: =MAX(1,$B$14*(1-D21/(D21+Parametres!$B$25))) -> 192.72727 | F21: =E21*(1+$B$16*(Parametres!$B$24-1)) -> 214.87537 | G21: =ROUNDUP(B21/F21,0) -> 1 | H21: =MAX(1,C21*(1-$B$15/($B$15+Parametres!$B$25))) -> 9.281768 | I21: =ROUND(H21*MAX(0,G21-1),0) -> 0 | J21: =$B$13-I21 -> 1131 | K21: =IF(J21>0,"OK","ECHEC") -> OK
A22: 2 | B22: =ROUND(Parametres!$B$52*A22^Parametres!$B$53*(1+Parametres!$B$58)^($B$6-1)*IF(A22=Parametres!$B$51,Parametres!$B$59,1),0) -> 193 | C22: =ROUND(Parametres!$B$54*A22^Parametres!$B$55*(1+Parametres!$B$58)^($B$6-1)*IF(A22=Parametres!$B$51,Parametres!$B$60,1),0) -> 36 | D22: =ROUND(Parametres!$B$56*A22^Parametres!$B$57*(1+Parametres!$B$58)^($B$6-1),0) -> 15 | E22: =MAX(1,$B$14*(1-D22/(D22+Parametres!$B$25))) -> 178.52632 | F22: =E22*(1+$B$16*(Parametres!$B$24-1)) -> 199.04244 | G22: =ROUNDUP(B22/F22,0) -> 1 | H22: =MAX(1,C22*(1-$B$15/($B$15+Parametres!$B$25))) -> 15.911602 | I22: =ROUND(H22*MAX(0,G22-1),0) -> 0 | J22: =MIN($B$13,J21+ROUND($B$13*Parametres!$B$26,0))-I22 -> 1131 | K22: =IF(AND(K21="OK",J22>0),"OK","ECHEC") -> OK
A23: 3 | B23: =ROUND(Parametres!$B$52*A23^Parametres!$B$53*(1+Parametres!$B$58)^($B$6-1)*IF(A23=Parametres!$B$51,Parametres!$B$59,1),0) -> 279 | C23: =ROUND(Parametres!$B$54*A23^Parametres!$B$55*(1+Parametres!$B$58)^($B$6-1)*IF(A23=Parametres!$B$51,Parametres!$B$60,1),0) -> 50 | D23: =ROUND(Parametres!$B$56*A23^Parametres!$B$57*(1+Parametres!$B$58)^($B$6-1),0) -> 21 | E23: =MAX(1,$B$14*(1-D23/(D23+Parametres!$B$25))) -> 167.92079 | F23: =E23*(1+$B$16*(Parametres!$B$24-1)) -> 187.21814 | G23: =ROUNDUP(B23/F23,0) -> 2 | H23: =MAX(1,C23*(1-$B$15/($B$15+Parametres!$B$25))) -> 22.099448 | I23: =ROUND(H23*MAX(0,G23-1),0) -> 22 | J23: =MIN($B$13,J22+ROUND($B$13*Parametres!$B$26,0))-I23 -> 1109 | K23: =IF(AND(K22="OK",J23>0),"OK","ECHEC") -> OK
A24: 4 | B24: =ROUND(Parametres!$B$52*A24^Parametres!$B$53*(1+Parametres!$B$58)^($B$6-1)*IF(A24=Parametres!$B$51,Parametres!$B$59,1),0) -> 361 | C24: =ROUND(Parametres!$B$54*A24^Parametres!$B$55*(1+Parametres!$B$58)^($B$6-1)*IF(A24=Parametres!$B$51,Parametres!$B$60,1),0) -> 63 | D24: =ROUND(Parametres!$B$56*A24^Parametres!$B$57*(1+Parametres!$B$58)^($B$6-1),0) -> 27 | E24: =MAX(1,$B$14*(1-D24/(D24+Parametres!$B$25))) -> 158.50467 | F24: =E24*(1+$B$16*(Parametres!$B$24-1)) -> 176.71993 | G24: =ROUNDUP(B24/F24,0) -> 3 | H24: =MAX(1,C24*(1-$B$15/($B$15+Parametres!$B$25))) -> 27.845304 | I24: =ROUND(H24*MAX(0,G24-1),0) -> 56 | J24: =MIN($B$13,J23+ROUND($B$13*Parametres!$B$26,0))-I24 -> 1075 | K24: =IF(AND(K23="OK",J24>0),"OK","ECHEC") -> OK
A25: 5 | B25: =ROUND(Parametres!$B$52*A25^Parametres!$B$53*(1+Parametres!$B$58)^($B$6-1)*IF(A25=Parametres!$B$51,Parametres!$B$59,1),0) -> 441 | C25: =ROUND(Parametres!$B$54*A25^Parametres!$B$55*(1+Parametres!$B$58)^($B$6-1)*IF(A25=Parametres!$B$51,Parametres!$B$60,1),0) -> 75 | D25: =ROUND(Parametres!$B$56*A25^Parametres!$B$57*(1+Parametres!$B$58)^($B$6-1),0) -> 33 | E25: =MAX(1,$B$14*(1-D25/(D25+Parametres!$B$25))) -> 150.0885 | F25: =E25*(1+$B$16*(Parametres!$B$24-1)) -> 167.33657 | G25: =ROUNDUP(B25/F25,0) -> 3 | H25: =MAX(1,C25*(1-$B$15/($B$15+Parametres!$B$25))) -> 33.149171 | I25: =ROUND(H25*MAX(0,G25-1),0) -> 66 | J25: =MIN($B$13,J24+ROUND($B$13*Parametres!$B$26,0))-I25 -> 1065 | K25: =IF(AND(K24="OK",J25>0),"OK","ECHEC") -> OK
A26: 6 | B26: =ROUND(Parametres!$B$52*A26^Parametres!$B$53*(1+Parametres!$B$58)^($B$6-1)*IF(A26=Parametres!$B$51,Parametres!$B$59,1),0) -> 520 | C26: =ROUND(Parametres!$B$54*A26^Parametres!$B$55*(1+Parametres!$B$58)^($B$6-1)*IF(A26=Parametres!$B$51,Parametres!$B$60,1),0) -> 87 | D26: =ROUND(Parametres!$B$56*A26^Parametres!$B$57*(1+Parametres!$B$58)^($B$6-1),0) -> 38 | E26: =MAX(1,$B$14*(1-D26/(D26+Parametres!$B$25))) -> 143.72881 | F26: =E26*(1+$B$16*(Parametres!$B$24-1)) -> 160.24604 | G26: =ROUNDUP(B26/F26,0) -> 4 | H26: =MAX(1,C26*(1-$B$15/($B$15+Parametres!$B$25))) -> 38.453039 | I26: =ROUND(H26*MAX(0,G26-1),0) -> 115 | J26: =MIN($B$13,J25+ROUND($B$13*Parametres!$B$26,0))-I26 -> 1016 | K26: =IF(AND(K25="OK",J26>0),"OK","ECHEC") -> OK
A27: 7 | B27: =ROUND(Parametres!$B$52*A27^Parametres!$B$53*(1+Parametres!$B$58)^($B$6-1)*IF(A27=Parametres!$B$51,Parametres!$B$59,1),0) -> 597 | C27: =ROUND(Parametres!$B$54*A27^Parametres!$B$55*(1+Parametres!$B$58)^($B$6-1)*IF(A27=Parametres!$B$51,Parametres!$B$60,1),0) -> 98 | D27: =ROUND(Parametres!$B$56*A27^Parametres!$B$57*(1+Parametres!$B$58)^($B$6-1),0) -> 43 | E27: =MAX(1,$B$14*(1-D27/(D27+Parametres!$B$25))) -> 137.88618 | F27: =E27*(1+$B$16*(Parametres!$B$24-1)) -> 153.73197 | G27: =ROUNDUP(B27/F27,0) -> 4 | H27: =MAX(1,C27*(1-$B$15/($B$15+Parametres!$B$25))) -> 43.314917 | I27: =ROUND(H27*MAX(0,G27-1),0) -> 130 | J27: =MIN($B$13,J26+ROUND($B$13*Parametres!$B$26,0))-I27 -> 1001 | K27: =IF(AND(K26="OK",J27>0),"OK","ECHEC") -> OK
A28: 8 | B28: =ROUND(Parametres!$B$52*A28^Parametres!$B$53*(1+Parametres!$B$58)^($B$6-1)*IF(A28=Parametres!$B$51,Parametres!$B$59,1),0) -> 674 | C28: =ROUND(Parametres!$B$54*A28^Parametres!$B$55*(1+Parametres!$B$58)^($B$6-1)*IF(A28=Parametres!$B$51,Parametres!$B$60,1),0) -> 109 | D28: =ROUND(Parametres!$B$56*A28^Parametres!$B$57*(1+Parametres!$B$58)^($B$6-1),0) -> 49 | E28: =MAX(1,$B$14*(1-D28/(D28+Parametres!$B$25))) -> 131.47287 | F28: =E28*(1+$B$16*(Parametres!$B$24-1)) -> 146.58165 | G28: =ROUNDUP(B28/F28,0) -> 5 | H28: =MAX(1,C28*(1-$B$15/($B$15+Parametres!$B$25))) -> 48.176796 | I28: =ROUND(H28*MAX(0,G28-1),0) -> 193 | J28: =MIN($B$13,J27+ROUND($B$13*Parametres!$B$26,0))-I28 -> 938 | K28: =IF(AND(K27="OK",J28>0),"OK","ECHEC") -> OK
A29: 9 | B29: =ROUND(Parametres!$B$52*A29^Parametres!$B$53*(1+Parametres!$B$58)^($B$6-1)*IF(A29=Parametres!$B$51,Parametres!$B$59,1),0) -> 749 | C29: =ROUND(Parametres!$B$54*A29^Parametres!$B$55*(1+Parametres!$B$58)^($B$6-1)*IF(A29=Parametres!$B$51,Parametres!$B$60,1),0) -> 120 | D29: =ROUND(Parametres!$B$56*A29^Parametres!$B$57*(1+Parametres!$B$58)^($B$6-1),0) -> 54 | E29: =MAX(1,$B$14*(1-D29/(D29+Parametres!$B$25))) -> 126.56716 | F29: =E29*(1+$B$16*(Parametres!$B$24-1)) -> 141.11218 | G29: =ROUNDUP(B29/F29,0) -> 6 | H29: =MAX(1,C29*(1-$B$15/($B$15+Parametres!$B$25))) -> 53.038674 | I29: =ROUND(H29*MAX(0,G29-1),0) -> 265 | J29: =MIN($B$13,J28+ROUND($B$13*Parametres!$B$26,0))-I29 -> 866 | K29: =IF(AND(K28="OK",J29>0),"OK","ECHEC") -> OK
A30: 10 | B30: =ROUND(Parametres!$B$52*A30^Parametres!$B$53*(1+Parametres!$B$58)^($B$6-1)*IF(A30=Parametres!$B$51,Parametres!$B$59,1),0) -> 1812 | C30: =ROUND(Parametres!$B$54*A30^Parametres!$B$55*(1+Parametres!$B$58)^($B$6-1)*IF(A30=Parametres!$B$51,Parametres!$B$60,1),0) -> 196 | D30: =ROUND(Parametres!$B$56*A30^Parametres!$B$57*(1+Parametres!$B$58)^($B$6-1),0) -> 59 | E30: =MAX(1,$B$14*(1-D30/(D30+Parametres!$B$25))) -> 122.01439 | F30: =E30*(1+$B$16*(Parametres!$B$24-1)) -> 136.0362 | G30: =ROUNDUP(B30/F30,0) -> 14 | H30: =MAX(1,C30*(1-$B$15/($B$15+Parametres!$B$25))) -> 86.629834 | I30: =ROUND(H30*MAX(0,G30-1),0) -> 1126 | J30: =MIN($B$13,J29+ROUND($B$13*Parametres!$B$26,0))-I30 -> 5 | K30: =IF(AND(K29="OK",J30>0),"OK","ECHEC") -> OK
A32: VERDICT
A33: Palier le plus loin nettoye | B33: =SUMPRODUCT(MAX((K21:K30="OK")*A21:A30)) -> 10
A34: Run complete ? | B34: =IF(K30="OK","OUI — cycle nettoye","NON — retour au palier 1") -> OUI — cycle nettoye
A35: Marge de PV a la fin | B35: =J30 -> 5
A36: Diagnostic | B36: =IF(J30>$B$13*0.4,"Trop facile — augmente le cycle ou la croissance par cycle",IF(J30>0,"Bien calibre — victoire mais serree","Trop dur — il faut plus de niveau ou d'equipement")) -> Bien calibre — victoire mais serree
A38: Regle de calibrage : une run reussie a niveau approprie doit se terminer avec 5 a 25% des PV. Au-dela de 40%, augmente le cycle. En dessous de 0, il faut du niveau ou de l'equipement.

Sheet Equipement
A1: EQUIPEMENT — 6 emplacements, 5 raretes, forge
A2: Puissance = (base + palier x coefficient) x multiplicateur de rarete x croissance du cycle. Les objets tombent rarement : la fusion, pas le drop, est la vraie source d'equipement.
D3: Cycle de reference | E3: 1 | F3: Les objets se bonifient avec le cycle, sinon l'equipement plafonnerait des le cycle 1.
A4: LES 6 EMPLACEMENTS
A5: Emplacement | B5: Stat principale | C5: Stat secondaire | D5: Poids de puissance | E5: Role
A6: Arme | B6: ATQ | C6: Critique | D6: 1 | E6: La source principale de degats.
A7: Casque | B7: PV | C7: DEF | D7: 0.5 | E7: Survie de base.
A8: Plastron | B8: PV | C8: DEF | D8: 0.7 | E8: Le plus gros bloc defensif.
A9: Jambieres | B9: DEF | C9: PV | D9: 0.5 | E9: Defense secondaire.
A10: Bague | B10: Critique | C10: ATQ | D10: 0.35 | E10: Amplifie l'arme.
A11: Collier | B11: Chance | C11: Bonus XP | D11: 0.35 | E11: Ameliore le loot et l'XP — l'objet qui se cumule avec la nutrition.
A12: Total des poids | D12: =SUM(D6:D11) -> 3.4
A14: PUISSANCE BRUTE D'UN OBJET SELON LE PALIER ET LA RARETE | I14: Vente — or recu par objet
A15: Palier de drop | B15: Commun | C15: Rare | D15: Ultra-rare | E15: Mythique | F15: Legendaire | G15: Ecart Legendaire / Commun | I15: Commun | J15: Rare | K15: Ultra-rare | L15: Mythique | M15: Legendaire
A16: 1 | B16: =ROUND((Parametres!$B$86+Parametres!$B$87*$A16)*Parametres!$B$88*(1+Parametres!$B$58)^($E$3-1),0) -> 10 | C16: =ROUND((Parametres!$B$86+Parametres!$B$87*$A16)*Parametres!$B$89*(1+Parametres!$B$58)^($E$3-1),0) -> 16 | D16: =ROUND((Parametres!$B$86+Parametres!$B$87*$A16)*Parametres!$B$90*(1+Parametres!$B$58)^($E$3-1),0) -> 26 | E16: =ROUND((Parametres!$B$86+Parametres!$B$87*$A16)*Parametres!$B$91*(1+Parametres!$B$58)^($E$3-1),0) -> 42 | F16: =ROUND((Parametres!$B$86+Parametres!$B$87*$A16)*Parametres!$B$92*(1+Parametres!$B$58)^($E$3-1),0) -> 68 | G16: =F16/B16 -> 6.8 | I16: =ROUND(B16*Parametres!$B$110,0) -> 15 | J16: =ROUND(C16*Parametres!$B$110,0) -> 24 | K16: =ROUND(D16*Parametres!$B$110,0) -> 39 | L16: =ROUND(E16*Parametres!$B$110,0) -> 63 | M16: =ROUND(F16*Parametres!$B$110,0) -> 102
A17: 2 | B17: =ROUND((Parametres!$B$86+Parametres!$B$87*$A17)*Parametres!$B$88*(1+Parametres!$B$58)^($E$3-1),0) -> 14 | C17: =ROUND((Parametres!$B$86+Parametres!$B$87*$A17)*Parametres!$B$89*(1+Parametres!$B$58)^($E$3-1),0) -> 22 | D17: =ROUND((Parametres!$B$86+Parametres!$B$87*$A17)*Parametres!$B$90*(1+Parametres!$B$58)^($E$3-1),0) -> 36 | E17: =ROUND((Parametres!$B$86+Parametres!$B$87*$A17)*Parametres!$B$91*(1+Parametres!$B$58)^($E$3-1),0) -> 59 | F17: =ROUND((Parametres!$B$86+Parametres!$B$87*$A17)*Parametres!$B$92*(1+Parametres!$B$58)^($E$3-1),0) -> 95 | G17: =F17/B17 -> 6.7857143 | I17: =ROUND(B17*Parametres!$B$110,0) -> 21 | J17: =ROUND(C17*Parametres!$B$110,0) -> 33 | K17: =ROUND(D17*Parametres!$B$110,0) -> 54 | L17: =ROUND(E17*Parametres!$B$110,0) -> 89 | M17: =ROUND(F17*Parametres!$B$110,0) -> 143
A18: 3 | B18: =ROUND((Parametres!$B$86+Parametres!$B$87*$A18)*Parametres!$B$88*(1+Parametres!$B$58)^($E$3-1),0) -> 18 | C18: =ROUND((Parametres!$B$86+Parametres!$B$87*$A18)*Parametres!$B$89*(1+Parametres!$B$58)^($E$3-1),0) -> 29 | D18: =ROUND((Parametres!$B$86+Parametres!$B$87*$A18)*Parametres!$B$90*(1+Parametres!$B$58)^($E$3-1),0) -> 47 | E18: =ROUND((Parametres!$B$86+Parametres!$B$87*$A18)*Parametres!$B$91*(1+Parametres!$B$58)^($E$3-1),0) -> 76 | F18: =ROUND((Parametres!$B$86+Parametres!$B$87*$A18)*Parametres!$B$92*(1+Parametres!$B$58)^($E$3-1),0) -> 122 | G18: =F18/B18 -> 6.7777778 | I18: =ROUND(B18*Parametres!$B$110,0) -> 27 | J18: =ROUND(C18*Parametres!$B$110,0) -> 44 | K18: =ROUND(D18*Parametres!$B$110,0) -> 71 | L18: =ROUND(E18*Parametres!$B$110,0) -> 114 | M18: =ROUND(F18*Parametres!$B$110,0) -> 183
A19: 4 | B19: =ROUND((Parametres!$B$86+Parametres!$B$87*$A19)*Parametres!$B$88*(1+Parametres!$B$58)^($E$3-1),0) -> 22 | C19: =ROUND((Parametres!$B$86+Parametres!$B$87*$A19)*Parametres!$B$89*(1+Parametres!$B$58)^($E$3-1),0) -> 35 | D19: =ROUND((Parametres!$B$86+Parametres!$B$87*$A19)*Parametres!$B$90*(1+Parametres!$B$58)^($E$3-1),0) -> 57 | E19: =ROUND((Parametres!$B$86+Parametres!$B$87*$A19)*Parametres!$B$91*(1+Parametres!$B$58)^($E$3-1),0) -> 92 | F19: =ROUND((Parametres!$B$86+Parametres!$B$87*$A19)*Parametres!$B$92*(1+Parametres!$B$58)^($E$3-1),0) -> 150 | G19: =F19/B19 -> 6.8181818 | I19: =ROUND(B19*Parametres!$B$110,0) -> 33 | J19: =ROUND(C19*Parametres!$B$110,0) -> 53 | K19: =ROUND(D19*Parametres!$B$110,0) -> 86 | L19: =ROUND(E19*Parametres!$B$110,0) -> 138 | M19: =ROUND(F19*Parametres!$B$110,0) -> 225
A20: 5 | B20: =ROUND((Parametres!$B$86+Parametres!$B$87*$A20)*Parametres!$B$88*(1+Parametres!$B$58)^($E$3-1),0) -> 26 | C20: =ROUND((Parametres!$B$86+Parametres!$B$87*$A20)*Parametres!$B$89*(1+Parametres!$B$58)^($E$3-1),0) -> 42 | D20: =ROUND((Parametres!$B$86+Parametres!$B$87*$A20)*Parametres!$B$90*(1+Parametres!$B$58)^($E$3-1),0) -> 68 | E20: =ROUND((Parametres!$B$86+Parametres!$B$87*$A20)*Parametres!$B$91*(1+Parametres!$B$58)^($E$3-1),0) -> 109 | F20: =ROUND((Parametres!$B$86+Parametres!$B$87*$A20)*Parametres!$B$92*(1+Parametres!$B$58)^($E$3-1),0) -> 177 | G20: =F20/B20 -> 6.8076923 | I20: =ROUND(B20*Parametres!$B$110,0) -> 39 | J20: =ROUND(C20*Parametres!$B$110,0) -> 63 | K20: =ROUND(D20*Parametres!$B$110,0) -> 102 | L20: =ROUND(E20*Parametres!$B$110,0) -> 164 | M20: =ROUND(F20*Parametres!$B$110,0) -> 266
A21: 6 | B21: =ROUND((Parametres!$B$86+Parametres!$B$87*$A21)*Parametres!$B$88*(1+Parametres!$B$58)^($E$3-1),0) -> 30 | C21: =ROUND((Parametres!$B$86+Parametres!$B$87*$A21)*Parametres!$B$89*(1+Parametres!$B$58)^($E$3-1),0) -> 48 | D21: =ROUND((Parametres!$B$86+Parametres!$B$87*$A21)*Parametres!$B$90*(1+Parametres!$B$58)^($E$3-1),0) -> 78 | E21: =ROUND((Parametres!$B$86+Parametres!$B$87*$A21)*Parametres!$B$91*(1+Parametres!$B$58)^($E$3-1),0) -> 126 | F21: =ROUND((Parametres!$B$86+Parametres!$B$87*$A21)*Parametres!$B$92*(1+Parametres!$B$58)^($E$3-1),0) -> 204 | G21: =F21/B21 -> 6.8 | I21: =ROUND(B21*Parametres!$B$110,0) -> 45 | J21: =ROUND(C21*Parametres!$B$110,0) -> 72 | K21: =ROUND(D21*Parametres!$B$110,0) -> 117 | L21: =ROUND(E21*Parametres!$B$110,0) -> 189 | M21: =ROUND(F21*Parametres!$B$110,0) -> 306
A22: 7 | B22: =ROUND((Parametres!$B$86+Parametres!$B$87*$A22)*Parametres!$B$88*(1+Parametres!$B$58)^($E$3-1),0) -> 34 | C22: =ROUND((Parametres!$B$86+Parametres!$B$87*$A22)*Parametres!$B$89*(1+Parametres!$B$58)^($E$3-1),0) -> 54 | D22: =ROUND((Parametres!$B$86+Parametres!$B$87*$A22)*Parametres!$B$90*(1+Parametres!$B$58)^($E$3-1),0) -> 88 | E22: =ROUND((Parametres!$B$86+Parametres!$B$87*$A22)*Parametres!$B$91*(1+Parametres!$B$58)^($E$3-1),0) -> 143 | F22: =ROUND((Parametres!$B$86+Parametres!$B$87*$A22)*Parametres!$B$92*(1+Parametres!$B$58)^($E$3-1),0) -> 231 | G22: =F22/B22 -> 6.7941176 | I22: =ROUND(B22*Parametres!$B$110,0) -> 51 | J22: =ROUND(C22*Parametres!$B$110,0) -> 81 | K22: =ROUND(D22*Parametres!$B$110,0) -> 132 | L22: =ROUND(E22*Parametres!$B$110,0) -> 215 | M22: =ROUND(F22*Parametres!$B$110,0) -> 347
A23: 8 | B23: =ROUND((Parametres!$B$86+Parametres!$B$87*$A23)*Parametres!$B$88*(1+Parametres!$B$58)^($E$3-1),0) -> 38 | C23: =ROUND((Parametres!$B$86+Parametres!$B$87*$A23)*Parametres!$B$89*(1+Parametres!$B$58)^($E$3-1),0) -> 61 | D23: =ROUND((Parametres!$B$86+Parametres!$B$87*$A23)*Parametres!$B$90*(1+Parametres!$B$58)^($E$3-1),0) -> 99 | E23: =ROUND((Parametres!$B$86+Parametres!$B$87*$A23)*Parametres!$B$91*(1+Parametres!$B$58)^($E$3-1),0) -> 160 | F23: =ROUND((Parametres!$B$86+Parametres!$B$87*$A23)*Parametres!$B$92*(1+Parametres!$B$58)^($E$3-1),0) -> 258 | G23: =F23/B23 -> 6.7894737 | I23: =ROUND(B23*Parametres!$B$110,0) -> 57 | J23: =ROUND(C23*Parametres!$B$110,0) -> 92 | K23: =ROUND(D23*Parametres!$B$110,0) -> 149 | L23: =ROUND(E23*Parametres!$B$110,0) -> 240 | M23: =ROUND(F23*Parametres!$B$110,0) -> 387
A24: 9 | B24: =ROUND((Parametres!$B$86+Parametres!$B$87*$A24)*Parametres!$B$88*(1+Parametres!$B$58)^($E$3-1),0) -> 42 | C24: =ROUND((Parametres!$B$86+Parametres!$B$87*$A24)*Parametres!$B$89*(1+Parametres!$B$58)^($E$3-1),0) -> 67 | D24: =ROUND((Parametres!$B$86+Parametres!$B$87*$A24)*Parametres!$B$90*(1+Parametres!$B$58)^($E$3-1),0) -> 109 | E24: =ROUND((Parametres!$B$86+Parametres!$B$87*$A24)*Parametres!$B$91*(1+Parametres!$B$58)^($E$3-1),0) -> 176 | F24: =ROUND((Parametres!$B$86+Parametres!$B$87*$A24)*Parametres!$B$92*(1+Parametres!$B$58)^($E$3-1),0) -> 286 | G24: =F24/B24 -> 6.8095238 | I24: =ROUND(B24*Parametres!$B$110,0) -> 63 | J24: =ROUND(C24*Parametres!$B$110,0) -> 101 | K24: =ROUND(D24*Parametres!$B$110,0) -> 164 | L24: =ROUND(E24*Parametres!$B$110,0) -> 264 | M24: =ROUND(F24*Parametres!$B$110,0) -> 429
A25: 10 | B25: =ROUND((Parametres!$B$86+Parametres!$B$87*$A25)*Parametres!$B$88*(1+Parametres!$B$58)^($E$3-1),0) -> 46 | C25: =ROUND((Parametres!$B$86+Parametres!$B$87*$A25)*Parametres!$B$89*(1+Parametres!$B$58)^($E$3-1),0) -> 74 | D25: =ROUND((Parametres!$B$86+Parametres!$B$87*$A25)*Parametres!$B$90*(1+Parametres!$B$58)^($E$3-1),0) -> 120 | E25: =ROUND((Parametres!$B$86+Parametres!$B$87*$A25)*Parametres!$B$91*(1+Parametres!$B$58)^($E$3-1),0) -> 193 | F25: =ROUND((Parametres!$B$86+Parametres!$B$87*$A25)*Parametres!$B$92*(1+Parametres!$B$58)^($E$3-1),0) -> 313 | G25: =F25/B25 -> 6.8043478 | I25: =ROUND(B25*Parametres!$B$110,0) -> 69 | J25: =ROUND(C25*Parametres!$B$110,0) -> 111 | K25: =ROUND(D25*Parametres!$B$110,0) -> 180 | L25: =ROUND(E25*Parametres!$B$110,0) -> 290 | M25: =ROUND(F25*Parametres!$B$110,0) -> 470
A27: Un legendaire du palier 1 (puissance ~42) vaut moins qu'un commun du palier 10 (~46). La progression dans le donjon prime toujours sur la chance : impossible de sauter des etapes avec un coup de chance.
A28: Boucle fermee : monter de cycle donne de meilleurs objets, qui permettent de monter de cycle. Mais le NIVEAU (PV/ATQ/DEF) reste le vrai plafond, et il n'existe que par l'entrainement reel. Impossible de farmer sa sortie d'un mur.
A29: FORGE — ameliorer un objet deja possede (paye en Gemmes)
A30: Les Gemmes viennent UNIQUEMENT des montees de niveau, donc de vrai entrainement. La forge est la recompense directe de la salle.
A31: Niveau de forge | B31: Gain cumule | C31: Multiplicateur total | D31: Cout en gemmes | E31: Cout cumule | F31: Niveaux a monter pour se le payer
A32: 0 | B32: =A32*Parametres!$B$93 -> 0 | C32: =1+B32 -> 1 | D32: =IF(A32=0,0,ROUND(Parametres!$B$95*Parametres!$B$96^(A32-1),0)) -> 0 | E32: =D32 -> 0 | F32: =ROUND(E32/(Parametres!$B$70+Parametres!$B$71),1) -> 0
A33: 1 | B33: =A33*Parametres!$B$93 -> 0.08 | C33: =1+B33 -> 1.08 | D33: =IF(A33=0,0,ROUND(Parametres!$B$95*Parametres!$B$96^(A33-1),0)) -> 5 | E33: =E32+D33 -> 5 | F33: =ROUND(E33/(Parametres!$B$70+Parametres!$B$71),1) -> 1.3
A34: 2 | B34: =A34*Parametres!$B$93 -> 0.16 | C34: =1+B34 -> 1.16 | D34: =IF(A34=0,0,ROUND(Parametres!$B$95*Parametres!$B$96^(A34-1),0)) -> 6 | E34: =E33+D34 -> 11 | F34: =ROUND(E34/(Parametres!$B$70+Parametres!$B$71),1) -> 2.8
A35: 3 | B35: =A35*Parametres!$B$93 -> 0.24 | C35: =1+B35 -> 1.24 | D35: =IF(A35=0,0,ROUND(Parametres!$B$95*Parametres!$B$96^(A35-1),0)) -> 7 | E35: =E34+D35 -> 18 | F35: =ROUND(E35/(Parametres!$B$70+Parametres!$B$71),1) -> 4.5
A36: 4 | B36: =A36*Parametres!$B$93 -> 0.32 | C36: =1+B36 -> 1.32 | D36: =IF(A36=0,0,ROUND(Parametres!$B$95*Parametres!$B$96^(A36-1),0)) -> 9 | E36: =E35+D36 -> 27 | F36: =ROUND(E36/(Parametres!$B$70+Parametres!$B$71),1) -> 6.8
A37: 5 | B37: =A37*Parametres!$B$93 -> 0.4 | C37: =1+B37 -> 1.4 | D37: =IF(A37=0,0,ROUND(Parametres!$B$95*Parametres!$B$96^(A37-1),0)) -> 11 | E37: =E36+D37 -> 38 | F37: =ROUND(E37/(Parametres!$B$70+Parametres!$B$71),1) -> 9.5
A38: 6 | B38: =A38*Parametres!$B$93 -> 0.48 | C38: =1+B38 -> 1.48 | D38: =IF(A38=0,0,ROUND(Parametres!$B$95*Parametres!$B$96^(A38-1),0)) -> 14 | E38: =E37+D38 -> 52 | F38: =ROUND(E38/(Parametres!$B$70+Parametres!$B$71),1) -> 13
A39: 7 | B39: =A39*Parametres!$B$93 -> 0.56 | C39: =1+B39 -> 1.56 | D39: =IF(A39=0,0,ROUND(Parametres!$B$95*Parametres!$B$96^(A39-1),0)) -> 16 | E39: =E38+D39 -> 68 | F39: =ROUND(E39/(Parametres!$B$70+Parametres!$B$71),1) -> 17
A40: 8 | B40: =A40*Parametres!$B$93 -> 0.64 | C40: =1+B40 -> 1.64 | D40: =IF(A40=0,0,ROUND(Parametres!$B$95*Parametres!$B$96^(A40-1),0)) -> 20 | E40: =E39+D40 -> 88 | F40: =ROUND(E40/(Parametres!$B$70+Parametres!$B$71),1) -> 22
A41: 9 | B41: =A41*Parametres!$B$93 -> 0.72 | C41: =1+B41 -> 1.72 | D41: =IF(A41=0,0,ROUND(Parametres!$B$95*Parametres!$B$96^(A41-1),0)) -> 25 | E41: =E40+D41 -> 113 | F41: =ROUND(E41/(Parametres!$B$70+Parametres!$B$71),1) -> 28.3
A42: 10 | B42: =A42*Parametres!$B$93 -> 0.8 | C42: =1+B42 -> 1.8 | D42: =IF(A42=0,0,ROUND(Parametres!$B$95*Parametres!$B$96^(A42-1),0)) -> 30 | E42: =E41+D42 -> 143 | F42: =ROUND(E42/(Parametres!$B$70+Parametres!$B$71),1) -> 35.8
A44: Forge max sur un objet = +80% de puissance. Cout total ~ une douzaine de montees de niveau. Un objet forge au maximum reste donc un choix : on ne peut pas tout monter.

Sheet Fusion-Vente
A1: FUSION & VENTE — que faire d'un objet
A2: Trois objets de meme rarete ET meme emplacement fusionnent en un objet de la rarete au-dessus. L'objet obtenu herite du PALIER LE PLUS ELEVE des trois. Tout le reste se vend.
A4: L'ECHELLE DE RARETE ET SON COUT REEL
A5: Rarete | B5: Multiplicateur de puissance | C5: Fusions cumulees | D5: Cout en communs (equivalents) | E5: Poids de drop direct | F5: Probabilite de drop direct | G5: Chemin realiste
A6: Commun | B6: =Parametres!$B$88 -> 1 | C6: 0 | D6: =Parametres!$B$107^C6 -> 1 | E6: =Parametres!$B$75 -> 70 | F6: =E6/SUM($E$6:$E$10) -> 0.7 | G6: Le minerai. Tu en auras beaucoup.
A7: Rare | B7: =Parametres!$B$89 -> 1.6 | C7: 1 | D7: =Parametres!$B$107^C7 -> 3 | E7: =Parametres!$B$76 -> 22 | F7: =E7/SUM($E$6:$E$10) -> 0.22 | G7: Fusion de 3 communs, ou drop direct frequent.
A8: Ultra-rare | B8: =Parametres!$B$90 -> 2.6 | C8: 2 | D8: =Parametres!$B$107^C8 -> 9 | E8: =Parametres!$B$77 -> 6.5 | F8: =E8/SUM($E$6:$E$10) -> 0.065 | G8: Fusion. Un drop direct reste une bonne surprise.
A9: Mythique | B9: =Parametres!$B$91 -> 4.2 | C9: 3 | D9: =Parametres!$B$107^C9 -> 27 | E9: =Parametres!$B$78 -> 1.4 | F9: =E9/SUM($E$6:$E$10) -> 0.014 | G9: Fusion presque toujours. 9 fusions en amont.
A10: Legendaire | B10: =Parametres!$B$92 -> 6.8 | C10: 4 | D10: =Parametres!$B$107^C10 -> 81 | E10: =Parametres!$B$79 -> 0.1 | F10: =E10/SUM($E$6:$E$10) -> 0.001 | G10: Fusion uniquement, en pratique. 40 fusions en amont.
A12: RYTHME REEL D'ACQUISITION
A13: La fusion exige le meme emplacement, donc le flux se divise par 6. C'est ce qui empeche d'avoir six pieces legendaires en trois mois.
A15: Objets largues par semaine (tous emplacements) | B15: =ROUND(Parametres!$B$111*Parametres!$B$74,1) -> 5.6
A16: Objets largues par semaine et par emplacement | B16: =ROUND(B15/Parametres!$B$108,2) -> 0.93
A17: Valeur moyenne d'un drop (en communs-equivalents) | B17: =SUMPRODUCT($F$6:$F$10,$D$6:$D$10) -> 2.404
A18: Communs-equivalents par semaine et par emplacement | B18: =B16*B17 -> 2.23572
A20: TEMPS POUR OBTENIR UNE PIECE, PAR EMPLACEMENT
A21: Rarete visee | B21: Communs-equivalents requis | C21: Semaines | D21: Mois | E21: Ressenti
A22: Commun | B22: =D6 -> 1 | C22: =ROUND(B22/$B$18,1) -> 0.4 | D22: =ROUND(C22/4.345,1) -> 0.1 | E22: Immediat.
A23: Rare | B23: =D7 -> 3 | C23: =ROUND(B23/$B$18,1) -> 1.3 | D23: =ROUND(C23/4.345,1) -> 0.3 | E23: Quelques jours.
A24: Ultra-rare | B24: =D8 -> 9 | C24: =ROUND(B24/$B$18,1) -> 4 | D24: =ROUND(C24/4.345,1) -> 0.9 | E24: Environ deux semaines.
A25: Mythique | B25: =D9 -> 27 | C25: =ROUND(B25/$B$18,1) -> 12.1 | D25: =ROUND(C25/4.345,1) -> 2.8 | E25: Un objectif mensuel — ca se planifie.
A26: Legendaire | B26: =D10 -> 81 | C26: =ROUND(B26/$B$18,1) -> 36.2 | D26: =ROUND(C26/4.345,1) -> 8.3 | E26: L'objectif de l'annee. Une seule piece a la fois.
A28: FUSION CHANCEUSE — ou la nutrition paie vraiment
A29: Chaque fusion peut sauter DEUX raretes au lieu d'une. La probabilite vient uniquement de la Chance, donc de la serie nutrition et du collier.
A30: Points de Chance | B30: Probabilite de saut double | C30: Communs-equivalents economises | D30: Semaines gagnees sur un Legendaire
A31: 0 | B31: =A31*Parametres!$B$109 -> 0 | C31: =ROUND($D$10*B31,1) -> 0 | D31: =ROUND(C31/$B$18,1) -> 0
A32: 10 | B32: =A32*Parametres!$B$109 -> 0.05 | C32: =ROUND($D$10*B32,1) -> 4.1 | D32: =ROUND(C32/$B$18,1) -> 1.8
A33: 20 | B33: =A33*Parametres!$B$109 -> 0.1 | C33: =ROUND($D$10*B33,1) -> 8.1 | D33: =ROUND(C33/$B$18,1) -> 3.6
A34: 30 | B34: =A34*Parametres!$B$109 -> 0.15 | C34: =ROUND($D$10*B34,1) -> 12.2 | D34: =ROUND(C34/$B$18,1) -> 5.5
A35: 45 | B35: =A35*Parametres!$B$109 -> 0.225 | C35: =ROUND($D$10*B35,1) -> 18.2 | D35: =ROUND(C35/$B$18,1) -> 8.1
A37: VENTE — pourquoi ce n'est jamais un raccourci
A38: Verification | B38: Valeur | C38: Verdict
A39: Prix de vente d'un commun (palier 8) | B39: =Equipement!$I$23 -> 57
A40: Cout d'un coffre en or | B40: =Parametres!$B$67 -> 3000
A41: Communs a vendre pour payer un coffre | B41: =ROUND(B40/B39,0) -> 53
A42: Objets obtenus par coffre | B42: 1
A43: Ratio vendu / obtenu | B43: =B41 -> 53 | C43: Vendre pour racheter des coffres est toujours perdant : il faut sacrifier une dizaine d'objets pour en obtenir un seul. Aucune boucle infinie possible.
A45: LA DECISION, A CHAQUE OBJET
A46: Tu as deja 2 objets identiques | B46: FUSIONNE. Le 3e complete le triplet.
A47: Objet d'un palier plus haut que ton equipe | B47: EQUIPE-LE. Le palier prime sur la rarete a niveau egal.
A48: Commun d'un emplacement deja bien servi | B48: GARDE-LE quand meme si tu es a 1 ou 2 du triplet.
A49: Objet d'un palier tres bas, aucun triplet en vue | B49: VENDS. C'est le seul vrai dechet du systeme.
A50: Tu hesites entre fusionner et vendre | B50: FUSIONNE. La vente rapporte toujours moins que la puissance gagnee.
A53: COUT EN OR DE LA FUSION — le vrai usage de l'or
A54: Chaque etage de rarete coute le meme total en or. L'or ne fait jamais avancer seul : il debloque des fusions dont tu as deja la matiere.
A55: Fusion | B55: Cout unitaire (or) | C55: Fusions requises pour 1 Legendaire | D55: Or total a cet etage | E55: Semaines d'or
A56: 3 Communs -> 1 Rare | B56: =ROUND(Parametres!$B$112*Parametres!$B$113^0,0) -> 200 | C56: 27 | D56: =B56*C56 -> 5400 | E56: =ROUND(D56/Economie!$C$12,1) -> 1.6
A57: 3 Rares -> 1 Ultra-rare | B57: =ROUND(Parametres!$B$112*Parametres!$B$113^1,0) -> 600 | C57: 9 | D57: =B57*C57 -> 5400 | E57: =ROUND(D57/Economie!$C$12,1) -> 1.6
A58: 3 Ultra-rares -> 1 Mythique | B58: =ROUND(Parametres!$B$112*Parametres!$B$113^2,0) -> 1800 | C58: 3 | D58: =B58*C58 -> 5400 | E58: =ROUND(D58/Economie!$C$12,1) -> 1.6
A59: 3 Mythiques -> 1 Legendaire | B59: =ROUND(Parametres!$B$112*Parametres!$B$113^3,0) -> 5400 | C59: 1 | D59: =B59*C59 -> 5400 | E59: =ROUND(D59/Economie!$C$12,1) -> 1.6
A60: TOTAL — 1 Legendaire depuis zero | C60: =SUM(C56:C59) -> 40 | D60: =SUM(D56:D59) -> 21600 | E60: =SUM(E56:E59) -> 6.4
A62: Propriete voulue : les quatre etages coutent exactement le meme total. Fusionner du commun en masse coute aussi cher que la fusion finale — l'or reste utile du debut a la fin.

Sheet Loot-Pity
A1: LOOT & ANTI-MALCHANCE — taux de drop, Chance, pity
A2: Les drops sont rares (~1 objet tous les 10 paliers). Le hasard cree l'excitation, le pity plafonne le pire cas, et la fusion garantit que rien n'est jamais perdu.
A4: Points de Chance du joueur | B4: 20 | C4: Vient de la serie nutrition + du collier. Max nutrition = 30.
A6: TABLE DE RARETE
A7: Rarete | B7: Poids de base | C7: Facteur de Chance | D7: Poids effectif | E7: Probabilite (par objet largue) | F7: Objets a obtenir en moyenne | G7: Paliers a nettoyer en moyenne
A8: Commun | B8: =Parametres!$B$75 -> 70 | C8: 0 | D8: =B8*(1+$B$4*Parametres!$B$80*C8) -> 70 | E8: =D8/SUM($D$8:$D$12) -> 0.64862861 | F8: =1/E8 -> 1.5417143 | G8: =F8/Parametres!$B$74 -> 15.417143
A9: Rare | B9: =Parametres!$B$76 -> 22 | C9: 1 | D9: =B9*(1+$B$4*Parametres!$B$80*C9) -> 26.4 | E9: =D9/SUM($D$8:$D$12) -> 0.24462565 | F9: =1/E9 -> 4.0878788 | G9: =F9/Parametres!$B$74 -> 40.878788
A10: Ultra-rare | B10: =Parametres!$B$77 -> 6.5 | C10: 2 | D10: =B10*(1+$B$4*Parametres!$B$80*C10) -> 9.1 | E10: =D10/SUM($D$8:$D$12) -> 0.08432172 | F10: =1/E10 -> 11.859341 | G10: =F10/Parametres!$B$74 -> 118.59341
A11: Mythique | B11: =Parametres!$B$78 -> 1.4 | C11: 3 | D11: =B11*(1+$B$4*Parametres!$B$80*C11) -> 2.24 | E11: =D11/SUM($D$8:$D$12) -> 0.020756116 | F11: =1/E11 -> 48.178571 | G11: =F11/Parametres!$B$74 -> 481.78571
A12: Legendaire | B12: =Parametres!$B$79 -> 0.1 | C12: 4 | D12: =B12*(1+$B$4*Parametres!$B$80*C12) -> 0.18 | E12: =D12/SUM($D$8:$D$12) -> 0.0016679021 | F12: =1/E12 -> 599.55556 | G12: =F12/Parametres!$B$74 -> 5995.5556
A13: Total | D13: =SUM(D8:D12) -> 107.92 | E13: =SUM(E8:E12) -> 1
A15: PROBABILITE CUMULEE D'AVOIR AU MOINS 1 LEGENDAIRE
A16: Objets largues | B16: Sans pity | C16: Avec pity (doux + dur) | D16: Jours reels equivalents
A17: 10 | B17: =1-(1-$E$11)^A17 -> 0.18920945 | C17: =IF(A17>=Parametres!$B$83,1,1-(1-$E$11)^MIN(A17,Parametres!$B$81)*IF(A17>Parametres!$B$81,PRODUCT(1)*(1-$E$11-Parametres!$B$82)^(A17-Parametres!$B$81),1)) -> 0.18920945 | D17: =ROUND(A17/(Parametres!$B$74*8),0) -> 13
A18: 20 | B18: =1-(1-$E$11)^A18 -> 0.34261868 | C18: =IF(A18>=Parametres!$B$83,1,1-(1-$E$11)^MIN(A18,Parametres!$B$81)*IF(A18>Parametres!$B$81,PRODUCT(1)*(1-$E$11-Parametres!$B$82)^(A18-Parametres!$B$81),1)) -> 0.34261868 | D18: =ROUND(A18/(Parametres!$B$74*8),0) -> 25
A19: 30 | B19: =1-(1-$E$11)^A19 -> 0.46700144 | C19: =IF(A19>=Parametres!$B$83,1,1-(1-$E$11)^MIN(A19,Parametres!$B$81)*IF(A19>Parametres!$B$81,PRODUCT(1)*(1-$E$11-Parametres!$B$82)^(A19-Parametres!$B$81),1)) -> 0.46700144 | D19: =ROUND(A19/(Parametres!$B$74*8),0) -> 38
A20: 40 | B20: =1-(1-$E$11)^A20 -> 0.5678498 | C20: =IF(A20>=Parametres!$B$83,1,1-(1-$E$11)^MIN(A20,Parametres!$B$81)*IF(A20>Parametres!$B$81,PRODUCT(1)*(1-$E$11-Parametres!$B$82)^(A20-Parametres!$B$81),1)) -> 0.5678498 | D20: =ROUND(A20/(Parametres!$B$74*8),0) -> 50
A21: 50 | B21: =1-(1-$E$11)^A21 -> 0.6496167 | C21: =IF(A21>=Parametres!$B$83,1,1-(1-$E$11)^MIN(A21,Parametres!$B$81)*IF(A21>Parametres!$B$81,PRODUCT(1)*(1-$E$11-Parametres!$B$82)^(A21-Parametres!$B$81),1)) -> 0.74330773 | D21: =ROUND(A21/(Parametres!$B$74*8),0) -> 63
A22: 60 | B22: =1-(1-$E$11)^A22 -> 0.71591253 | C22: =IF(A22>=Parametres!$B$83,1,1-(1-$E$11)^MIN(A22,Parametres!$B$81)*IF(A22>Parametres!$B$81,PRODUCT(1)*(1-$E$11-Parametres!$B$82)^(A22-Parametres!$B$81),1)) -> 1 | D22: =ROUND(A22/(Parametres!$B$74*8),0) -> 75
A23: 80 | B23: =1-(1-$E$11)^A23 -> 0.81324621 | C23: =IF(A23>=Parametres!$B$83,1,1-(1-$E$11)^MIN(A23,Parametres!$B$81)*IF(A23>Parametres!$B$81,PRODUCT(1)*(1-$E$11-Parametres!$B$82)^(A23-Parametres!$B$81),1)) -> 1 | D23: =ROUND(A23/(Parametres!$B$74*8),0) -> 100
A24: Hypothese : ~8 paliers nettoyes par jour. Avec le pity dur, un legendaire est garanti au 60e objet largue, soit environ 3 semaines dans le pire des cas.
A26: COURBE DU PITY DOUX
A27: Objet largue n° | B27: Chance de legendaire a ce tirage | C27: Statut
A28: 1 | B28: =IF(A28>=Parametres!$B$83,1,MIN(1,$E$11+MAX(0,A28-Parametres!$B$81)*Parametres!$B$82)) -> 0.020756116 | C28: =IF(A28>=Parametres!$B$83,"GARANTI",IF(A28>=Parametres!$B$81,"Pity doux actif","Taux de base")) -> Taux de base
A29: 20 | B29: =IF(A29>=Parametres!$B$83,1,MIN(1,$E$11+MAX(0,A29-Parametres!$B$81)*Parametres!$B$82)) -> 0.020756116 | C29: =IF(A29>=Parametres!$B$83,"GARANTI",IF(A29>=Parametres!$B$81,"Pity doux actif","Taux de base")) -> Taux de base
A30: 39 | B30: =IF(A30>=Parametres!$B$83,1,MIN(1,$E$11+MAX(0,A30-Parametres!$B$81)*Parametres!$B$82)) -> 0.020756116 | C30: =IF(A30>=Parametres!$B$83,"GARANTI",IF(A30>=Parametres!$B$81,"Pity doux actif","Taux de base")) -> Taux de base
A31: 40 | B31: =IF(A31>=Parametres!$B$83,1,MIN(1,$E$11+MAX(0,A31-Parametres!$B$81)*Parametres!$B$82)) -> 0.020756116 | C31: =IF(A31>=Parametres!$B$83,"GARANTI",IF(A31>=Parametres!$B$81,"Pity doux actif","Taux de base")) -> Pity doux actif
A32: 45 | B32: =IF(A32>=Parametres!$B$83,1,MIN(1,$E$11+MAX(0,A32-Parametres!$B$81)*Parametres!$B$82)) -> 0.17075612 | C32: =IF(A32>=Parametres!$B$83,"GARANTI",IF(A32>=Parametres!$B$81,"Pity doux actif","Taux de base")) -> Pity doux actif
A33: 50 | B33: =IF(A33>=Parametres!$B$83,1,MIN(1,$E$11+MAX(0,A33-Parametres!$B$81)*Parametres!$B$82)) -> 0.32075612 | C33: =IF(A33>=Parametres!$B$83,"GARANTI",IF(A33>=Parametres!$B$81,"Pity doux actif","Taux de base")) -> Pity doux actif
A34: 55 | B34: =IF(A34>=Parametres!$B$83,1,MIN(1,$E$11+MAX(0,A34-Parametres!$B$81)*Parametres!$B$82)) -> 0.47075612 | C34: =IF(A34>=Parametres!$B$83,"GARANTI",IF(A34>=Parametres!$B$81,"Pity doux actif","Taux de base")) -> Pity doux actif
A35: 59 | B35: =IF(A35>=Parametres!$B$83,1,MIN(1,$E$11+MAX(0,A35-Parametres!$B$81)*Parametres!$B$82)) -> 0.59075612 | C35: =IF(A35>=Parametres!$B$83,"GARANTI",IF(A35>=Parametres!$B$81,"Pity doux actif","Taux de base")) -> Pity doux actif
A36: 60 | B36: =IF(A36>=Parametres!$B$83,1,MIN(1,$E$11+MAX(0,A36-Parametres!$B$81)*Parametres!$B$82)) -> 1 | C36: =IF(A36>=Parametres!$B$83,"GARANTI",IF(A36>=Parametres!$B$81,"Pity doux actif","Taux de base")) -> GARANTI
A38: Pourquoi ce systeme : le tirage reste excitant a chaque palier (ca peut tomber n'importe quand), mais la malchance a une fin connue. C'est ce qui evite l'abandon.

Sheet Economie
A1: ECONOMIE — 3 monnaies, 3 sources, 3 usages
A2: Or = farmable, volume. Essence = farmable, petites ameliorations. Gemmes = uniquement en montant de niveau, donc uniquement par vrai entrainement.
A4: HYPOTHESES D'ACTIVITE
A5: Seances par semaine | B5: 4
A6: Runs de donjon completes par semaine | B6: 5
A7: Cycle de donjon actuel | B7: 3
A8: Niveaux gagnes par mois (a ce stade) | B8: 1.5
A10: REVENUS
A11: Monnaie | B11: Source unique | C11: Par semaine | D11: Par mois | E11: Farmable sans s'entrainer ?
A12: Or | B12: Paliers de donjon nettoyes | C12: =ROUND($B$6*Parametres!$B$63*55*(1+Parametres!$B$64*($B$7-1)),0) -> 3300 | D12: =C12*4.345 -> 14338.5 | E12: Oui — mais bride par le palier atteint
A13: Essence | B13: Paliers de donjon nettoyes | C13: =ROUND($B$6*(Parametres!$B$65*Parametres!$B$51+Parametres!$B$66),0) -> 75 | D13: =C13*4.345 -> 325.875 | E13: Oui — c'est la monnaie de patience
A14: Gemmes | B14: Montees de niveau uniquement | C14: =ROUND($B$8/4.345*(Parametres!$B$70+Parametres!$B$71),1) -> 1.4 | D14: =C14*4.345 -> 6.083 | E14: NON — exige de l'entrainement reel
A17: DEPENSES
A18: Achat | B18: Monnaie | C18: Cout | D18: Ce que ca donne | E18: Semaines pour se le payer
A19: Coffre d'objet | B19: Or | C19: =Parametres!$B$67 -> 3000 | D19: 1 objet aleatoire (table de rarete) | E19: =C19/$C$12 -> 0.90909091
A20: Amelioration de stat #1 | B20: Essence | C20: =Parametres!$B$68 -> 40 | D20: +1 point de stat permanent | E20: =C20/$C$13 -> 0.53333333
A21: Amelioration de stat #5 | B21: Essence | C21: =ROUND(Parametres!$B$68*Parametres!$B$69^4,0) -> 133 | D21: Cout x1,25 par amelioration deja achetee | E21: =C21/$C$13 -> 1.7733333
A22: Amelioration de stat #10 | B22: Essence | C22: =ROUND(Parametres!$B$68*Parametres!$B$69^9,0) -> 596 | D22: Le mur naturel de l'essence | E22: =C22/$C$13 -> 7.9466667
A23: Forge niveau 1 | B23: Gemmes | C23: =Equipement!$D$33 -> 5 | D23: +8% sur un objet | E23: =C23/$C$14 -> 3.5714286
A24: Forge complete (niv. 10) | B24: Gemmes | C24: =Equipement!$E$42 -> 143 | D24: +80% sur un objet | E24: =C24/$C$14 -> 102.14286
A25: Coffre legendaire | B25: Gemmes | C25: 20 | D25: Rarete minimum garantie : Epique | E25: =C25/$C$14 -> 14.285714
A27: REGLE D'EQUILIBRE
A28: L'or ne doit jamais etre bloquant. | B28: Il sert au volume : ouvrir des coffres souvent, sentir le flux.
A29: L'essence doit devenir rare avec le temps. | B29: Cout x1,25 cumulatif : les 5 premieres ameliorations sont rapides, la 10e est un objectif.
A30: Les gemmes sont la vraie devise de prestige. | B30: Impossible a farmer. Chaque gemme = une seance reelle. C'est le lien incassable avec la salle.
A31: Aucun achat ne remplace la progression. | B31: Un objet achete reste limite par le palier de donjon atteint.

Sheet Sim 52 semaines
A1: SIMULATION AN 1 — a quoi ressemble une annee reelle
A2: Projection semaine par semaine avec un rythme d'entrainement realiste. Change les leviers ci-dessous pour tester un scenario (assidu, moyen, irregulier).
A4: SCENARIO
A5: Seances par semaine | B5: 4 | D5: 4 = objectif. Mets 2 pour tester un scenario irregulier.
A6: Volume moyen par seance (lb) | B6: 20000
A7: PR par seance | B7: 0.4
A8: Taux d'adhesion nutrition (0 a 1) | B8: 0.5 | D8: Approxime le taux de jours ou les 3 cibles sont atteintes (sans effet de serie, simplifie).
A9: Multiplicateur de moral moyen | B9: 0.98
A10: Runs de donjon par semaine | B10: 5
A11: Croissance du volume par semaine | B11: 0.008 | D11: Dans la vraie vie tu leves plus lourd avec le temps. +0,8%/sem = +50% sur un an, plafonne a 2x.
A12: Sem. | B12: XP brut de la semaine | C12: Mult. nutrition | D12: Mult. streak | E12: XP net de la semaine | F12: XP cumulatif | G12: Niveau | H12: Gemmes cumulees | I12: Cycle de donjon | J12: Or cumule | K12: Essence cumulee | L12: Jalon
A13: 1 | B13: =ROUND($B$5*(Parametres!$B$5+$B$6*MIN(2,(1+$B$11)^(A13-1))/Parametres!$B$6+$B$7*Parametres!$B$7),0) -> 640 | C13: =1+$B$8*(Parametres!$B$28+Parametres!$B$29+Parametres!$B$30) -> 1.085 | D13: =MIN(1+Parametres!$B$47*A13,1+Parametres!$B$48) -> 1.02 | E13: =ROUND(B13*C13*D13*$B$9,0) -> 694 | F13: =E13 -> 694 | G13: =MATCH(F13,Progression!$C$5:$C$54,1) -> 4 | H13: =INDEX(Progression!$I$5:$I$54,G13) -> 9 | I13: =IF(G13<Donjon!$B$42,0,MATCH(G13,Donjon!$B$42:$B$53,1)) -> 0 | J13: =ROUND(IF(I13=0,0,$B$10*Parametres!$B$63*55*(1+Parametres!$B$64*(I13-1))),0) -> 0 | K13: =ROUND(IF(I13=0,0,$B$10*(Parametres!$B$65*Parametres!$B$51+Parametres!$B$66)),0) -> 0 | L13: Niveau 1 → premiers paliers
A14: 2 | B14: =ROUND($B$5*(Parametres!$B$5+$B$6*MIN(2,(1+$B$11)^(A14-1))/Parametres!$B$6+$B$7*Parametres!$B$7),0) -> 643 | C14: =1+$B$8*(Parametres!$B$28+Parametres!$B$29+Parametres!$B$30) -> 1.085 | D14: =MIN(1+Parametres!$B$47*A14,1+Parametres!$B$48) -> 1.04 | E14: =ROUND(B14*C14*D14*$B$9,0) -> 711 | F14: =F13+E14 -> 1405 | G14: =MATCH(F14,Progression!$C$5:$C$54,1) -> 5 | H14: =INDEX(Progression!$I$5:$I$54,G14) -> 13 | I14: =IF(G14<Donjon!$B$42,0,MATCH(G14,Donjon!$B$42:$B$53,1)) -> 0 | J14: =J13+ROUND(IF(I14=0,0,$B$10*Parametres!$B$63*55*(1+Parametres!$B$64*(I14-1))),0) -> 0 | K14: =K13+ROUND(IF(I14=0,0,$B$10*(Parametres!$B$65*Parametres!$B$51+Parametres!$B$66)),0) -> 0
A15: 3 | B15: =ROUND($B$5*(Parametres!$B$5+$B$6*MIN(2,(1+$B$11)^(A15-1))/Parametres!$B$6+$B$7*Parametres!$B$7),0) -> 646 | C15: =1+$B$8*(Parametres!$B$28+Parametres!$B$29+Parametres!$B$30) -> 1.085 | D15: =MIN(1+Parametres!$B$47*A15,1+Parametres!$B$48) -> 1.06 | E15: =ROUND(B15*C15*D15*$B$9,0) -> 728 | F15: =F14+E15 -> 2133 | G15: =MATCH(F15,Progression!$C$5:$C$54,1) -> 6 | H15: =INDEX(Progression!$I$5:$I$54,G15) -> 17 | I15: =IF(G15<Donjon!$B$42,0,MATCH(G15,Donjon!$B$42:$B$53,1)) -> 1 | J15: =J14+ROUND(IF(I15=0,0,$B$10*Parametres!$B$63*55*(1+Parametres!$B$64*(I15-1))),0) -> 2750 | K15: =K14+ROUND(IF(I15=0,0,$B$10*(Parametres!$B$65*Parametres!$B$51+Parametres!$B$66)),0) -> 75
A16: 4 | B16: =ROUND($B$5*(Parametres!$B$5+$B$6*MIN(2,(1+$B$11)^(A16-1))/Parametres!$B$6+$B$7*Parametres!$B$7),0) -> 650 | C16: =1+$B$8*(Parametres!$B$28+Parametres!$B$29+Parametres!$B$30) -> 1.085 | D16: =MIN(1+Parametres!$B$47*A16,1+Parametres!$B$48) -> 1.08 | E16: =ROUND(B16*C16*D16*$B$9,0) -> 746 | F16: =F15+E16 -> 2879 | G16: =MATCH(F16,Progression!$C$5:$C$54,1) -> 7 | H16: =INDEX(Progression!$I$5:$I$54,G16) -> 21 | I16: =IF(G16<Donjon!$B$42,0,MATCH(G16,Donjon!$B$42:$B$53,1)) -> 2 | J16: =J15+ROUND(IF(I16=0,0,$B$10*Parametres!$B$63*55*(1+Parametres!$B$64*(I16-1))),0) -> 5775 | K16: =K15+ROUND(IF(I16=0,0,$B$10*(Parametres!$B$65*Parametres!$B$51+Parametres!$B$66)),0) -> 150 | L16: 1er mois
A17: 5 | B17: =ROUND($B$5*(Parametres!$B$5+$B$6*MIN(2,(1+$B$11)^(A17-1))/Parametres!$B$6+$B$7*Parametres!$B$7),0) -> 653 | C17: =1+$B$8*(Parametres!$B$28+Parametres!$B$29+Parametres!$B$30) -> 1.085 | D17: =MIN(1+Parametres!$B$47*A17,1+Parametres!$B$48) -> 1.1 | E17: =ROUND(B17*C17*D17*$B$9,0) -> 764 | F17: =F16+E17 -> 3643 | G17: =MATCH(F17,Progression!$C$5:$C$54,1) -> 8 | H17: =INDEX(Progression!$I$5:$I$54,G17) -> 25 | I17: =IF(G17<Donjon!$B$42,0,MATCH(G17,Donjon!$B$42:$B$53,1)) -> 3 | J17: =J16+ROUND(IF(I17=0,0,$B$10*Parametres!$B$63*55*(1+Parametres!$B$64*(I17-1))),0) -> 9075 | K17: =K16+ROUND(IF(I17=0,0,$B$10*(Parametres!$B$65*Parametres!$B$51+Parametres!$B$66)),0) -> 225
A18: 6 | B18: =ROUND($B$5*(Parametres!$B$5+$B$6*MIN(2,(1+$B$11)^(A18-1))/Parametres!$B$6+$B$7*Parametres!$B$7),0) -> 656 | C18: =1+$B$8*(Parametres!$B$28+Parametres!$B$29+Parametres!$B$30) -> 1.085 | D18: =MIN(1+Parametres!$B$47*A18,1+Parametres!$B$48) -> 1.12 | E18: =ROUND(B18*C18*D18*$B$9,0) -> 781 | F18: =F17+E18 -> 4424 | G18: =MATCH(F18,Progression!$C$5:$C$54,1) -> 9 | H18: =INDEX(Progression!$I$5:$I$54,G18) -> 29 | I18: =IF(G18<Donjon!$B$42,0,MATCH(G18,Donjon!$B$42:$B$53,1)) -> 3 | J18: =J17+ROUND(IF(I18=0,0,$B$10*Parametres!$B$63*55*(1+Parametres!$B$64*(I18-1))),0) -> 12375 | K18: =K17+ROUND(IF(I18=0,0,$B$10*(Parametres!$B$65*Parametres!$B$51+Parametres!$B$66)),0) -> 300
A19: 7 | B19: =ROUND($B$5*(Parametres!$B$5+$B$6*MIN(2,(1+$B$11)^(A19-1))/Parametres!$B$6+$B$7*Parametres!$B$7),0) -> 660 | C19: =1+$B$8*(Parametres!$B$28+Parametres!$B$29+Parametres!$B$30) -> 1.085 | D19: =MIN(1+Parametres!$B$47*A19,1+Parametres!$B$48) -> 1.14 | E19: =ROUND(B19*C19*D19*$B$9,0) -> 800 | F19: =F18+E19 -> 5224 | G19: =MATCH(F19,Progression!$C$5:$C$54,1) -> 9 | H19: =INDEX(Progression!$I$5:$I$54,G19) -> 29 | I19: =IF(G19<Donjon!$B$42,0,MATCH(G19,Donjon!$B$42:$B$53,1)) -> 3 | J19: =J18+ROUND(IF(I19=0,0,$B$10*Parametres!$B$63*55*(1+Parametres!$B$64*(I19-1))),0) -> 15675 | K19: =K18+ROUND(IF(I19=0,0,$B$10*(Parametres!$B$65*Parametres!$B$51+Parametres!$B$66)),0) -> 375
A20: 8 | B20: =ROUND($B$5*(Parametres!$B$5+$B$6*MIN(2,(1+$B$11)^(A20-1))/Parametres!$B$6+$B$7*Parametres!$B$7),0) -> 663 | C20: =1+$B$8*(Parametres!$B$28+Parametres!$B$29+Parametres!$B$30) -> 1.085 | D20: =MIN(1+Parametres!$B$47*A20,1+Parametres!$B$48) -> 1.16 | E20: =ROUND(B20*C20*D20*$B$9,0) -> 818 | F20: =F19+E20 -> 6042 | G20: =MATCH(F20,Progression!$C$5:$C$54,1) -> 10 | H20: =INDEX(Progression!$I$5:$I$54,G20) -> 34 | I20: =IF(G20<Donjon!$B$42,0,MATCH(G20,Donjon!$B$42:$B$53,1)) -> 4 | J20: =J19+ROUND(IF(I20=0,0,$B$10*Parametres!$B$63*55*(1+Parametres!$B$64*(I20-1))),0) -> 19250 | K20: =K19+ROUND(IF(I20=0,0,$B$10*(Parametres!$B$65*Parametres!$B$51+Parametres!$B$66)),0) -> 450
A21: 9 | B21: =ROUND($B$5*(Parametres!$B$5+$B$6*MIN(2,(1+$B$11)^(A21-1))/Parametres!$B$6+$B$7*Parametres!$B$7),0) -> 666 | C21: =1+$B$8*(Parametres!$B$28+Parametres!$B$29+Parametres!$B$30) -> 1.085 | D21: =MIN(1+Parametres!$B$47*A21,1+Parametres!$B$48) -> 1.18 | E21: =ROUND(B21*C21*D21*$B$9,0) -> 836 | F21: =F20+E21 -> 6878 | G21: =MATCH(F21,Progression!$C$5:$C$54,1) -> 10 | H21: =INDEX(Progression!$I$5:$I$54,G21) -> 34 | I21: =IF(G21<Donjon!$B$42,0,MATCH(G21,Donjon!$B$42:$B$53,1)) -> 4 | J21: =J20+ROUND(IF(I21=0,0,$B$10*Parametres!$B$63*55*(1+Parametres!$B$64*(I21-1))),0) -> 22825 | K21: =K20+ROUND(IF(I21=0,0,$B$10*(Parametres!$B$65*Parametres!$B$51+Parametres!$B$66)),0) -> 525
A22: 10 | B22: =ROUND($B$5*(Parametres!$B$5+$B$6*MIN(2,(1+$B$11)^(A22-1))/Parametres!$B$6+$B$7*Parametres!$B$7),0) -> 670 | C22: =1+$B$8*(Parametres!$B$28+Parametres!$B$29+Parametres!$B$30) -> 1.085 | D22: =MIN(1+Parametres!$B$47*A22,1+Parametres!$B$48) -> 1.2 | E22: =ROUND(B22*C22*D22*$B$9,0) -> 855 | F22: =F21+E22 -> 7733 | G22: =MATCH(F22,Progression!$C$5:$C$54,1) -> 11 | H22: =INDEX(Progression!$I$5:$I$54,G22) -> 39 | I22: =IF(G22<Donjon!$B$42,0,MATCH(G22,Donjon!$B$42:$B$53,1)) -> 5 | J22: =J21+ROUND(IF(I22=0,0,$B$10*Parametres!$B$63*55*(1+Parametres!$B$64*(I22-1))),0) -> 26675 | K22: =K21+ROUND(IF(I22=0,0,$B$10*(Parametres!$B$65*Parametres!$B$51+Parametres!$B$66)),0) -> 600
A23: 11 | B23: =ROUND($B$5*(Parametres!$B$5+$B$6*MIN(2,(1+$B$11)^(A23-1))/Parametres!$B$6+$B$7*Parametres!$B$7),0) -> 673 | C23: =1+$B$8*(Parametres!$B$28+Parametres!$B$29+Parametres!$B$30) -> 1.085 | D23: =MIN(1+Parametres!$B$47*A23,1+Parametres!$B$48) -> 1.2 | E23: =ROUND(B23*C23*D23*$B$9,0) -> 859 | F23: =F22+E23 -> 8592 | G23: =MATCH(F23,Progression!$C$5:$C$54,1) -> 11 | H23: =INDEX(Progression!$I$5:$I$54,G23) -> 39 | I23: =IF(G23<Donjon!$B$42,0,MATCH(G23,Donjon!$B$42:$B$53,1)) -> 5 | J23: =J22+ROUND(IF(I23=0,0,$B$10*Parametres!$B$63*55*(1+Parametres!$B$64*(I23-1))),0) -> 30525 | K23: =K22+ROUND(IF(I23=0,0,$B$10*(Parametres!$B$65*Parametres!$B$51+Parametres!$B$66)),0) -> 675
A24: 12 | B24: =ROUND($B$5*(Parametres!$B$5+$B$6*MIN(2,(1+$B$11)^(A24-1))/Parametres!$B$6+$B$7*Parametres!$B$7),0) -> 677 | C24: =1+$B$8*(Parametres!$B$28+Parametres!$B$29+Parametres!$B$30) -> 1.085 | D24: =MIN(1+Parametres!$B$47*A24,1+Parametres!$B$48) -> 1.2 | E24: =ROUND(B24*C24*D24*$B$9,0) -> 864 | F24: =F23+E24 -> 9456 | G24: =MATCH(F24,Progression!$C$5:$C$54,1) -> 12 | H24: =INDEX(Progression!$I$5:$I$54,G24) -> 44 | I24: =IF(G24<Donjon!$B$42,0,MATCH(G24,Donjon!$B$42:$B$53,1)) -> 5 | J24: =J23+ROUND(IF(I24=0,0,$B$10*Parametres!$B$63*55*(1+Parametres!$B$64*(I24-1))),0) -> 34375 | K24: =K23+ROUND(IF(I24=0,0,$B$10*(Parametres!$B$65*Parametres!$B$51+Parametres!$B$66)),0) -> 750
A25: 13 | B25: =ROUND($B$5*(Parametres!$B$5+$B$6*MIN(2,(1+$B$11)^(A25-1))/Parametres!$B$6+$B$7*Parametres!$B$7),0) -> 680 | C25: =1+$B$8*(Parametres!$B$28+Parametres!$B$29+Parametres!$B$30) -> 1.085 | D25: =MIN(1+Parametres!$B$47*A25,1+Parametres!$B$48) -> 1.2 | E25: =ROUND(B25*C25*D25*$B$9,0) -> 868 | F25: =F24+E25 -> 10324 | G25: =MATCH(F25,Progression!$C$5:$C$54,1) -> 12 | H25: =INDEX(Progression!$I$5:$I$54,G25) -> 44 | I25: =IF(G25<Donjon!$B$42,0,MATCH(G25,Donjon!$B$42:$B$53,1)) -> 5 | J25: =J24+ROUND(IF(I25=0,0,$B$10*Parametres!$B$63*55*(1+Parametres!$B$64*(I25-1))),0) -> 38225 | K25: =K24+ROUND(IF(I25=0,0,$B$10*(Parametres!$B$65*Parametres!$B$51+Parametres!$B$66)),0) -> 825 | L25: 3 mois
A26: 14 | B26: =ROUND($B$5*(Parametres!$B$5+$B$6*MIN(2,(1+$B$11)^(A26-1))/Parametres!$B$6+$B$7*Parametres!$B$7),0) -> 684 | C26: =1+$B$8*(Parametres!$B$28+Parametres!$B$29+Parametres!$B$30) -> 1.085 | D26: =MIN(1+Parametres!$B$47*A26,1+Parametres!$B$48) -> 1.2 | E26: =ROUND(B26*C26*D26*$B$9,0) -> 873 | F26: =F25+E26 -> 11197 | G26: =MATCH(F26,Progression!$C$5:$C$54,1) -> 13 | H26: =INDEX(Progression!$I$5:$I$54,G26) -> 49 | I26: =IF(G26<Donjon!$B$42,0,MATCH(G26,Donjon!$B$42:$B$53,1)) -> 6 | J26: =J25+ROUND(IF(I26=0,0,$B$10*Parametres!$B$63*55*(1+Parametres!$B$64*(I26-1))),0) -> 42350 | K26: =K25+ROUND(IF(I26=0,0,$B$10*(Parametres!$B$65*Parametres!$B$51+Parametres!$B$66)),0) -> 900
A27: 15 | B27: =ROUND($B$5*(Parametres!$B$5+$B$6*MIN(2,(1+$B$11)^(A27-1))/Parametres!$B$6+$B$7*Parametres!$B$7),0) -> 687 | C27: =1+$B$8*(Parametres!$B$28+Parametres!$B$29+Parametres!$B$30) -> 1.085 | D27: =MIN(1+Parametres!$B$47*A27,1+Parametres!$B$48) -> 1.2 | E27: =ROUND(B27*C27*D27*$B$9,0) -> 877 | F27: =F26+E27 -> 12074 | G27: =MATCH(F27,Progression!$C$5:$C$54,1) -> 13 | H27: =INDEX(Progression!$I$5:$I$54,G27) -> 49 | I27: =IF(G27<Donjon!$B$42,0,MATCH(G27,Donjon!$B$42:$B$53,1)) -> 6 | J27: =J26+ROUND(IF(I27=0,0,$B$10*Parametres!$B$63*55*(1+Parametres!$B$64*(I27-1))),0) -> 46475 | K27: =K26+ROUND(IF(I27=0,0,$B$10*(Parametres!$B$65*Parametres!$B$51+Parametres!$B$66)),0) -> 975
A28: 16 | B28: =ROUND($B$5*(Parametres!$B$5+$B$6*MIN(2,(1+$B$11)^(A28-1))/Parametres!$B$6+$B$7*Parametres!$B$7),0) -> 691 | C28: =1+$B$8*(Parametres!$B$28+Parametres!$B$29+Parametres!$B$30) -> 1.085 | D28: =MIN(1+Parametres!$B$47*A28,1+Parametres!$B$48) -> 1.2 | E28: =ROUND(B28*C28*D28*$B$9,0) -> 882 | F28: =F27+E28 -> 12956 | G28: =MATCH(F28,Progression!$C$5:$C$54,1) -> 13 | H28: =INDEX(Progression!$I$5:$I$54,G28) -> 49 | I28: =IF(G28<Donjon!$B$42,0,MATCH(G28,Donjon!$B$42:$B$53,1)) -> 6 | J28: =J27+ROUND(IF(I28=0,0,$B$10*Parametres!$B$63*55*(1+Parametres!$B$64*(I28-1))),0) -> 50600 | K28: =K27+ROUND(IF(I28=0,0,$B$10*(Parametres!$B$65*Parametres!$B$51+Parametres!$B$66)),0) -> 1050
A29: 17 | B29: =ROUND($B$5*(Parametres!$B$5+$B$6*MIN(2,(1+$B$11)^(A29-1))/Parametres!$B$6+$B$7*Parametres!$B$7),0) -> 694 | C29: =1+$B$8*(Parametres!$B$28+Parametres!$B$29+Parametres!$B$30) -> 1.085 | D29: =MIN(1+Parametres!$B$47*A29,1+Parametres!$B$48) -> 1.2 | E29: =ROUND(B29*C29*D29*$B$9,0) -> 886 | F29: =F28+E29 -> 13842 | G29: =MATCH(F29,Progression!$C$5:$C$54,1) -> 14 | H29: =INDEX(Progression!$I$5:$I$54,G29) -> 54 | I29: =IF(G29<Donjon!$B$42,0,MATCH(G29,Donjon!$B$42:$B$53,1)) -> 6 | J29: =J28+ROUND(IF(I29=0,0,$B$10*Parametres!$B$63*55*(1+Parametres!$B$64*(I29-1))),0) -> 54725 | K29: =K28+ROUND(IF(I29=0,0,$B$10*(Parametres!$B$65*Parametres!$B$51+Parametres!$B$66)),0) -> 1125
A30: 18 | B30: =ROUND($B$5*(Parametres!$B$5+$B$6*MIN(2,(1+$B$11)^(A30-1))/Parametres!$B$6+$B$7*Parametres!$B$7),0) -> 698 | C30: =1+$B$8*(Parametres!$B$28+Parametres!$B$29+Parametres!$B$30) -> 1.085 | D30: =MIN(1+Parametres!$B$47*A30,1+Parametres!$B$48) -> 1.2 | E30: =ROUND(B30*C30*D30*$B$9,0) -> 891 | F30: =F29+E30 -> 14733 | G30: =MATCH(F30,Progression!$C$5:$C$54,1) -> 14 | H30: =INDEX(Progression!$I$5:$I$54,G30) -> 54 | I30: =IF(G30<Donjon!$B$42,0,MATCH(G30,Donjon!$B$42:$B$53,1)) -> 6 | J30: =J29+ROUND(IF(I30=0,0,$B$10*Parametres!$B$63*55*(1+Parametres!$B$64*(I30-1))),0) -> 58850 | K30: =K29+ROUND(IF(I30=0,0,$B$10*(Parametres!$B$65*Parametres!$B$51+Parametres!$B$66)),0) -> 1200
A31: 19 | B31: =ROUND($B$5*(Parametres!$B$5+$B$6*MIN(2,(1+$B$11)^(A31-1))/Parametres!$B$6+$B$7*Parametres!$B$7),0) -> 702 | C31: =1+$B$8*(Parametres!$B$28+Parametres!$B$29+Parametres!$B$30) -> 1.085 | D31: =MIN(1+Parametres!$B$47*A31,1+Parametres!$B$48) -> 1.2 | E31: =ROUND(B31*C31*D31*$B$9,0) -> 896 | F31: =F30+E31 -> 15629 | G31: =MATCH(F31,Progression!$C$5:$C$54,1) -> 14 | H31: =INDEX(Progression!$I$5:$I$54,G31) -> 54 | I31: =IF(G31<Donjon!$B$42,0,MATCH(G31,Donjon!$B$42:$B$53,1)) -> 6 | J31: =J30+ROUND(IF(I31=0,0,$B$10*Parametres!$B$63*55*(1+Parametres!$B$64*(I31-1))),0) -> 62975 | K31: =K30+ROUND(IF(I31=0,0,$B$10*(Parametres!$B$65*Parametres!$B$51+Parametres!$B$66)),0) -> 1275
A32: 20 | B32: =ROUND($B$5*(Parametres!$B$5+$B$6*MIN(2,(1+$B$11)^(A32-1))/Parametres!$B$6+$B$7*Parametres!$B$7),0) -> 705 | C32: =1+$B$8*(Parametres!$B$28+Parametres!$B$29+Parametres!$B$30) -> 1.085 | D32: =MIN(1+Parametres!$B$47*A32,1+Parametres!$B$48) -> 1.2 | E32: =ROUND(B32*C32*D32*$B$9,0) -> 900 | F32: =F31+E32 -> 16529 | G32: =MATCH(F32,Progression!$C$5:$C$54,1) -> 15 | H32: =INDEX(Progression!$I$5:$I$54,G32) -> 60 | I32: =IF(G32<Donjon!$B$42,0,MATCH(G32,Donjon!$B$42:$B$53,1)) -> 6 | J32: =J31+ROUND(IF(I32=0,0,$B$10*Parametres!$B$63*55*(1+Parametres!$B$64*(I32-1))),0) -> 67100 | K32: =K31+ROUND(IF(I32=0,0,$B$10*(Parametres!$B$65*Parametres!$B$51+Parametres!$B$66)),0) -> 1350
A33: 21 | B33: =ROUND($B$5*(Parametres!$B$5+$B$6*MIN(2,(1+$B$11)^(A33-1))/Parametres!$B$6+$B$7*Parametres!$B$7),0) -> 709 | C33: =1+$B$8*(Parametres!$B$28+Parametres!$B$29+Parametres!$B$30) -> 1.085 | D33: =MIN(1+Parametres!$B$47*A33,1+Parametres!$B$48) -> 1.2 | E33: =ROUND(B33*C33*D33*$B$9,0) -> 905 | F33: =F32+E33 -> 17434 | G33: =MATCH(F33,Progression!$C$5:$C$54,1) -> 15 | H33: =INDEX(Progression!$I$5:$I$54,G33) -> 60 | I33: =IF(G33<Donjon!$B$42,0,MATCH(G33,Donjon!$B$42:$B$53,1)) -> 6 | J33: =J32+ROUND(IF(I33=0,0,$B$10*Parametres!$B$63*55*(1+Parametres!$B$64*(I33-1))),0) -> 71225 | K33: =K32+ROUND(IF(I33=0,0,$B$10*(Parametres!$B$65*Parametres!$B$51+Parametres!$B$66)),0) -> 1425
A34: 22 | B34: =ROUND($B$5*(Parametres!$B$5+$B$6*MIN(2,(1+$B$11)^(A34-1))/Parametres!$B$6+$B$7*Parametres!$B$7),0) -> 713 | C34: =1+$B$8*(Parametres!$B$28+Parametres!$B$29+Parametres!$B$30) -> 1.085 | D34: =MIN(1+Parametres!$B$47*A34,1+Parametres!$B$48) -> 1.2 | E34: =ROUND(B34*C34*D34*$B$9,0) -> 910 | F34: =F33+E34 -> 18344 | G34: =MATCH(F34,Progression!$C$5:$C$54,1) -> 15 | H34: =INDEX(Progression!$I$5:$I$54,G34) -> 60 | I34: =IF(G34<Donjon!$B$42,0,MATCH(G34,Donjon!$B$42:$B$53,1)) -> 6 | J34: =J33+ROUND(IF(I34=0,0,$B$10*Parametres!$B$63*55*(1+Parametres!$B$64*(I34-1))),0) -> 75350 | K34: =K33+ROUND(IF(I34=0,0,$B$10*(Parametres!$B$65*Parametres!$B$51+Parametres!$B$66)),0) -> 1500
A35: 23 | B35: =ROUND($B$5*(Parametres!$B$5+$B$6*MIN(2,(1+$B$11)^(A35-1))/Parametres!$B$6+$B$7*Parametres!$B$7),0) -> 717 | C35: =1+$B$8*(Parametres!$B$28+Parametres!$B$29+Parametres!$B$30) -> 1.085 | D35: =MIN(1+Parametres!$B$47*A35,1+Parametres!$B$48) -> 1.2 | E35: =ROUND(B35*C35*D35*$B$9,0) -> 915 | F35: =F34+E35 -> 19259 | G35: =MATCH(F35,Progression!$C$5:$C$54,1) -> 16 | H35: =INDEX(Progression!$I$5:$I$54,G35) -> 66 | I35: =IF(G35<Donjon!$B$42,0,MATCH(G35,Donjon!$B$42:$B$53,1)) -> 7 | J35: =J34+ROUND(IF(I35=0,0,$B$10*Parametres!$B$63*55*(1+Parametres!$B$64*(I35-1))),0) -> 79750 | K35: =K34+ROUND(IF(I35=0,0,$B$10*(Parametres!$B$65*Parametres!$B$51+Parametres!$B$66)),0) -> 1575
A36: 24 | B36: =ROUND($B$5*(Parametres!$B$5+$B$6*MIN(2,(1+$B$11)^(A36-1))/Parametres!$B$6+$B$7*Parametres!$B$7),0) -> 720 | C36: =1+$B$8*(Parametres!$B$28+Parametres!$B$29+Parametres!$B$30) -> 1.085 | D36: =MIN(1+Parametres!$B$47*A36,1+Parametres!$B$48) -> 1.2 | E36: =ROUND(B36*C36*D36*$B$9,0) -> 919 | F36: =F35+E36 -> 20178 | G36: =MATCH(F36,Progression!$C$5:$C$54,1) -> 16 | H36: =INDEX(Progression!$I$5:$I$54,G36) -> 66 | I36: =IF(G36<Donjon!$B$42,0,MATCH(G36,Donjon!$B$42:$B$53,1)) -> 7 | J36: =J35+ROUND(IF(I36=0,0,$B$10*Parametres!$B$63*55*(1+Parametres!$B$64*(I36-1))),0) -> 84150 | K36: =K35+ROUND(IF(I36=0,0,$B$10*(Parametres!$B$65*Parametres!$B$51+Parametres!$B$66)),0) -> 1650
A37: 25 | B37: =ROUND($B$5*(Parametres!$B$5+$B$6*MIN(2,(1+$B$11)^(A37-1))/Parametres!$B$6+$B$7*Parametres!$B$7),0) -> 724 | C37: =1+$B$8*(Parametres!$B$28+Parametres!$B$29+Parametres!$B$30) -> 1.085 | D37: =MIN(1+Parametres!$B$47*A37,1+Parametres!$B$48) -> 1.2 | E37: =ROUND(B37*C37*D37*$B$9,0) -> 924 | F37: =F36+E37 -> 21102 | G37: =MATCH(F37,Progression!$C$5:$C$54,1) -> 16 | H37: =INDEX(Progression!$I$5:$I$54,G37) -> 66 | I37: =IF(G37<Donjon!$B$42,0,MATCH(G37,Donjon!$B$42:$B$53,1)) -> 7 | J37: =J36+ROUND(IF(I37=0,0,$B$10*Parametres!$B$63*55*(1+Parametres!$B$64*(I37-1))),0) -> 88550 | K37: =K36+ROUND(IF(I37=0,0,$B$10*(Parametres!$B$65*Parametres!$B$51+Parametres!$B$66)),0) -> 1725
A38: 26 | B38: =ROUND($B$5*(Parametres!$B$5+$B$6*MIN(2,(1+$B$11)^(A38-1))/Parametres!$B$6+$B$7*Parametres!$B$7),0) -> 728 | C38: =1+$B$8*(Parametres!$B$28+Parametres!$B$29+Parametres!$B$30) -> 1.085 | D38: =MIN(1+Parametres!$B$47*A38,1+Parametres!$B$48) -> 1.2 | E38: =ROUND(B38*C38*D38*$B$9,0) -> 929 | F38: =F37+E38 -> 22031 | G38: =MATCH(F38,Progression!$C$5:$C$54,1) -> 16 | H38: =INDEX(Progression!$I$5:$I$54,G38) -> 66 | I38: =IF(G38<Donjon!$B$42,0,MATCH(G38,Donjon!$B$42:$B$53,1)) -> 7 | J38: =J37+ROUND(IF(I38=0,0,$B$10*Parametres!$B$63*55*(1+Parametres!$B$64*(I38-1))),0) -> 92950 | K38: =K37+ROUND(IF(I38=0,0,$B$10*(Parametres!$B$65*Parametres!$B$51+Parametres!$B$66)),0) -> 1800 | L38: 6 mois
A39: 27 | B39: =ROUND($B$5*(Parametres!$B$5+$B$6*MIN(2,(1+$B$11)^(A39-1))/Parametres!$B$6+$B$7*Parametres!$B$7),0) -> 732 | C39: =1+$B$8*(Parametres!$B$28+Parametres!$B$29+Parametres!$B$30) -> 1.085 | D39: =MIN(1+Parametres!$B$47*A39,1+Parametres!$B$48) -> 1.2 | E39: =ROUND(B39*C39*D39*$B$9,0) -> 934 | F39: =F38+E39 -> 22965 | G39: =MATCH(F39,Progression!$C$5:$C$54,1) -> 17 | H39: =INDEX(Progression!$I$5:$I$54,G39) -> 72 | I39: =IF(G39<Donjon!$B$42,0,MATCH(G39,Donjon!$B$42:$B$53,1)) -> 7 | J39: =J38+ROUND(IF(I39=0,0,$B$10*Parametres!$B$63*55*(1+Parametres!$B$64*(I39-1))),0) -> 97350 | K39: =K38+ROUND(IF(I39=0,0,$B$10*(Parametres!$B$65*Parametres!$B$51+Parametres!$B$66)),0) -> 1875
A40: 28 | B40: =ROUND($B$5*(Parametres!$B$5+$B$6*MIN(2,(1+$B$11)^(A40-1))/Parametres!$B$6+$B$7*Parametres!$B$7),0) -> 736 | C40: =1+$B$8*(Parametres!$B$28+Parametres!$B$29+Parametres!$B$30) -> 1.085 | D40: =MIN(1+Parametres!$B$47*A40,1+Parametres!$B$48) -> 1.2 | E40: =ROUND(B40*C40*D40*$B$9,0) -> 939 | F40: =F39+E40 -> 23904 | G40: =MATCH(F40,Progression!$C$5:$C$54,1) -> 17 | H40: =INDEX(Progression!$I$5:$I$54,G40) -> 72 | I40: =IF(G40<Donjon!$B$42,0,MATCH(G40,Donjon!$B$42:$B$53,1)) -> 7 | J40: =J39+ROUND(IF(I40=0,0,$B$10*Parametres!$B$63*55*(1+Parametres!$B$64*(I40-1))),0) -> 101750 | K40: =K39+ROUND(IF(I40=0,0,$B$10*(Parametres!$B$65*Parametres!$B$51+Parametres!$B$66)),0) -> 1950
A41: 29 | B41: =ROUND($B$5*(Parametres!$B$5+$B$6*MIN(2,(1+$B$11)^(A41-1))/Parametres!$B$6+$B$7*Parametres!$B$7),0) -> 740 | C41: =1+$B$8*(Parametres!$B$28+Parametres!$B$29+Parametres!$B$30) -> 1.085 | D41: =MIN(1+Parametres!$B$47*A41,1+Parametres!$B$48) -> 1.2 | E41: =ROUND(B41*C41*D41*$B$9,0) -> 944 | F41: =F40+E41 -> 24848 | G41: =MATCH(F41,Progression!$C$5:$C$54,1) -> 17 | H41: =INDEX(Progression!$I$5:$I$54,G41) -> 72 | I41: =IF(G41<Donjon!$B$42,0,MATCH(G41,Donjon!$B$42:$B$53,1)) -> 7 | J41: =J40+ROUND(IF(I41=0,0,$B$10*Parametres!$B$63*55*(1+Parametres!$B$64*(I41-1))),0) -> 106150 | K41: =K40+ROUND(IF(I41=0,0,$B$10*(Parametres!$B$65*Parametres!$B$51+Parametres!$B$66)),0) -> 2025
A42: 30 | B42: =ROUND($B$5*(Parametres!$B$5+$B$6*MIN(2,(1+$B$11)^(A42-1))/Parametres!$B$6+$B$7*Parametres!$B$7),0) -> 744 | C42: =1+$B$8*(Parametres!$B$28+Parametres!$B$29+Parametres!$B$30) -> 1.085 | D42: =MIN(1+Parametres!$B$47*A42,1+Parametres!$B$48) -> 1.2 | E42: =ROUND(B42*C42*D42*$B$9,0) -> 949 | F42: =F41+E42 -> 25797 | G42: =MATCH(F42,Progression!$C$5:$C$54,1) -> 18 | H42: =INDEX(Progression!$I$5:$I$54,G42) -> 78 | I42: =IF(G42<Donjon!$B$42,0,MATCH(G42,Donjon!$B$42:$B$53,1)) -> 8 | J42: =J41+ROUND(IF(I42=0,0,$B$10*Parametres!$B$63*55*(1+Parametres!$B$64*(I42-1))),0) -> 110825 | K42: =K41+ROUND(IF(I42=0,0,$B$10*(Parametres!$B$65*Parametres!$B$51+Parametres!$B$66)),0) -> 2100
A43: 31 | B43: =ROUND($B$5*(Parametres!$B$5+$B$6*MIN(2,(1+$B$11)^(A43-1))/Parametres!$B$6+$B$7*Parametres!$B$7),0) -> 748 | C43: =1+$B$8*(Parametres!$B$28+Parametres!$B$29+Parametres!$B$30) -> 1.085 | D43: =MIN(1+Parametres!$B$47*A43,1+Parametres!$B$48) -> 1.2 | E43: =ROUND(B43*C43*D43*$B$9,0) -> 954 | F43: =F42+E43 -> 26751 | G43: =MATCH(F43,Progression!$C$5:$C$54,1) -> 18 | H43: =INDEX(Progression!$I$5:$I$54,G43) -> 78 | I43: =IF(G43<Donjon!$B$42,0,MATCH(G43,Donjon!$B$42:$B$53,1)) -> 8 | J43: =J42+ROUND(IF(I43=0,0,$B$10*Parametres!$B$63*55*(1+Parametres!$B$64*(I43-1))),0) -> 115500 | K43: =K42+ROUND(IF(I43=0,0,$B$10*(Parametres!$B$65*Parametres!$B$51+Parametres!$B$66)),0) -> 2175
A44: 32 | B44: =ROUND($B$5*(Parametres!$B$5+$B$6*MIN(2,(1+$B$11)^(A44-1))/Parametres!$B$6+$B$7*Parametres!$B$7),0) -> 752 | C44: =1+$B$8*(Parametres!$B$28+Parametres!$B$29+Parametres!$B$30) -> 1.085 | D44: =MIN(1+Parametres!$B$47*A44,1+Parametres!$B$48) -> 1.2 | E44: =ROUND(B44*C44*D44*$B$9,0) -> 960 | F44: =F43+E44 -> 27711 | G44: =MATCH(F44,Progression!$C$5:$C$54,1) -> 18 | H44: =INDEX(Progression!$I$5:$I$54,G44) -> 78 | I44: =IF(G44<Donjon!$B$42,0,MATCH(G44,Donjon!$B$42:$B$53,1)) -> 8 | J44: =J43+ROUND(IF(I44=0,0,$B$10*Parametres!$B$63*55*(1+Parametres!$B$64*(I44-1))),0) -> 120175 | K44: =K43+ROUND(IF(I44=0,0,$B$10*(Parametres!$B$65*Parametres!$B$51+Parametres!$B$66)),0) -> 2250
A45: 33 | B45: =ROUND($B$5*(Parametres!$B$5+$B$6*MIN(2,(1+$B$11)^(A45-1))/Parametres!$B$6+$B$7*Parametres!$B$7),0) -> 756 | C45: =1+$B$8*(Parametres!$B$28+Parametres!$B$29+Parametres!$B$30) -> 1.085 | D45: =MIN(1+Parametres!$B$47*A45,1+Parametres!$B$48) -> 1.2 | E45: =ROUND(B45*C45*D45*$B$9,0) -> 965 | F45: =F44+E45 -> 28676 | G45: =MATCH(F45,Progression!$C$5:$C$54,1) -> 18 | H45: =INDEX(Progression!$I$5:$I$54,G45) -> 78 | I45: =IF(G45<Donjon!$B$42,0,MATCH(G45,Donjon!$B$42:$B$53,1)) -> 8 | J45: =J44+ROUND(IF(I45=0,0,$B$10*Parametres!$B$63*55*(1+Parametres!$B$64*(I45-1))),0) -> 124850 | K45: =K44+ROUND(IF(I45=0,0,$B$10*(Parametres!$B$65*Parametres!$B$51+Parametres!$B$66)),0) -> 2325
A46: 34 | B46: =ROUND($B$5*(Parametres!$B$5+$B$6*MIN(2,(1+$B$11)^(A46-1))/Parametres!$B$6+$B$7*Parametres!$B$7),0) -> 760 | C46: =1+$B$8*(Parametres!$B$28+Parametres!$B$29+Parametres!$B$30) -> 1.085 | D46: =MIN(1+Parametres!$B$47*A46,1+Parametres!$B$48) -> 1.2 | E46: =ROUND(B46*C46*D46*$B$9,0) -> 970 | F46: =F45+E46 -> 29646 | G46: =MATCH(F46,Progression!$C$5:$C$54,1) -> 19 | H46: =INDEX(Progression!$I$5:$I$54,G46) -> 84 | I46: =IF(G46<Donjon!$B$42,0,MATCH(G46,Donjon!$B$42:$B$53,1)) -> 8 | J46: =J45+ROUND(IF(I46=0,0,$B$10*Parametres!$B$63*55*(1+Parametres!$B$64*(I46-1))),0) -> 129525 | K46: =K45+ROUND(IF(I46=0,0,$B$10*(Parametres!$B$65*Parametres!$B$51+Parametres!$B$66)),0) -> 2400
A47: 35 | B47: =ROUND($B$5*(Parametres!$B$5+$B$6*MIN(2,(1+$B$11)^(A47-1))/Parametres!$B$6+$B$7*Parametres!$B$7),0) -> 764 | C47: =1+$B$8*(Parametres!$B$28+Parametres!$B$29+Parametres!$B$30) -> 1.085 | D47: =MIN(1+Parametres!$B$47*A47,1+Parametres!$B$48) -> 1.2 | E47: =ROUND(B47*C47*D47*$B$9,0) -> 975 | F47: =F46+E47 -> 30621 | G47: =MATCH(F47,Progression!$C$5:$C$54,1) -> 19 | H47: =INDEX(Progression!$I$5:$I$54,G47) -> 84 | I47: =IF(G47<Donjon!$B$42,0,MATCH(G47,Donjon!$B$42:$B$53,1)) -> 8 | J47: =J46+ROUND(IF(I47=0,0,$B$10*Parametres!$B$63*55*(1+Parametres!$B$64*(I47-1))),0) -> 134200 | K47: =K46+ROUND(IF(I47=0,0,$B$10*(Parametres!$B$65*Parametres!$B$51+Parametres!$B$66)),0) -> 2475
A48: 36 | B48: =ROUND($B$5*(Parametres!$B$5+$B$6*MIN(2,(1+$B$11)^(A48-1))/Parametres!$B$6+$B$7*Parametres!$B$7),0) -> 769 | C48: =1+$B$8*(Parametres!$B$28+Parametres!$B$29+Parametres!$B$30) -> 1.085 | D48: =MIN(1+Parametres!$B$47*A48,1+Parametres!$B$48) -> 1.2 | E48: =ROUND(B48*C48*D48*$B$9,0) -> 981 | F48: =F47+E48 -> 31602 | G48: =MATCH(F48,Progression!$C$5:$C$54,1) -> 19 | H48: =INDEX(Progression!$I$5:$I$54,G48) -> 84 | I48: =IF(G48<Donjon!$B$42,0,MATCH(G48,Donjon!$B$42:$B$53,1)) -> 8 | J48: =J47+ROUND(IF(I48=0,0,$B$10*Parametres!$B$63*55*(1+Parametres!$B$64*(I48-1))),0) -> 138875 | K48: =K47+ROUND(IF(I48=0,0,$B$10*(Parametres!$B$65*Parametres!$B$51+Parametres!$B$66)),0) -> 2550
A49: 37 | B49: =ROUND($B$5*(Parametres!$B$5+$B$6*MIN(2,(1+$B$11)^(A49-1))/Parametres!$B$6+$B$7*Parametres!$B$7),0) -> 773 | C49: =1+$B$8*(Parametres!$B$28+Parametres!$B$29+Parametres!$B$30) -> 1.085 | D49: =MIN(1+Parametres!$B$47*A49,1+Parametres!$B$48) -> 1.2 | E49: =ROUND(B49*C49*D49*$B$9,0) -> 986 | F49: =F48+E49 -> 32588 | G49: =MATCH(F49,Progression!$C$5:$C$54,1) -> 19 | H49: =INDEX(Progression!$I$5:$I$54,G49) -> 84 | I49: =IF(G49<Donjon!$B$42,0,MATCH(G49,Donjon!$B$42:$B$53,1)) -> 8 | J49: =J48+ROUND(IF(I49=0,0,$B$10*Parametres!$B$63*55*(1+Parametres!$B$64*(I49-1))),0) -> 143550 | K49: =K48+ROUND(IF(I49=0,0,$B$10*(Parametres!$B$65*Parametres!$B$51+Parametres!$B$66)),0) -> 2625
A50: 38 | B50: =ROUND($B$5*(Parametres!$B$5+$B$6*MIN(2,(1+$B$11)^(A50-1))/Parametres!$B$6+$B$7*Parametres!$B$7),0) -> 777 | C50: =1+$B$8*(Parametres!$B$28+Parametres!$B$29+Parametres!$B$30) -> 1.085 | D50: =MIN(1+Parametres!$B$47*A50,1+Parametres!$B$48) -> 1.2 | E50: =ROUND(B50*C50*D50*$B$9,0) -> 991 | F50: =F49+E50 -> 33579 | G50: =MATCH(F50,Progression!$C$5:$C$54,1) -> 20 | H50: =INDEX(Progression!$I$5:$I$54,G50) -> 91 | I50: =IF(G50<Donjon!$B$42,0,MATCH(G50,Donjon!$B$42:$B$53,1)) -> 8 | J50: =J49+ROUND(IF(I50=0,0,$B$10*Parametres!$B$63*55*(1+Parametres!$B$64*(I50-1))),0) -> 148225 | K50: =K49+ROUND(IF(I50=0,0,$B$10*(Parametres!$B$65*Parametres!$B$51+Parametres!$B$66)),0) -> 2700
A51: 39 | B51: =ROUND($B$5*(Parametres!$B$5+$B$6*MIN(2,(1+$B$11)^(A51-1))/Parametres!$B$6+$B$7*Parametres!$B$7),0) -> 781 | C51: =1+$B$8*(Parametres!$B$28+Parametres!$B$29+Parametres!$B$30) -> 1.085 | D51: =MIN(1+Parametres!$B$47*A51,1+Parametres!$B$48) -> 1.2 | E51: =ROUND(B51*C51*D51*$B$9,0) -> 997 | F51: =F50+E51 -> 34576 | G51: =MATCH(F51,Progression!$C$5:$C$54,1) -> 20 | H51: =INDEX(Progression!$I$5:$I$54,G51) -> 91 | I51: =IF(G51<Donjon!$B$42,0,MATCH(G51,Donjon!$B$42:$B$53,1)) -> 8 | J51: =J50+ROUND(IF(I51=0,0,$B$10*Parametres!$B$63*55*(1+Parametres!$B$64*(I51-1))),0) -> 152900 | K51: =K50+ROUND(IF(I51=0,0,$B$10*(Parametres!$B$65*Parametres!$B$51+Parametres!$B$66)),0) -> 2775 | L51: 9 mois
A52: 40 | B52: =ROUND($B$5*(Parametres!$B$5+$B$6*MIN(2,(1+$B$11)^(A52-1))/Parametres!$B$6+$B$7*Parametres!$B$7),0) -> 786 | C52: =1+$B$8*(Parametres!$B$28+Parametres!$B$29+Parametres!$B$30) -> 1.085 | D52: =MIN(1+Parametres!$B$47*A52,1+Parametres!$B$48) -> 1.2 | E52: =ROUND(B52*C52*D52*$B$9,0) -> 1003 | F52: =F51+E52 -> 35579 | G52: =MATCH(F52,Progression!$C$5:$C$54,1) -> 20 | H52: =INDEX(Progression!$I$5:$I$54,G52) -> 91 | I52: =IF(G52<Donjon!$B$42,0,MATCH(G52,Donjon!$B$42:$B$53,1)) -> 8 | J52: =J51+ROUND(IF(I52=0,0,$B$10*Parametres!$B$63*55*(1+Parametres!$B$64*(I52-1))),0) -> 157575 | K52: =K51+ROUND(IF(I52=0,0,$B$10*(Parametres!$B$65*Parametres!$B$51+Parametres!$B$66)),0) -> 2850
A53: 41 | B53: =ROUND($B$5*(Parametres!$B$5+$B$6*MIN(2,(1+$B$11)^(A53-1))/Parametres!$B$6+$B$7*Parametres!$B$7),0) -> 790 | C53: =1+$B$8*(Parametres!$B$28+Parametres!$B$29+Parametres!$B$30) -> 1.085 | D53: =MIN(1+Parametres!$B$47*A53,1+Parametres!$B$48) -> 1.2 | E53: =ROUND(B53*C53*D53*$B$9,0) -> 1008 | F53: =F52+E53 -> 36587 | G53: =MATCH(F53,Progression!$C$5:$C$54,1) -> 20 | H53: =INDEX(Progression!$I$5:$I$54,G53) -> 91 | I53: =IF(G53<Donjon!$B$42,0,MATCH(G53,Donjon!$B$42:$B$53,1)) -> 8 | J53: =J52+ROUND(IF(I53=0,0,$B$10*Parametres!$B$63*55*(1+Parametres!$B$64*(I53-1))),0) -> 162250 | K53: =K52+ROUND(IF(I53=0,0,$B$10*(Parametres!$B$65*Parametres!$B$51+Parametres!$B$66)),0) -> 2925
A54: 42 | B54: =ROUND($B$5*(Parametres!$B$5+$B$6*MIN(2,(1+$B$11)^(A54-1))/Parametres!$B$6+$B$7*Parametres!$B$7),0) -> 795 | C54: =1+$B$8*(Parametres!$B$28+Parametres!$B$29+Parametres!$B$30) -> 1.085 | D54: =MIN(1+Parametres!$B$47*A54,1+Parametres!$B$48) -> 1.2 | E54: =ROUND(B54*C54*D54*$B$9,0) -> 1014 | F54: =F53+E54 -> 37601 | G54: =MATCH(F54,Progression!$C$5:$C$54,1) -> 20 | H54: =INDEX(Progression!$I$5:$I$54,G54) -> 91 | I54: =IF(G54<Donjon!$B$42,0,MATCH(G54,Donjon!$B$42:$B$53,1)) -> 8 | J54: =J53+ROUND(IF(I54=0,0,$B$10*Parametres!$B$63*55*(1+Parametres!$B$64*(I54-1))),0) -> 166925 | K54: =K53+ROUND(IF(I54=0,0,$B$10*(Parametres!$B$65*Parametres!$B$51+Parametres!$B$66)),0) -> 3000
A55: 43 | B55: =ROUND($B$5*(Parametres!$B$5+$B$6*MIN(2,(1+$B$11)^(A55-1))/Parametres!$B$6+$B$7*Parametres!$B$7),0) -> 799 | C55: =1+$B$8*(Parametres!$B$28+Parametres!$B$29+Parametres!$B$30) -> 1.085 | D55: =MIN(1+Parametres!$B$47*A55,1+Parametres!$B$48) -> 1.2 | E55: =ROUND(B55*C55*D55*$B$9,0) -> 1019 | F55: =F54+E55 -> 38620 | G55: =MATCH(F55,Progression!$C$5:$C$54,1) -> 21 | H55: =INDEX(Progression!$I$5:$I$54,G55) -> 98 | I55: =IF(G55<Donjon!$B$42,0,MATCH(G55,Donjon!$B$42:$B$53,1)) -> 9 | J55: =J54+ROUND(IF(I55=0,0,$B$10*Parametres!$B$63*55*(1+Parametres!$B$64*(I55-1))),0) -> 171875 | K55: =K54+ROUND(IF(I55=0,0,$B$10*(Parametres!$B$65*Parametres!$B$51+Parametres!$B$66)),0) -> 3075
A56: 44 | B56: =ROUND($B$5*(Parametres!$B$5+$B$6*MIN(2,(1+$B$11)^(A56-1))/Parametres!$B$6+$B$7*Parametres!$B$7),0) -> 803 | C56: =1+$B$8*(Parametres!$B$28+Parametres!$B$29+Parametres!$B$30) -> 1.085 | D56: =MIN(1+Parametres!$B$47*A56,1+Parametres!$B$48) -> 1.2 | E56: =ROUND(B56*C56*D56*$B$9,0) -> 1025 | F56: =F55+E56 -> 39645 | G56: =MATCH(F56,Progression!$C$5:$C$54,1) -> 21 | H56: =INDEX(Progression!$I$5:$I$54,G56) -> 98 | I56: =IF(G56<Donjon!$B$42,0,MATCH(G56,Donjon!$B$42:$B$53,1)) -> 9 | J56: =J55+ROUND(IF(I56=0,0,$B$10*Parametres!$B$63*55*(1+Parametres!$B$64*(I56-1))),0) -> 176825 | K56: =K55+ROUND(IF(I56=0,0,$B$10*(Parametres!$B$65*Parametres!$B$51+Parametres!$B$66)),0) -> 3150
A57: 45 | B57: =ROUND($B$5*(Parametres!$B$5+$B$6*MIN(2,(1+$B$11)^(A57-1))/Parametres!$B$6+$B$7*Parametres!$B$7),0) -> 808 | C57: =1+$B$8*(Parametres!$B$28+Parametres!$B$29+Parametres!$B$30) -> 1.085 | D57: =MIN(1+Parametres!$B$47*A57,1+Parametres!$B$48) -> 1.2 | E57: =ROUND(B57*C57*D57*$B$9,0) -> 1031 | F57: =F56+E57 -> 40676 | G57: =MATCH(F57,Progression!$C$5:$C$54,1) -> 21 | H57: =INDEX(Progression!$I$5:$I$54,G57) -> 98 | I57: =IF(G57<Donjon!$B$42,0,MATCH(G57,Donjon!$B$42:$B$53,1)) -> 9 | J57: =J56+ROUND(IF(I57=0,0,$B$10*Parametres!$B$63*55*(1+Parametres!$B$64*(I57-1))),0) -> 181775 | K57: =K56+ROUND(IF(I57=0,0,$B$10*(Parametres!$B$65*Parametres!$B$51+Parametres!$B$66)),0) -> 3225
A58: 46 | B58: =ROUND($B$5*(Parametres!$B$5+$B$6*MIN(2,(1+$B$11)^(A58-1))/Parametres!$B$6+$B$7*Parametres!$B$7),0) -> 813 | C58: =1+$B$8*(Parametres!$B$28+Parametres!$B$29+Parametres!$B$30) -> 1.085 | D58: =MIN(1+Parametres!$B$47*A58,1+Parametres!$B$48) -> 1.2 | E58: =ROUND(B58*C58*D58*$B$9,0) -> 1037 | F58: =F57+E58 -> 41713 | G58: =MATCH(F58,Progression!$C$5:$C$54,1) -> 21 | H58: =INDEX(Progression!$I$5:$I$54,G58) -> 98 | I58: =IF(G58<Donjon!$B$42,0,MATCH(G58,Donjon!$B$42:$B$53,1)) -> 9 | J58: =J57+ROUND(IF(I58=0,0,$B$10*Parametres!$B$63*55*(1+Parametres!$B$64*(I58-1))),0) -> 186725 | K58: =K57+ROUND(IF(I58=0,0,$B$10*(Parametres!$B$65*Parametres!$B$51+Parametres!$B$66)),0) -> 3300
A59: 47 | B59: =ROUND($B$5*(Parametres!$B$5+$B$6*MIN(2,(1+$B$11)^(A59-1))/Parametres!$B$6+$B$7*Parametres!$B$7),0) -> 817 | C59: =1+$B$8*(Parametres!$B$28+Parametres!$B$29+Parametres!$B$30) -> 1.085 | D59: =MIN(1+Parametres!$B$47*A59,1+Parametres!$B$48) -> 1.2 | E59: =ROUND(B59*C59*D59*$B$9,0) -> 1042 | F59: =F58+E59 -> 42755 | G59: =MATCH(F59,Progression!$C$5:$C$54,1) -> 21 | H59: =INDEX(Progression!$I$5:$I$54,G59) -> 98 | I59: =IF(G59<Donjon!$B$42,0,MATCH(G59,Donjon!$B$42:$B$53,1)) -> 9 | J59: =J58+ROUND(IF(I59=0,0,$B$10*Parametres!$B$63*55*(1+Parametres!$B$64*(I59-1))),0) -> 191675 | K59: =K58+ROUND(IF(I59=0,0,$B$10*(Parametres!$B$65*Parametres!$B$51+Parametres!$B$66)),0) -> 3375
A60: 48 | B60: =ROUND($B$5*(Parametres!$B$5+$B$6*MIN(2,(1+$B$11)^(A60-1))/Parametres!$B$6+$B$7*Parametres!$B$7),0) -> 822 | C60: =1+$B$8*(Parametres!$B$28+Parametres!$B$29+Parametres!$B$30) -> 1.085 | D60: =MIN(1+Parametres!$B$47*A60,1+Parametres!$B$48) -> 1.2 | E60: =ROUND(B60*C60*D60*$B$9,0) -> 1049 | F60: =F59+E60 -> 43804 | G60: =MATCH(F60,Progression!$C$5:$C$54,1) -> 22 | H60: =INDEX(Progression!$I$5:$I$54,G60) -> 105 | I60: =IF(G60<Donjon!$B$42,0,MATCH(G60,Donjon!$B$42:$B$53,1)) -> 9 | J60: =J59+ROUND(IF(I60=0,0,$B$10*Parametres!$B$63*55*(1+Parametres!$B$64*(I60-1))),0) -> 196625 | K60: =K59+ROUND(IF(I60=0,0,$B$10*(Parametres!$B$65*Parametres!$B$51+Parametres!$B$66)),0) -> 3450
A61: 49 | B61: =ROUND($B$5*(Parametres!$B$5+$B$6*MIN(2,(1+$B$11)^(A61-1))/Parametres!$B$6+$B$7*Parametres!$B$7),0) -> 826 | C61: =1+$B$8*(Parametres!$B$28+Parametres!$B$29+Parametres!$B$30) -> 1.085 | D61: =MIN(1+Parametres!$B$47*A61,1+Parametres!$B$48) -> 1.2 | E61: =ROUND(B61*C61*D61*$B$9,0) -> 1054 | F61: =F60+E61 -> 44858 | G61: =MATCH(F61,Progression!$C$5:$C$54,1) -> 22 | H61: =INDEX(Progression!$I$5:$I$54,G61) -> 105 | I61: =IF(G61<Donjon!$B$42,0,MATCH(G61,Donjon!$B$42:$B$53,1)) -> 9 | J61: =J60+ROUND(IF(I61=0,0,$B$10*Parametres!$B$63*55*(1+Parametres!$B$64*(I61-1))),0) -> 201575 | K61: =K60+ROUND(IF(I61=0,0,$B$10*(Parametres!$B$65*Parametres!$B$51+Parametres!$B$66)),0) -> 3525
A62: 50 | B62: =ROUND($B$5*(Parametres!$B$5+$B$6*MIN(2,(1+$B$11)^(A62-1))/Parametres!$B$6+$B$7*Parametres!$B$7),0) -> 831 | C62: =1+$B$8*(Parametres!$B$28+Parametres!$B$29+Parametres!$B$30) -> 1.085 | D62: =MIN(1+Parametres!$B$47*A62,1+Parametres!$B$48) -> 1.2 | E62: =ROUND(B62*C62*D62*$B$9,0) -> 1060 | F62: =F61+E62 -> 45918 | G62: =MATCH(F62,Progression!$C$5:$C$54,1) -> 22 | H62: =INDEX(Progression!$I$5:$I$54,G62) -> 105 | I62: =IF(G62<Donjon!$B$42,0,MATCH(G62,Donjon!$B$42:$B$53,1)) -> 9 | J62: =J61+ROUND(IF(I62=0,0,$B$10*Parametres!$B$63*55*(1+Parametres!$B$64*(I62-1))),0) -> 206525 | K62: =K61+ROUND(IF(I62=0,0,$B$10*(Parametres!$B$65*Parametres!$B$51+Parametres!$B$66)),0) -> 3600
A63: 51 | B63: =ROUND($B$5*(Parametres!$B$5+$B$6*MIN(2,(1+$B$11)^(A63-1))/Parametres!$B$6+$B$7*Parametres!$B$7),0) -> 836 | C63: =1+$B$8*(Parametres!$B$28+Parametres!$B$29+Parametres!$B$30) -> 1.085 | D63: =MIN(1+Parametres!$B$47*A63,1+Parametres!$B$48) -> 1.2 | E63: =ROUND(B63*C63*D63*$B$9,0) -> 1067 | F63: =F62+E63 -> 46985 | G63: =MATCH(F63,Progression!$C$5:$C$54,1) -> 22 | H63: =INDEX(Progression!$I$5:$I$54,G63) -> 105 | I63: =IF(G63<Donjon!$B$42,0,MATCH(G63,Donjon!$B$42:$B$53,1)) -> 9 | J63: =J62+ROUND(IF(I63=0,0,$B$10*Parametres!$B$63*55*(1+Parametres!$B$64*(I63-1))),0) -> 211475 | K63: =K62+ROUND(IF(I63=0,0,$B$10*(Parametres!$B$65*Parametres!$B$51+Parametres!$B$66)),0) -> 3675
A64: 52 | B64: =ROUND($B$5*(Parametres!$B$5+$B$6*MIN(2,(1+$B$11)^(A64-1))/Parametres!$B$6+$B$7*Parametres!$B$7),0) -> 841 | C64: =1+$B$8*(Parametres!$B$28+Parametres!$B$29+Parametres!$B$30) -> 1.085 | D64: =MIN(1+Parametres!$B$47*A64,1+Parametres!$B$48) -> 1.2 | E64: =ROUND(B64*C64*D64*$B$9,0) -> 1073 | F64: =F63+E64 -> 48058 | G64: =MATCH(F64,Progression!$C$5:$C$54,1) -> 23 | H64: =INDEX(Progression!$I$5:$I$54,G64) -> 112 | I64: =IF(G64<Donjon!$B$42,0,MATCH(G64,Donjon!$B$42:$B$53,1)) -> 9 | J64: =J63+ROUND(IF(I64=0,0,$B$10*Parametres!$B$63*55*(1+Parametres!$B$64*(I64-1))),0) -> 216425 | K64: =K63+ROUND(IF(I64=0,0,$B$10*(Parametres!$B$65*Parametres!$B$51+Parametres!$B$66)),0) -> 3750 | L64: 1 an
